Workbook
Name UPDATE: 'Data Sheet'!$E$1

Sheet HistoricalFS
B2: ="Historical Financials Statements - "&'Data Sheet'!B1 -> Historical Financials Statements - ASIAN PAINTS LTD
B3: Years | C3: ='[1]Data Sheet'!B16 -> 42460 | D3: ='[1]Data Sheet'!C16 -> 42825 | E3: ='[1]Data Sheet'!D16 -> 43190 | F3: ='[1]Data Sheet'!E16 -> 43555 | G3: ='[1]Data Sheet'!F16 -> 43921 | H3: ='[1]Data Sheet'!G16 -> 44286 | I3: ='[1]Data Sheet'!H16 -> 44651 | J3: ='[1]Data Sheet'!I16 -> 45016 | ... L3: ='[1]Data Sheet'!K16 -> 45747
A5: # | B5: Income Statement
B6: Sales | C6: =IFERROR('Data Sheet'!B17,0) -> 14271.49 | D6: =IFERROR('Data Sheet'!C17,0) -> 15061.99 | E6: =IFERROR('Data Sheet'!D17,0) -> 16824.55 | F6: =IFERROR('Data Sheet'!E17,0) -> 19240.13 | G6: =IFERROR('Data Sheet'!F17,0) -> 20211.25 | H6: =IFERROR('Data Sheet'!G17,0) -> 21712.79 | I6: =IFERROR('Data Sheet'!H17,0) -> 29101.28 | J6: =IFERROR('Data Sheet'!I17,0) -> 34488.59 | ... L6: =IFERROR('Data Sheet'!K17,0) -> 33905.62
B7: Sales Growth % | C7: - | D7: =D6/C6-1 -> 0.055390152 | E7: =E6/D6-1 -> 0.11702039 | F7: =F6/E6-1 -> 0.14357472 | G7: =G6/F6-1 -> 0.050473671 | H7: =H6/G6-1 -> 0.074292288 | I7: =I6/H6-1 -> 0.34028285 | J7: =J6/I6-1 -> 0.18512278 | K7: =K6/J6-1 -> 0.029173127 | L7: =L6/K6-1 -> -0.044770308
B9: COGS | C9: =IFERROR(SUM('Data Sheet'!B18,'Data Sheet'!B20:B22)-1*'Data Sheet'!B19,0) -> 9413.84 | D9: =IFERROR(SUM('Data Sheet'!C18,'Data Sheet'!C20:C22)-1*'Data Sheet'!C19,0) -> 9732.66 | E9: =IFERROR(SUM('Data Sheet'!D18,'Data Sheet'!D20:D22)-1*'Data Sheet'!D19,0) -> 11194.17 | F9: =IFERROR(SUM('Data Sheet'!E18,'Data Sheet'!E20:E22)-1*'Data Sheet'!E19,0) -> 12905.81 | G9: =IFERROR(SUM('Data Sheet'!F18,'Data Sheet'!F20:F22)-1*'Data Sheet'!F19,0) -> 13158.02 | H9: =IFERROR(SUM('Data Sheet'!G18,'Data Sheet'!G20:G22)-1*'Data Sheet'!G19,0) -> 14035.07 | I9: =IFERROR(SUM('Data Sheet'!H18,'Data Sheet'!H20:H22)-1*'Data Sheet'!H19,0) -> 20590.57 | J9: =IFERROR(SUM('Data Sheet'!I18,'Data Sheet'!I20:I22)-1*'Data Sheet'!I19,0) -> 23766.7 | ... L9: =IFERROR(SUM('Data Sheet'!K18,'Data Sheet'!K20:K22)-1*'Data Sheet'!K19,0) -> 22741.27
B10: COGS % of Sales | C10: =C9/C6 -> 0.65962559 | D10: =D9/D6 -> 0.64617358 | E10: =E9/E6 -> 0.66534736 | F10: =F9/F6 -> 0.67077561 | G10: =G9/G6 -> 0.65102455 | H10: =H9/H6 -> 0.64639643 | I10: =I9/I6 -> 0.7075486 | J10: =J9/J6 -> 0.68911776 | ... L10: =L9/L6 -> 0.67072273
B12: Gross Profit | C12: =C6-C9 -> 4857.65 | D12: =D6-D9 -> 5329.33 | E12: =E6-E9 -> 5630.38 | F12: =F6-F9 -> 6334.32 | G12: =G6-G9 -> 7053.23 | H12: =H6-H9 -> 7677.72 | I12: =I6-I9 -> 8510.71 | J12: =J6-J9 -> 10721.89 | ... L12: =L6-L9 -> 11164.35
B13: Gross Margins | C13: =C12/C6 -> 0.34037441 | D13: =D12/D6 -> 0.35382642 | E13: =E12/E6 -> 0.33465264 | F13: =F12/F6 -> 0.32922439 | G13: =G12/G6 -> 0.34897545 | H13: =H12/H6 -> 0.35360357 | I13: =I12/I6 -> 0.2924514 | J13: =J12/J6 -> 0.31088224 | ... L13: =L12/L6 -> 0.32927727
B15: Selling & General Expenses | C15: =IFERROR(SUM('Data Sheet'!B23:B24),0) -> 2132.61 | D15: =IFERROR(SUM('Data Sheet'!C23:C24),0) -> 2335.57 | E15: =IFERROR(SUM('Data Sheet'!D23:D24),0) -> 2426.37 | F15: =IFERROR(SUM('Data Sheet'!E23:E24),0) -> 2569.38 | G15: =IFERROR(SUM('Data Sheet'!F23:F24),0) -> 2896.41 | H15: =IFERROR(SUM('Data Sheet'!G23:G24),0) -> 2822.12 | I15: =IFERROR(SUM('Data Sheet'!H23:H24),0) -> 3707.1 | J15: =IFERROR(SUM('Data Sheet'!I23:I24),0) -> 4462.05 | ... L15: =IFERROR(SUM('Data Sheet'!K23:K24),0) -> 5158.14
B16: S&G Exp % of Sales | C16: =C15/C6 -> 0.14943149 | D16: =D15/D6 -> 0.15506384 | E16: =E15/E6 -> 0.14421604 | F16: =F15/F6 -> 0.13354276 | G16: =G15/G6 -> 0.14330682 | H16: =H15/H6 -> 0.12997501 | I16: =I15/I6 -> 0.12738615 | J16: =J15/J6 -> 0.12937757 | ... L16: =L15/L6 -> 0.1521323
B18: EBITDA | C18: =C12-C15 -> 2725.04 | D18: =D12-D15 -> 2993.76 | E18: =E12-E15 -> 3204.01 | F18: =F12-F15 -> 3764.94 | G18: =G12-G15 -> 4156.82 | H18: =H12-H15 -> 4855.6 | I18: =I12-I15 -> 4803.61 | J18: =J12-J15 -> 6259.84 | ... L18: =L12-L15 -> 6006.21
B19: EBITDA % of Sales | C19: =C18/C6 -> 0.19094292 | D19: =D18/D6 -> 0.19876258 | E19: =E18/E6 -> 0.19043659 | F19: =F18/F6 -> 0.19568163 | G19: =G18/G6 -> 0.20566863 | H19: =H18/H6 -> 0.22362856 | I19: =I18/I6 -> 0.16506525 | J19: =J18/J6 -> 0.18150467 | ... L19: =L18/L6 -> 0.17714497
B21: Interest | C21: =IFERROR('Data Sheet'!B27,0) -> 49 | D21: =IFERROR('Data Sheet'!C27,0) -> 37.33 | E21: =IFERROR('Data Sheet'!D27,0) -> 41.47 | F21: =IFERROR('Data Sheet'!E27,0) -> 110.47 | G21: =IFERROR('Data Sheet'!F27,0) -> 102.33 | H21: =IFERROR('Data Sheet'!G27,0) -> 91.63 | I21: =IFERROR('Data Sheet'!H27,0) -> 95.41 | J21: =IFERROR('Data Sheet'!I27,0) -> 144.45 | ... L21: =IFERROR('Data Sheet'!K27,0) -> 227.02
B22: Interest % of Sales | C22: =C21/C6 -> 0.0034334187 | D22: =D21/D6 -> 0.0024784242 | E22: =E21/E6 -> 0.0024648505 | F22: =F21/F6 -> 0.0057416452 | G22: =G21/G6 -> 0.0050630218 | H22: =H21/H6 -> 0.0042200933 | I22: =I21/I6 -> 0.0032785499 | J22: =J21/J6 -> 0.0041883417 | ... L22: =L21/L6 -> 0.0066956451
B24: Depriciation | C24: =IFERROR('Data Sheet'!B26,0) -> 275.58 | D24: =IFERROR('Data Sheet'!C26,0) -> 334.79 | E24: =IFERROR('Data Sheet'!D26,0) -> 360.47 | F24: =IFERROR('Data Sheet'!E26,0) -> 622.14 | G24: =IFERROR('Data Sheet'!F26,0) -> 780.5 | H24: =IFERROR('Data Sheet'!G26,0) -> 791.27 | I24: =IFERROR('Data Sheet'!H26,0) -> 816.36 | J24: =IFERROR('Data Sheet'!I26,0) -> 858.02 | ... L24: =IFERROR('Data Sheet'!K26,0) -> 1026.34
B25: Depriciation % of Sales | C25: =C24/C6 -> 0.019309827 | D25: =D24/D6 -> 0.022227475 | E25: =E24/E6 -> 0.021425239 | F25: =F24/F6 -> 0.03233554 | G25: =G24/G6 -> 0.038617107 | H25: =H24/H6 -> 0.036442576 | I25: =I24/I6 -> 0.028052374 | J25: =J24/J6 -> 0.024878373 | ... L25: =L24/L6 -> 0.030270498
B27: EBIT | C27: =C18-C24 -> 2449.46 | D27: =D18-D24 -> 2658.97 | E27: =E18-E24 -> 2843.54 | F27: =F18-F24 -> 3142.8 | G27: =G18-G24 -> 3376.32 | H27: =H18-H24 -> 4064.33 | I27: =I18-I24 -> 3987.25 | J27: =J18-J24 -> 5401.82 | ... L27: =L18-L24 -> 4979.87
B28: EBIT % of Sales | C28: =IFERROR(C27/C6,0) -> 0.1716331 | D28: =IFERROR(D27/D6,0) -> 0.17653511 | E28: =IFERROR(E27/E6,0) -> 0.16901136 | F28: =IFERROR(F27/F6,0) -> 0.16334609 | G28: =IFERROR(G27/G6,0) -> 0.16705152 | H28: =IFERROR(H27/H6,0) -> 0.18718599 | I28: =IFERROR(I27/I6,0) -> 0.13701287 | J28: =IFERROR(J27/J6,0) -> 0.15662629 | ... L28: =IFERROR(L27/L6,0) -> 0.14687447
B30: EBT | C30: =IFERROR(C18-SUM(C21,C24),0) -> 2400.46 | D30: =IFERROR(D18-SUM(D21,D24),0) -> 2621.64 | E30: =IFERROR(E18-SUM(E21,E24),0) -> 2802.07 | F30: =IFERROR(F18-SUM(F21,F24),0) -> 3032.33 | G30: =IFERROR(G18-SUM(G21,G24),0) -> 3273.99 | H30: =IFERROR(H18-SUM(H21,H24),0) -> 3972.7 | I30: =IFERROR(I18-SUM(I21,I24),0) -> 3891.84 | J30: =IFERROR(J18-SUM(J21,J24),0) -> 5257.37 | ... L30: =IFERROR(L18-SUM(L21,L24),0) -> 4752.85
B31: EBT % of Sales | C31: =C30/C6 -> 0.16819968 | D31: =D30/D6 -> 0.17405668 | E31: =E30/E6 -> 0.1665465 | F31: =F30/F6 -> 0.15760444 | G31: =G30/G6 -> 0.1619885 | H31: =H30/H6 -> 0.18296589 | I31: =I30/I6 -> 0.13373432 | J31: =J30/J6 -> 0.15243795 | ... L31: =L30/L6 -> 0.14017883
B33: Tax | C33: =IFERROR('Data Sheet'!B29,0) -> 844.49 | D33: =IFERROR('Data Sheet'!C29,0) -> 943.29 | E33: =IFERROR('Data Sheet'!D29,0) -> 1040.96 | F33: =IFERROR('Data Sheet'!E29,0) -> 1098.06 | G33: =IFERROR('Data Sheet'!F29,0) -> 854.85 | H33: =IFERROR('Data Sheet'!G29,0) -> 1097.6 | I33: =IFERROR('Data Sheet'!H29,0) -> 1102.91 | J33: =IFERROR('Data Sheet'!I29,0) -> 1493.5 | ... L33: =IFERROR('Data Sheet'!K29,0) -> 1393.36
B34: Effective Tax Rate | C34: =C33/C30 -> 0.3518034 | D34: =D33/D30 -> 0.35980913 | E34: =E33/E30 -> 0.37149679 | F34: =F33/F30 -> 0.36211758 | G34: =G33/G30 -> 0.26110342 | H34: =H33/H30 -> 0.27628565 | I34: =I33/I30 -> 0.28339038 | J34: =J33/J30 -> 0.2840774 | ... L34: =L33/L30 -> 0.29316305
B36: Net Profit | C36: =C30-C33 -> 1555.97 | D36: =D30-D33 -> 1678.35 | E36: =E30-E33 -> 1761.11 | F36: =F30-F33 -> 1934.27 | G36: =G30-G33 -> 2419.14 | H36: =H30-H33 -> 2875.1 | I36: =I30-I33 -> 2788.93 | J36: =J30-J33 -> 3763.87 | ... L36: =L30-L33 -> 3359.49
B37: Net Margins | C37: =C36/C6 -> 0.10902646 | D37: =D36/D6 -> 0.1114295 | E37: =E36/E6 -> 0.10467501 | F37: =F36/F6 -> 0.1005331 | G37: =G36/G6 -> 0.11969275 | H37: =H36/H6 -> 0.13241504 | I37: =I36/I6 -> 0.095835303 | J37: =J36/J6 -> 0.10913377 | ... L37: =L36/L6 -> 0.099083574
B39: No. of Equity Shares | C39: =IFERROR('Data Sheet'!B93,0) -> 95.92 | D39: =IFERROR('Data Sheet'!C93,0) -> 95.92 | E39: =IFERROR('Data Sheet'!D93,0) -> 95.92 | F39: =IFERROR('Data Sheet'!E93,0) -> 95.92 | G39: =IFERROR('Data Sheet'!F93,0) -> 95.92 | H39: =IFERROR('Data Sheet'!G93,0) -> 95.92 | I39: =IFERROR('Data Sheet'!H93,0) -> 95.92 | J39: =IFERROR('Data Sheet'!I93,0) -> 95.92 | ... L39: =IFERROR('Data Sheet'!K93,0) -> 95.92
B41: EPS | C41: =IFERROR(C36/C39,0) -> 16.221539 | D41: =IFERROR(D36/D39,0) -> 17.497394 | E41: =IFERROR(E36/E39,0) -> 18.360196 | F41: =IFERROR(F36/F39,0) -> 20.16545 | G41: =IFERROR(G36/G39,0) -> 25.220392 | H41: =IFERROR(H36/H39,0) -> 29.973937 | I41: =IFERROR(I36/I39,0) -> 29.075584 | J41: =IFERROR(J36/J39,0) -> 39.239679 | ... L41: =IFERROR(L36/L39,0) -> 35.023874
B42: EPS Growth % | C42: - | D42: =IFERROR(D41/C41,0) -> 1.0786519 | E42: =IFERROR(E41/D41,0) -> 1.0493103 | F42: =IFERROR(F41/E41,0) -> 1.0983244 | G42: =IFERROR(G41/F41,0) -> 1.2506734 | H42: =IFERROR(H41/G41,0) -> 1.1884802 | I42: =IFERROR(I41/H41,0) -> 0.97002887 | J42: =IFERROR(J41/I41,0) -> 1.3495749 | K42: =IFERROR(K41/J41,0) -> 1.2584733 | L42: =IFERROR(L41/K41,0) -> 0.70924245
B44: Divided per Share | C44: =IFERROR('Data Sheet'!B31/HistoricalFS!C39,0) -> 7.5 | D44: =IFERROR('Data Sheet'!C31/HistoricalFS!D39,0) -> 10.300042 | E44: =IFERROR('Data Sheet'!D31/HistoricalFS!E39,0) -> 8.6999583 | F44: =IFERROR('Data Sheet'!E31/HistoricalFS!F39,0) -> 10.5 | G44: =IFERROR('Data Sheet'!F31/HistoricalFS!G39,0) -> 12 | H44: =IFERROR('Data Sheet'!G31/HistoricalFS!H39,0) -> 17.849979 | I44: =IFERROR('Data Sheet'!H31/HistoricalFS!I39,0) -> 19.150021 | J44: =IFERROR('Data Sheet'!I31/HistoricalFS!J39,0) -> 25.650021 | ... L44: =IFERROR('Data Sheet'!K31/HistoricalFS!L39,0) -> 24.800042
B45: Dividend Payout Ratio | C45: =IFERROR(C44/C41,0) -> 0.46234825 | D45: =IFERROR(D44/D41,0) -> 0.58866148 | E45: =IFERROR(E44/E41,0) -> 0.47384888 | F45: =IFERROR(F44/F41,0) -> 0.52069256 | G45: =IFERROR(G44/G41,0) -> 0.47580545 | H45: =IFERROR(H44/H41,0) -> 0.59551668 | I45: =IFERROR(I44/I41,0) -> 0.65862894 | J45: =IFERROR(J44/J41,0) -> 0.65367561 | ... L45: =IFERROR(L44/L41,0) -> 0.70808962
B47: Retained Earnings | C47: =IFERROR(IF(C41>C44,1-C45,0),0) -> 0.53765175 | D47: =IFERROR(IF(D41>D44,1-D45,0),0) -> 0.41133852 | E47: =IFERROR(IF(E41>E44,1-E45,0),0) -> 0.52615112 | F47: =IFERROR(IF(F41>F44,1-F45,0),0) -> 0.47930744 | G47: =IFERROR(IF(G41>G44,1-G45,0),0) -> 0.52419455 | H47: =IFERROR(IF(H41>H44,1-H45,0),0) -> 0.40448332 | I47: =IFERROR(IF(I41>I44,1-I45,0),0) -> 0.34137106 | J47: =IFERROR(IF(J41>J44,1-J45,0),0) -> 0.34632439 | ... L47: =IFERROR(IF(L41>L44,1-L45,0),0) -> 0.29191038
A49: # | B49: Balance Sheet
B50: Equity Share Capital | C50: =IFERROR('Data Sheet'!B57,0) -> 95.92 | D50: =IFERROR('Data Sheet'!C57,0) -> 95.92 | E50: =IFERROR('Data Sheet'!D57,0) -> 95.92 | F50: =IFERROR('Data Sheet'!E57,0) -> 95.92 | G50: =IFERROR('Data Sheet'!F57,0) -> 95.92 | H50: =IFERROR('Data Sheet'!G57,0) -> 95.92 | I50: =IFERROR('Data Sheet'!H57,0) -> 95.92 | J50: =IFERROR('Data Sheet'!I57,0) -> 95.92 | ... L50: =IFERROR('Data Sheet'!K57,0) -> 95.92
B51: Reserves | C51: =IFERROR('Data Sheet'!B58,0) -> 6428.9 | D51: =IFERROR('Data Sheet'!C58,0) -> 7507.97 | E51: =IFERROR('Data Sheet'!D58,0) -> 8314.31 | F51: =IFERROR('Data Sheet'!E58,0) -> 9374.63 | G51: =IFERROR('Data Sheet'!F58,0) -> 10034.24 | H51: =IFERROR('Data Sheet'!G58,0) -> 12710.37 | I51: =IFERROR('Data Sheet'!H58,0) -> 13715.64 | J51: =IFERROR('Data Sheet'!I58,0) -> 15896.31 | ... L51: =IFERROR('Data Sheet'!K58,0) -> 19303.89
B52: Borrowings | C52: =IFERROR('Data Sheet'!B59,0) -> 323.29 | D52: =IFERROR('Data Sheet'!C59,0) -> 560.34 | E52: =IFERROR('Data Sheet'!D59,0) -> 533.43 | F52: =IFERROR('Data Sheet'!E59,0) -> 1319.6 | G52: =IFERROR('Data Sheet'!F59,0) -> 1118.5 | H52: =IFERROR('Data Sheet'!G59,0) -> 1093.12 | I52: =IFERROR('Data Sheet'!H59,0) -> 1586.88 | J52: =IFERROR('Data Sheet'!I59,0) -> 1932.62 | ... L52: =IFERROR('Data Sheet'!K59,0) -> 2290.29
B53: Other Liabilities | C53: =IFERROR('Data Sheet'!B60,0) -> 3710.92 | D53: =IFERROR('Data Sheet'!C60,0) -> 4240.96 | E53: =IFERROR('Data Sheet'!D60,0) -> 4819.82 | F53: =IFERROR('Data Sheet'!E60,0) -> 5458.69 | G53: =IFERROR('Data Sheet'!F60,0) -> 4889.31 | H53: =IFERROR('Data Sheet'!G60,0) -> 6455.93 | I53: =IFERROR('Data Sheet'!H60,0) -> 7559.99 | J53: =IFERROR('Data Sheet'!I60,0) -> 7854.48 | ... L53: =IFERROR('Data Sheet'!K60,0) -> 8665.15
B54: Total Liabilities | C54: =SUM(C50:C53) -> 10559.03 | D54: =SUM(D50:D53) -> 12405.19 | E54: =SUM(E50:E53) -> 13763.48 | F54: =SUM(F50:F53) -> 16248.84 | G54: =SUM(G50:G53) -> 16137.97 | H54: =SUM(H50:H53) -> 20355.34 | I54: =SUM(I50:I53) -> 22958.43 | J54: =SUM(J50:J53) -> 25779.33 | ... L54: =SUM(L50:L53) -> 30355.25
B56: Fixed Assets Net Block | C56: =IFERROR('Data Sheet'!B62,0) -> 3416.35 | D56: =IFERROR('Data Sheet'!C62,0) -> 3303.74 | E56: =IFERROR('Data Sheet'!D62,0) -> 3732.24 | F56: =IFERROR('Data Sheet'!E62,0) -> 6496.56 | G56: =IFERROR('Data Sheet'!F62,0) -> 6272.31 | H56: =IFERROR('Data Sheet'!G62,0) -> 5858.52 | I56: =IFERROR('Data Sheet'!H62,0) -> 5519.06 | J56: =IFERROR('Data Sheet'!I62,0) -> 5770.46 | ... L56: =IFERROR('Data Sheet'!K62,0) -> 9220.1
B57: Capital Work in Progress | C57: =IFERROR('Data Sheet'!B63,0) -> 106.59 | D57: =IFERROR('Data Sheet'!C63,0) -> 257.54 | E57: =IFERROR('Data Sheet'!D63,0) -> 1405.11 | F57: =IFERROR('Data Sheet'!E63,0) -> 209.67 | G57: =IFERROR('Data Sheet'!F63,0) -> 140.24 | H57: =IFERROR('Data Sheet'!G63,0) -> 182.98 | I57: =IFERROR('Data Sheet'!H63,0) -> 426.43 | J57: =IFERROR('Data Sheet'!I63,0) -> 1019.59 | ... L57: =IFERROR('Data Sheet'!K63,0) -> 1254.49
B58: Investments | C58: =IFERROR('Data Sheet'!B64,0) -> 2712.13 | D58: =IFERROR('Data Sheet'!C64,0) -> 2651.99 | E58: =IFERROR('Data Sheet'!D64,0) -> 2140.7 | F58: =IFERROR('Data Sheet'!E64,0) -> 2568.58 | G58: =IFERROR('Data Sheet'!F64,0) -> 2018.85 | H58: =IFERROR('Data Sheet'!G64,0) -> 4736.8 | I58: =IFERROR('Data Sheet'!H64,0) -> 3247.53 | J58: =IFERROR('Data Sheet'!I64,0) -> 4261.71 | ... L58: =IFERROR('Data Sheet'!K64,0) -> 4724.75
B59: Other Assets | C59: =IFERROR('Data Sheet'!B65-SUM('Data Sheet'!B67:B69),0) -> 714.68 | D59: =IFERROR('Data Sheet'!C65-SUM('Data Sheet'!C67:C69),0) -> 1317.17 | E59: =IFERROR('Data Sheet'!D65-SUM('Data Sheet'!D67:D69),0) -> 1691.84 | F59: =IFERROR('Data Sheet'!E65-SUM('Data Sheet'!E67:E69),0) -> 1471.96 | G59: =IFERROR('Data Sheet'!F65-SUM('Data Sheet'!F67:F69),0) -> 1738.71 | H59: =IFERROR('Data Sheet'!G65-SUM('Data Sheet'!G67:G69),0) -> 2565.52 | I59: =IFERROR('Data Sheet'!H65-SUM('Data Sheet'!H67:H69),0) -> 2876.66 | J59: =IFERROR('Data Sheet'!I65-SUM('Data Sheet'!I67:I69),0) -> 3036.17 | ... L59: =IFERROR('Data Sheet'!K65-SUM('Data Sheet'!K67:K69),0) -> 3341.01
B60: Total Non-Current Assets | C60: =SUM(C56:C59) -> 6949.75 | D60: =SUM(D56:D59) -> 7530.44 | E60: =SUM(E56:E59) -> 8969.89 | F60: =SUM(F56:F59) -> 10746.77 | G60: =SUM(G56:G59) -> 10170.11 | H60: =SUM(H56:H59) -> 13343.82 | I60: =SUM(I56:I59) -> 12069.68 | J60: =SUM(J56:J59) -> 14087.93 | ... L60: =SUM(L56:L59) -> 18540.35
B62: Receivables | C62: =IFERROR('Data Sheet'!B67,0) -> 1186.84 | D62: =IFERROR('Data Sheet'!C67,0) -> 1446.6 | E62: =IFERROR('Data Sheet'!D67,0) -> 1730.63 | F62: =IFERROR('Data Sheet'!E67,0) -> 1907.33 | G62: =IFERROR('Data Sheet'!F67,0) -> 1795.22 | H62: =IFERROR('Data Sheet'!G67,0) -> 2602.17 | I62: =IFERROR('Data Sheet'!H67,0) -> 3871.44 | J62: =IFERROR('Data Sheet'!I67,0) -> 4636.94 | ... L62: =IFERROR('Data Sheet'!K67,0) -> 4313.65
B63: Inventory | C63: =IFERROR('Data Sheet'!B68,0) -> 1998.24 | D63: =IFERROR('Data Sheet'!C68,0) -> 2626.94 | E63: =IFERROR('Data Sheet'!D68,0) -> 2658.31 | F63: =IFERROR('Data Sheet'!E68,0) -> 3149.86 | G63: =IFERROR('Data Sheet'!F68,0) -> 3389.81 | H63: =IFERROR('Data Sheet'!G68,0) -> 3798.6 | I63: =IFERROR('Data Sheet'!H68,0) -> 6152.98 | J63: =IFERROR('Data Sheet'!I68,0) -> 6210.64 | ... L63: =IFERROR('Data Sheet'!K68,0) -> 6719.27
B64: Cash & Bank | C64: =IFERROR('Data Sheet'!B69,0) -> 424.2 | D64: =IFERROR('Data Sheet'!C69,0) -> 801.21 | E64: =IFERROR('Data Sheet'!D69,0) -> 404.65 | F64: =IFERROR('Data Sheet'!E69,0) -> 444.88 | G64: =IFERROR('Data Sheet'!F69,0) -> 782.83 | H64: =IFERROR('Data Sheet'!G69,0) -> 610.75 | I64: =IFERROR('Data Sheet'!H69,0) -> 864.33 | J64: =IFERROR('Data Sheet'!I69,0) -> 843.82 | ... L64: =IFERROR('Data Sheet'!K69,0) -> 781.98
B65: Total Current Assets | C65: =SUM(C62:C64) -> 3609.28 | D65: =SUM(D62:D64) -> 4874.75 | E65: =SUM(E62:E64) -> 4793.59 | F65: =SUM(F62:F64) -> 5502.07 | G65: =SUM(G62:G64) -> 5967.86 | H65: =SUM(H62:H64) -> 7011.52 | I65: =SUM(I62:I64) -> 10888.75 | J65: =SUM(J62:J64) -> 11691.4 | ... L65: =SUM(L62:L64) -> 11814.9
B67: Total Assets | C67: =SUM(C65,C60) -> 10559.03 | D67: =SUM(D65,D60) -> 12405.19 | E67: =SUM(E65,E60) -> 13763.48 | F67: =SUM(F65,F60) -> 16248.84 | G67: =SUM(G65,G60) -> 16137.97 | H67: =SUM(H65,H60) -> 20355.34 | I67: =SUM(I65,I60) -> 22958.43 | J67: =SUM(J65,J60) -> 25779.33 | ... L67: =SUM(L65,L60) -> 30355.25
B69: Check | C69: =C67=C54 -> TRUE | D69: =D67=D54 -> TRUE | E69: =E67=E54 -> TRUE | F69: =F67=F54 -> TRUE | G69: =G67=G54 -> TRUE | H69: =H67=H54 -> TRUE | I69: =I67=I54 -> TRUE | J69: =J67=J54 -> TRUE | ... L69: =L67=L54 -> TRUE
A71: # | B71: Cash Flows Statement
B73: Cash Flow from Operating Activity | C73: =IFERROR('Data Sheet'!B82,0) -> 2242.95 | D73: =IFERROR('Data Sheet'!C82,0) -> 1527.33 | E73: =IFERROR('Data Sheet'!D82,0) -> 2113.44 | F73: =IFERROR('Data Sheet'!E82,0) -> 2469.54 | G73: =IFERROR('Data Sheet'!F82,0) -> 3038.15 | H73: =IFERROR('Data Sheet'!G82,0) -> 3683.35 | I73: =IFERROR('Data Sheet'!H82,0) -> 986.49 | J73: =IFERROR('Data Sheet'!I82,0) -> 4193.43 | ... L73: =IFERROR('Data Sheet'!K82,0) -> 4423.96
B74: Cash Flow from Investing Activity | C74: =IFERROR('Data Sheet'!B83,0) -> -866.21 | D74: =IFERROR('Data Sheet'!C83,0) -> -681.11 | E74: =IFERROR('Data Sheet'!D83,0) -> -1556.14 | F74: =IFERROR('Data Sheet'!E83,0) -> -917.79 | G74: =IFERROR('Data Sheet'!F83,0) -> -517.91 | H74: =IFERROR('Data Sheet'!G83,0) -> -540.54 | I74: =IFERROR('Data Sheet'!H83,0) -> -316.75 | J74: =IFERROR('Data Sheet'!I83,0) -> -1282.34 | ... L74: =IFERROR('Data Sheet'!K83,0) -> -940.91
B75: Cash Flow from Financing Activity | C75: =IFERROR('Data Sheet'!B84,0) -> -848.98 | D75: =IFERROR('Data Sheet'!C84,0) -> -756.43 | E75: =IFERROR('Data Sheet'!D84,0) -> -1379.14 | F75: =IFERROR('Data Sheet'!E84,0) -> -1117.46 | G75: =IFERROR('Data Sheet'!F84,0) -> -2871.46 | H75: =IFERROR('Data Sheet'!G84,0) -> -650.4 | I75: =IFERROR('Data Sheet'!H84,0) -> -1807.61 | J75: =IFERROR('Data Sheet'!I84,0) -> -2140.05 | ... L75: =IFERROR('Data Sheet'!K84,0) -> -3752.58
B77: Net Cash Flows | C77: =SUM(C73:C75) -> 527.76 | D77: =SUM(D73:D75) -> 89.79 | E77: =SUM(E73:E75) -> -821.84 | F77: =SUM(F73:F75) -> 434.29 | G77: =SUM(G73:G75) -> -351.22 | H77: =SUM(H73:H75) -> 2492.41 | I77: =SUM(I73:I75) -> -1137.87 | J77: =SUM(J73:J75) -> 771.04 | ... L77: =SUM(L73:L75) -> -269.53
A79: # | B79: Cash Flows Statement (Expanded)
B81: Cash Flow from Operating Activity
B82: Profit from operations | C82: =IFERROR('Raw CF'!E4,0) -> 2848 | D82: =IFERROR('Raw CF'!F4,0) -> 3056 | E82: =IFERROR('Raw CF'!G4,0) -> 3274 | F82: =IFERROR('Raw CF'!H4,0) -> 3861 | G82: =IFERROR('Raw CF'!I4,0) -> 4380 | H82: =IFERROR('Raw CF'!J4,0) -> 4970 | I82: =IFERROR('Raw CF'!K4,0) -> 4957 | J82: =IFERROR('Raw CF'!L4,0) -> 6460 | ... L82: =IFERROR('Raw CF'!N4,0) -> 6390
B83: Receivables | C83: =IFERROR('Raw CF'!E5,0) -> -146 | D83: =IFERROR('Raw CF'!F5,0) -> -475 | E83: =IFERROR('Raw CF'!G5,0) -> -483 | F83: =IFERROR('Raw CF'!H5,0) -> -205 | G83: =IFERROR('Raw CF'!I5,0) -> 160 | H83: =IFERROR('Raw CF'!J5,0) -> -849 | I83: =IFERROR('Raw CF'!K5,0) -> -1326 | J83: =IFERROR('Raw CF'!L5,0) -> -834 | ... L83: =IFERROR('Raw CF'!N5,0) -> 282
B84: Inventory | C84: =IFERROR('Raw CF'!E6,0) -> 202 | D84: =IFERROR('Raw CF'!F6,0) -> -629 | E84: =IFERROR('Raw CF'!G6,0) -> -39 | F84: =IFERROR('Raw CF'!H6,0) -> -492 | G84: =IFERROR('Raw CF'!I6,0) -> -251 | H84: =IFERROR('Raw CF'!J6,0) -> -409 | I84: =IFERROR('Raw CF'!K6,0) -> -2354 | J84: =IFERROR('Raw CF'!L6,0) -> -56 | ... L84: =IFERROR('Raw CF'!N6,0) -> -805
B85: Payables | C85: =IFERROR('Raw CF'!E7,0) -> 142 | D85: =IFERROR('Raw CF'!F7,0) -> 501 | E85: =IFERROR('Raw CF'!G7,0) -> 442 | F85: =IFERROR('Raw CF'!H7,0) -> 287 | G85: =IFERROR('Raw CF'!I7,0) -> -241 | H85: =IFERROR('Raw CF'!J7,0) -> 1143 | I85: =IFERROR('Raw CF'!K7,0) -> 644 | J85: =IFERROR('Raw CF'!L7,0) -> -539 | ... L85: =IFERROR('Raw CF'!N7,0) -> -160
B86: Other WC items | C86: =IFERROR('Raw CF'!E8,0) -> 0 | D86: =IFERROR('Raw CF'!F8,0) -> 0 | E86: =IFERROR('Raw CF'!G8,0) -> 0 | F86: =IFERROR('Raw CF'!H8,0) -> 0 | G86: =IFERROR('Raw CF'!I8,0) -> 0 | H86: =IFERROR('Raw CF'!J8,0) -> -92 | I86: =IFERROR('Raw CF'!K8,0) -> 242 | J86: =IFERROR('Raw CF'!L8,0) -> 657 | ... L86: =IFERROR('Raw CF'!N8,0) -> 114
B87: Working capital changes | C87: =IFERROR('Raw CF'!E9,0) -> 198 | D87: =IFERROR('Raw CF'!F9,0) -> -603 | E87: =IFERROR('Raw CF'!G9,0) -> -80 | F87: =IFERROR('Raw CF'!H9,0) -> -410 | G87: =IFERROR('Raw CF'!I9,0) -> -331 | H87: =IFERROR('Raw CF'!J9,0) -> -206 | I87: =IFERROR('Raw CF'!K9,0) -> -2795 | J87: =IFERROR('Raw CF'!L9,0) -> -772 | ... L87: =IFERROR('Raw CF'!N9,0) -> -570
B88: Direct taxes | C88: =IFERROR('Raw CF'!E10,0) -> -802 | D88: =IFERROR('Raw CF'!F10,0) -> -925 | E88: =IFERROR('Raw CF'!G10,0) -> -1081 | F88: =IFERROR('Raw CF'!H10,0) -> -982 | G88: =IFERROR('Raw CF'!I10,0) -> -1011 | H88: =IFERROR('Raw CF'!J10,0) -> -1080 | I88: =IFERROR('Raw CF'!K10,0) -> -1176 | J88: =IFERROR('Raw CF'!L10,0) -> -1494 | ... L88: =IFERROR('Raw CF'!N10,0) -> -1396
B89: Cash Generated from Operations | C89: =IFERROR(SUM(C82:C88),0) -> 2442 | D89: =IFERROR(SUM(D82:D88),0) -> 925 | E89: =IFERROR(SUM(E82:E88),0) -> 2033 | F89: =IFERROR(SUM(F82:F88),0) -> 2059 | G89: =IFERROR(SUM(G82:G88),0) -> 2706 | H89: =IFERROR(SUM(H82:H88),0) -> 3477 | I89: =IFERROR(SUM(I82:I88),0) -> -1808 | J89: =IFERROR(SUM(J82:J88),0) -> 3422 | ... L89: =IFERROR(SUM(L82:L88),0) -> 3855
B91: Cash Flow from Investing Activity
B92: Fixed assets purchased | C92: =IFERROR('Raw CF'!E13,0) -> -817 | D92: =IFERROR('Raw CF'!F13,0) -> -684 | E92: =IFERROR('Raw CF'!G13,0) -> -1426 | F92: =IFERROR('Raw CF'!H13,0) -> -1151 | G92: =IFERROR('Raw CF'!I13,0) -> -404 | H92: =IFERROR('Raw CF'!J13,0) -> -282 | I92: =IFERROR('Raw CF'!K13,0) -> -551 | J92: =IFERROR('Raw CF'!L13,0) -> -1446 | ... L92: =IFERROR('Raw CF'!N13,0) -> -1830
B93: Fixed assets sold | C93: =IFERROR('Raw CF'!E14,0) -> 15 | D93: =IFERROR('Raw CF'!F14,0) -> 17 | E93: =IFERROR('Raw CF'!G14,0) -> 17 | F93: =IFERROR('Raw CF'!H14,0) -> 17 | G93: =IFERROR('Raw CF'!I14,0) -> 37 | H93: =IFERROR('Raw CF'!J14,0) -> 28 | I93: =IFERROR('Raw CF'!K14,0) -> 40 | J93: =IFERROR('Raw CF'!L14,0) -> 26 | ... L93: =IFERROR('Raw CF'!N14,0) -> 10
B94: Investments purchased | C94: =IFERROR('Raw CF'!E15,0) -> -282 | D94: =IFERROR('Raw CF'!F15,0) -> -153 | E94: =IFERROR('Raw CF'!G15,0) -> -320 | F94: =IFERROR('Raw CF'!H15,0) -> -573 | G94: =IFERROR('Raw CF'!I15,0) -> -25 | H94: =IFERROR('Raw CF'!J15,0) -> -140 | I94: =IFERROR('Raw CF'!K15,0) -> 0 | J94: =IFERROR('Raw CF'!L15,0) -> -146 | ... L94: =IFERROR('Raw CF'!N15,0) -> -1
B95: Investments sold | C95: =IFERROR('Raw CF'!E16,0) -> 205 | D95: =IFERROR('Raw CF'!F16,0) -> 357 | E95: =IFERROR('Raw CF'!G16,0) -> 362 | F95: =IFERROR('Raw CF'!H16,0) -> 733 | G95: =IFERROR('Raw CF'!I16,0) -> 134 | H95: =IFERROR('Raw CF'!J16,0) -> 272 | I95: =IFERROR('Raw CF'!K16,0) -> 207 | J95: =IFERROR('Raw CF'!L16,0) -> 446 | ... L95: =IFERROR('Raw CF'!N16,0) -> 421
B96: Interest received | C96: =IFERROR('Raw CF'!E17,0) -> 15 | D96: =IFERROR('Raw CF'!F17,0) -> 32 | E96: =IFERROR('Raw CF'!G17,0) -> 39 | F96: =IFERROR('Raw CF'!H17,0) -> 40 | G96: =IFERROR('Raw CF'!I17,0) -> 65 | H96: =IFERROR('Raw CF'!J17,0) -> 73 | I96: =IFERROR('Raw CF'!K17,0) -> 77 | J96: =IFERROR('Raw CF'!L17,0) -> 87 | ... L96: =IFERROR('Raw CF'!N17,0) -> 155
B97: Dividends received | C97: =IFERROR('Raw CF'!E18,0) -> 69 | D97: =IFERROR('Raw CF'!F18,0) -> 74 | E97: =IFERROR('Raw CF'!G18,0) -> 38 | F97: =IFERROR('Raw CF'!H18,0) -> 40 | G97: =IFERROR('Raw CF'!I18,0) -> 27 | H97: =IFERROR('Raw CF'!J18,0) -> 8 | I97: =IFERROR('Raw CF'!K18,0) -> 15 | J97: =IFERROR('Raw CF'!L18,0) -> 56 | ... L97: =IFERROR('Raw CF'!N18,0) -> 136
B98: Investment in group cos | C98: =IFERROR('Raw CF'!E19,0) -> 0 | D98: =IFERROR('Raw CF'!F19,0) -> 0 | E98: =IFERROR('Raw CF'!G19,0) -> 0 | F98: =IFERROR('Raw CF'!H19,0) -> 0 | G98: =IFERROR('Raw CF'!I19,0) -> 0 | H98: =IFERROR('Raw CF'!J19,0) -> 0 | I98: =IFERROR('Raw CF'!K19,0) -> 0 | J98: =IFERROR('Raw CF'!L19,0) -> -180 | ... L98: =IFERROR('Raw CF'!N19,0) -> 0
B99: Redemp n Canc of Shares | C99: =IFERROR('Raw CF'!E20,0) -> 0 | D99: =IFERROR('Raw CF'!F20,0) -> 0 | E99: =IFERROR('Raw CF'!G20,0) -> 141 | F99: =IFERROR('Raw CF'!H20,0) -> 0 | G99: =IFERROR('Raw CF'!I20,0) -> 0 | H99: =IFERROR('Raw CF'!J20,0) -> 0 | I99: =IFERROR('Raw CF'!K20,0) -> 0 | J99: =IFERROR('Raw CF'!L20,0) -> 0 | ... L99: =IFERROR('Raw CF'!N20,0) -> 38
B100: Acquisition of companies | C100: =IFERROR('Raw CF'!E21,0) -> 0 | D100: =IFERROR('Raw CF'!F21,0) -> 0 | E100: =IFERROR('Raw CF'!G21,0) -> -525 | F100: =IFERROR('Raw CF'!H21,0) -> 0 | G100: =IFERROR('Raw CF'!I21,0) -> 0 | H100: =IFERROR('Raw CF'!J21,0) -> 0 | I100: =IFERROR('Raw CF'!K21,0) -> 0 | J100: =IFERROR('Raw CF'!L21,0) -> 0 | ... L100: =IFERROR('Raw CF'!N21,0) -> 0
B101: Other investing items | C101: =IFERROR('Raw CF'!E22,0) -> -70 | D101: =IFERROR('Raw CF'!F22,0) -> -324 | E101: =IFERROR('Raw CF'!G22,0) -> 118 | F101: =IFERROR('Raw CF'!H22,0) -> -24 | G101: =IFERROR('Raw CF'!I22,0) -> -353 | H101: =IFERROR('Raw CF'!J22,0) -> -500 | I101: =IFERROR('Raw CF'!K22,0) -> -105 | J101: =IFERROR('Raw CF'!L22,0) -> -126 | ... L101: =IFERROR('Raw CF'!N22,0) -> 130
B102: Cash from Investments | C102: =SUM(C92:C101) -> -865 | D102: =SUM(D92:D101) -> -681 | E102: =SUM(E92:E101) -> -1556 | F102: =SUM(F92:F101) -> -918 | G102: =SUM(G92:G101) -> -519 | H102: =SUM(H92:H101) -> -541 | I102: =SUM(I92:I101) -> -317 | J102: =SUM(J92:J101) -> -1283 | ... L102: =SUM(L92:L101) -> -941
B104: Cash Flow from Financing Activity
B105: Proceeds from shares | C105: =IFERROR('Raw CF'!E25,0) -> 0 | D105: =IFERROR('Raw CF'!F25,0) -> 0 | E105: =IFERROR('Raw CF'!G25,0) -> 0 | F105: =IFERROR('Raw CF'!H25,0) -> 0 | G105: =IFERROR('Raw CF'!I25,0) -> 0 | H105: =IFERROR('Raw CF'!J25,0) -> 0 | I105: =IFERROR('Raw CF'!K25,0) -> 0 | J105: =IFERROR('Raw CF'!L25,0) -> 0 | ... L105: =IFERROR('Raw CF'!N25,0) -> 0
B106: Proceeds from borrowings | C106: =IFERROR('Raw CF'!E26,0) -> 8 | D106: =IFERROR('Raw CF'!F26,0) -> 271 | E106: =IFERROR('Raw CF'!G26,0) -> 10 | F106: =IFERROR('Raw CF'!H26,0) -> 243 | G106: =IFERROR('Raw CF'!I26,0) -> 18 | H106: =IFERROR('Raw CF'!J26,0) -> 155 | I106: =IFERROR('Raw CF'!K26,0) -> 418 | J106: =IFERROR('Raw CF'!L26,0) -> 254 | ... L106: =IFERROR('Raw CF'!N26,0) -> 415
B107: Repayment of borrowings | C107: =IFERROR('Raw CF'!E27,0) -> -119 | D107: =IFERROR('Raw CF'!F27,0) -> -58 | E107: =IFERROR('Raw CF'!G27,0) -> -54 | F107: =IFERROR('Raw CF'!H27,0) -> -26 | G107: =IFERROR('Raw CF'!I27,0) -> -279 | H107: =IFERROR('Raw CF'!J27,0) -> -14 | I107: =IFERROR('Raw CF'!K27,0) -> -8 | J107: =IFERROR('Raw CF'!L27,0) -> -25 | ... L107: =IFERROR('Raw CF'!N27,0) -> -428
B108: Interest paid fin | C108: =IFERROR('Raw CF'!E28,0) -> -40 | D108: =IFERROR('Raw CF'!F28,0) -> -36 | E108: =IFERROR('Raw CF'!G28,0) -> -35 | F108: =IFERROR('Raw CF'!H28,0) -> -106 | G108: =IFERROR('Raw CF'!I28,0) -> -101 | H108: =IFERROR('Raw CF'!J28,0) -> -89 | I108: =IFERROR('Raw CF'!K28,0) -> -94 | J108: =IFERROR('Raw CF'!L28,0) -> -142 | ... L108: =IFERROR('Raw CF'!N28,0) -> -203
B109: Dividends paid | C109: =IFERROR('Raw CF'!E29,0) -> -764 | D109: =IFERROR('Raw CF'!F29,0) -> -947 | E109: =IFERROR('Raw CF'!G29,0) -> -1218 | F109: =IFERROR('Raw CF'!H29,0) -> -1049 | G109: =IFERROR('Raw CF'!I29,0) -> -2121 | H109: =IFERROR('Raw CF'!J29,0) -> -499 | I109: =IFERROR('Raw CF'!K29,0) -> -1763 | J109: =IFERROR('Raw CF'!L29,0) -> -1936 | ... L109: =IFERROR('Raw CF'!N29,0) -> -3140
B110: Financial liabilities | C110: =IFERROR('Raw CF'!E30,0) -> 0 | D110: =IFERROR('Raw CF'!F30,0) -> 0 | E110: =IFERROR('Raw CF'!G30,0) -> 0 | F110: =IFERROR('Raw CF'!H30,0) -> -180 | G110: =IFERROR('Raw CF'!I30,0) -> -179 | H110: =IFERROR('Raw CF'!J30,0) -> -203 | I110: =IFERROR('Raw CF'!K30,0) -> -221 | J110: =IFERROR('Raw CF'!L30,0) -> -256 | ... L110: =IFERROR('Raw CF'!N30,0) -> -325
B111: Other financing items | C111: =IFERROR('Raw CF'!E31,0) -> 66 | D111: =IFERROR('Raw CF'!F31,0) -> 13 | E111: =IFERROR('Raw CF'!G31,0) -> -82 | F111: =IFERROR('Raw CF'!H31,0) -> 0 | G111: =IFERROR('Raw CF'!I31,0) -> -209 | H111: =IFERROR('Raw CF'!J31,0) -> 0 | I111: =IFERROR('Raw CF'!K31,0) -> -140 | J111: =IFERROR('Raw CF'!L31,0) -> -36 | ... L111: =IFERROR('Raw CF'!N31,0) -> -72
B112: Cash from Financing | C112: =SUM(C105:C111) -> -849 | D112: =SUM(D105:D111) -> -757 | E112: =SUM(E105:E111) -> -1379 | F112: =SUM(F105:F111) -> -1118 | G112: =SUM(G105:G111) -> -2871 | H112: =SUM(H105:H111) -> -650 | I112: =SUM(I105:I111) -> -1808 | J112: =SUM(J105:J111) -> -2141 | ... L112: =SUM(L105:L111) -> -3753
B114: Net Cash Flows | C114: =IFERROR(SUM(C89,C102,C112),0) -> 728 | D114: =IFERROR(SUM(D89,D102,D112),0) -> -513 | E114: =IFERROR(SUM(E89,E102,E112),0) -> -902 | F114: =IFERROR(SUM(F89,F102,F112),0) -> 23 | G114: =IFERROR(SUM(G89,G102,G112),0) -> -684 | H114: =IFERROR(SUM(H89,H102,H112),0) -> 2286 | I114: =IFERROR(SUM(I89,I102,I112),0) -> -3933 | J114: =IFERROR(SUM(J89,J102,J112),0) -> -2 | ... L114: =IFERROR(SUM(L89,L102,L112),0) -> -839

Sheet Ratio Analysis
B2: ="Ratio Analysis - "&'Data Sheet'!B1 -> Ratio Analysis - ASIAN PAINTS LTD
B3: Years | C3: ='[1]Data Sheet'!B16 -> 42460 | D3: ='[1]Data Sheet'!C16 -> 42825 | E3: ='[1]Data Sheet'!D16 -> 43190 | F3: ='[1]Data Sheet'!E16 -> 43555 | G3: ='[1]Data Sheet'!F16 -> 43921 | H3: ='[1]Data Sheet'!G16 -> 44286 | I3: ='[1]Data Sheet'!H16 -> 44651 | J3: ='[1]Data Sheet'!I16 -> 45016 | ... L3: ='[1]Data Sheet'!K16 -> 45747 | M3: Trend | N3: Mean | O3: Median
B5: Sales Growth | D5: =IFERROR(HistoricalFS!D7,0) -> 0.055390152 | E5: =IFERROR(HistoricalFS!E7,0) -> 0.11702039 | F5: =IFERROR(HistoricalFS!F7,0) -> 0.14357472 | G5: =IFERROR(HistoricalFS!G7,0) -> 0.050473671 | H5: =IFERROR(HistoricalFS!H7,0) -> 0.074292288 | I5: =IFERROR(HistoricalFS!I7,0) -> 0.34028285 | J5: =IFERROR(HistoricalFS!J7,0) -> 0.18512278 | K5: =IFERROR(HistoricalFS!K7,0) -> 0.029173127 | L5: =IFERROR(HistoricalFS!L7,0) -> -0.044770308 | N5: =IFERROR(AVERAGE(D5:L5),0) -> 0.10561774 | O5: =IFERROR(MEDIAN(D5:L5),0) -> 0.074292288
B6: EBITDA Growth | D6: =IFERROR(HistoricalFS!D18/HistoricalFS!C18-1,0) -> 0.098611397 | E6: =IFERROR(HistoricalFS!E18/HistoricalFS!D18-1,0) -> 0.070229411 | F6: =IFERROR(HistoricalFS!F18/HistoricalFS!E18-1,0) -> 0.17507124 | G6: =IFERROR(HistoricalFS!G18/HistoricalFS!F18-1,0) -> 0.10408665 | H6: =IFERROR(HistoricalFS!H18/HistoricalFS!G18-1,0) -> 0.16810446 | I6: =IFERROR(HistoricalFS!I18/HistoricalFS!H18-1,0) -> -0.010707225 | J6: =IFERROR(HistoricalFS!J18/HistoricalFS!I18-1,0) -> 0.30315325 | K6: =IFERROR(HistoricalFS!K18/HistoricalFS!J18-1,0) -> 0.21168912 | L6: =IFERROR(HistoricalFS!L18/HistoricalFS!K18-1,0) -> -0.20814425 | N6: =IFERROR(AVERAGE(D6:L6),0) -> 0.10134378 | O6: =IFERROR(MEDIAN(D6:L6),0) -> 0.10408665
B7: EBIT Growth | D7: =IFERROR(HistoricalFS!D27/HistoricalFS!C27-1,0) -> 0.085533138 | E7: =IFERROR(HistoricalFS!E27/HistoricalFS!D27-1,0) -> 0.069414096 | F7: =IFERROR(HistoricalFS!F27/HistoricalFS!E27-1,0) -> 0.10524206 | G7: =IFERROR(HistoricalFS!G27/HistoricalFS!F27-1,0) -> 0.074303169 | H7: =IFERROR(HistoricalFS!H27/HistoricalFS!G27-1,0) -> 0.20377512 | I7: =IFERROR(HistoricalFS!I27/HistoricalFS!H27-1,0) -> -0.018964995 | J7: =IFERROR(HistoricalFS!J27/HistoricalFS!I27-1,0) -> 0.35477334 | K7: =IFERROR(HistoricalFS!K27/HistoricalFS!J27-1,0) -> 0.24624293 | L7: =IFERROR(HistoricalFS!L27/HistoricalFS!K27-1,0) -> -0.26026667 | N7: =IFERROR(AVERAGE(D7:L7),0) -> 0.095561354 | O7: =IFERROR(MEDIAN(D7:L7),0) -> 0.085533138
B8: EBT Growth | D8: =IFERROR(HistoricalFS!D30/HistoricalFS!C30-1,0) -> 0.092140673 | E8: =IFERROR(HistoricalFS!E30/HistoricalFS!D30-1,0) -> 0.068823332 | F8: =IFERROR(HistoricalFS!F30/HistoricalFS!E30-1,0) -> 0.082174964 | G8: =IFERROR(HistoricalFS!G30/HistoricalFS!F30-1,0) -> 0.079694492 | H8: =IFERROR(HistoricalFS!H30/HistoricalFS!G30-1,0) -> 0.21341238 | I8: =IFERROR(HistoricalFS!I30/HistoricalFS!H30-1,0) -> -0.020353915 | J8: =IFERROR(HistoricalFS!J30/HistoricalFS!I30-1,0) -> 0.35087003 | K8: =IFERROR(HistoricalFS!K30/HistoricalFS!J30-1,0) -> 0.24145913 | L8: =IFERROR(HistoricalFS!L30/HistoricalFS!K30-1,0) -> -0.27179587 | N8: =IFERROR(AVERAGE(D8:L8),0) -> 0.092936135 | O8: =IFERROR(MEDIAN(D8:L8),0) -> 0.082174964
B9: Net Profit Growth | D9: =IFERROR(HistoricalFS!D36/HistoricalFS!C36-1,0) -> 0.078651902 | E9: =IFERROR(HistoricalFS!E36/HistoricalFS!D36-1,0) -> 0.049310335 | F9: =IFERROR(HistoricalFS!F36/HistoricalFS!E36-1,0) -> 0.098324352 | G9: =IFERROR(HistoricalFS!G36/HistoricalFS!F36-1,0) -> 0.25067338 | H9: =IFERROR(HistoricalFS!H36/HistoricalFS!G36-1,0) -> 0.1884802 | I9: =IFERROR(HistoricalFS!I36/HistoricalFS!H36-1,0) -> -0.029971131 | J9: =IFERROR(HistoricalFS!J36/HistoricalFS!I36-1,0) -> 0.34957493 | K9: =IFERROR(HistoricalFS!K36/HistoricalFS!J36-1,0) -> 0.25847333 | L9: =IFERROR(HistoricalFS!L36/HistoricalFS!K36-1,0) -> -0.29075755 | N9: =IFERROR(AVERAGE(D9:L9),0) -> 0.10586219 | O9: =IFERROR(MEDIAN(D9:L9),0) -> 0.098324352
B10: Dividend Growth | D10: =IFERROR(HistoricalFS!D44/HistoricalFS!C44-1,0) -> 0.37333889 | E10: =IFERROR(HistoricalFS!E44/HistoricalFS!D44-1,0) -> -0.15534727 | F10: =IFERROR(HistoricalFS!F44/HistoricalFS!E44-1,0) -> 0.20690234 | G10: =IFERROR(HistoricalFS!G44/HistoricalFS!F44-1,0) -> 0.14285714 | H10: =IFERROR(HistoricalFS!H44/HistoricalFS!G44-1,0) -> 0.48749826 | I10: =IFERROR(HistoricalFS!I44/HistoricalFS!H44-1,0) -> 0.072831553 | J10: =IFERROR(HistoricalFS!J44/HistoricalFS!I44-1,0) -> 0.33942522 | K10: =IFERROR(HistoricalFS!K44/HistoricalFS!J44-1,0) -> 0.29824618 | L10: =IFERROR(HistoricalFS!L44/HistoricalFS!K44-1,0) -> -0.25525494 | N10: =IFERROR(AVERAGE(D10:L10),0) -> 0.16783304 | O10: =IFERROR(MEDIAN(D10:L10),0) -> 0.20690234
B12: Gross Margin | C12: =IFERROR(HistoricalFS!C13,0) -> 0.34037441 | D12: =IFERROR(HistoricalFS!D13,0) -> 0.35382642 | E12: =IFERROR(HistoricalFS!E13,0) -> 0.33465264 | F12: =IFERROR(HistoricalFS!F13,0) -> 0.32922439 | G12: =IFERROR(HistoricalFS!G13,0) -> 0.34897545 | H12: =IFERROR(HistoricalFS!H13,0) -> 0.35360357 | I12: =IFERROR(HistoricalFS!I13,0) -> 0.2924514 | J12: =IFERROR(HistoricalFS!J13,0) -> 0.31088224 | ... L12: =IFERROR(HistoricalFS!L13,0) -> 0.32927727 | N12: =IFERROR(AVERAGE(C12:L12),0) -> 0.33450028 | O12: =IFERROR(MEDIAN(C12:L12),0) -> 0.33751352
B13: EBITA Margin | C13: =IFERROR(HistoricalFS!C19,0) -> 0.19094292 | D13: =IFERROR(HistoricalFS!D19,0) -> 0.19876258 | E13: =IFERROR(HistoricalFS!E19,0) -> 0.19043659 | F13: =IFERROR(HistoricalFS!F19,0) -> 0.19568163 | G13: =IFERROR(HistoricalFS!G19,0) -> 0.20566863 | H13: =IFERROR(HistoricalFS!H19,0) -> 0.22362856 | I13: =IFERROR(HistoricalFS!I19,0) -> 0.16506525 | J13: =IFERROR(HistoricalFS!J19,0) -> 0.18150467 | ... L13: =IFERROR(HistoricalFS!L19,0) -> 0.17714497 | N13: =IFERROR(AVERAGE(C13:L13),0) -> 0.19425289 | O13: =IFERROR(MEDIAN(C13:L13),0) -> 0.19331228
B14: EBIT Margin | C14: =IFERROR(HistoricalFS!C28,0) -> 0.1716331 | D14: =IFERROR(HistoricalFS!D28,0) -> 0.17653511 | E14: =IFERROR(HistoricalFS!E28,0) -> 0.16901136 | F14: =IFERROR(HistoricalFS!F28,0) -> 0.16334609 | G14: =IFERROR(HistoricalFS!G28,0) -> 0.16705152 | H14: =IFERROR(HistoricalFS!H28,0) -> 0.18718599 | I14: =IFERROR(HistoricalFS!I28,0) -> 0.13701287 | J14: =IFERROR(HistoricalFS!J28,0) -> 0.15662629 | ... L14: =IFERROR(HistoricalFS!L28,0) -> 0.14687447 | N14: =IFERROR(AVERAGE(C14:L14),0) -> 0.16649382 | O14: =IFERROR(MEDIAN(C14:L14),0) -> 0.16803144
B15: EBT Margin | C15: =IFERROR(HistoricalFS!C31,0) -> 0.16819968 | D15: =IFERROR(HistoricalFS!D31,0) -> 0.17405668 | E15: =IFERROR(HistoricalFS!E31,0) -> 0.1665465 | F15: =IFERROR(HistoricalFS!F31,0) -> 0.15760444 | G15: =IFERROR(HistoricalFS!G31,0) -> 0.1619885 | H15: =IFERROR(HistoricalFS!H31,0) -> 0.18296589 | I15: =IFERROR(HistoricalFS!I31,0) -> 0.13373432 | J15: =IFERROR(HistoricalFS!J31,0) -> 0.15243795 | ... L15: =IFERROR(HistoricalFS!L31,0) -> 0.14017883 | N15: =IFERROR(AVERAGE(C15:L15),0) -> 0.16215939 | O15: =IFERROR(MEDIAN(C15:L15),0) -> 0.1642675
B16: Net Profit Margin | C16: =IFERROR(HistoricalFS!C37,0) -> 0.10902646 | D16: =IFERROR(HistoricalFS!D37,0) -> 0.1114295 | E16: =IFERROR(HistoricalFS!E37,0) -> 0.10467501 | F16: =IFERROR(HistoricalFS!F37,0) -> 0.1005331 | G16: =IFERROR(HistoricalFS!G37,0) -> 0.11969275 | H16: =IFERROR(HistoricalFS!H37,0) -> 0.13241504 | I16: =IFERROR(HistoricalFS!I37,0) -> 0.095835303 | J16: =IFERROR(HistoricalFS!J37,0) -> 0.10913377 | ... L16: =IFERROR(HistoricalFS!L37,0) -> 0.099083574 | N16: =IFERROR(AVERAGE(C16:L16),0) -> 0.11152733 | O16: =IFERROR(MEDIAN(C16:L16),0) -> 0.10908012
B18: Sales Expenses % of sales | C18: =IFERROR(HistoricalFS!C16,0) -> 0.14943149 | D18: =IFERROR(HistoricalFS!D16,0) -> 0.15506384 | E18: =IFERROR(HistoricalFS!E16,0) -> 0.14421604 | F18: =IFERROR(HistoricalFS!F16,0) -> 0.13354276 | G18: =IFERROR(HistoricalFS!G16,0) -> 0.14330682 | H18: =IFERROR(HistoricalFS!H16,0) -> 0.12997501 | I18: =IFERROR(HistoricalFS!I16,0) -> 0.12738615 | J18: =IFERROR(HistoricalFS!J16,0) -> 0.12937757 | ... L18: =IFERROR(HistoricalFS!L16,0) -> 0.1521323 | N18: =IFERROR(AVERAGE(C18:L18),0) -> 0.14024739 | O18: =IFERROR(MEDIAN(C18:L18),0) -> 0.14067436
B19: Depriciation % of sales | C19: =IFERROR(HistoricalFS!C25,0) -> 0.019309827 | D19: =IFERROR(HistoricalFS!D25,0) -> 0.022227475 | E19: =IFERROR(HistoricalFS!E25,0) -> 0.021425239 | F19: =IFERROR(HistoricalFS!F25,0) -> 0.03233554 | G19: =IFERROR(HistoricalFS!G25,0) -> 0.038617107 | H19: =IFERROR(HistoricalFS!H25,0) -> 0.036442576 | I19: =IFERROR(HistoricalFS!I25,0) -> 0.028052374 | J19: =IFERROR(HistoricalFS!J25,0) -> 0.024878373 | ... L19: =IFERROR(HistoricalFS!L25,0) -> 0.030270498 | N19: =IFERROR(AVERAGE(C19:L19),0) -> 0.027759074 | O19: =IFERROR(MEDIAN(C19:L19),0) -> 0.026465374
B20: Operating Income % of sales | C20: =C14 -> 0.1716331 | D20: =D14 -> 0.17653511 | E20: =E14 -> 0.16901136 | F20: =F14 -> 0.16334609 | G20: =G14 -> 0.16705152 | H20: =H14 -> 0.18718599 | I20: =I14 -> 0.13701287 | J20: =J14 -> 0.15662629 | ... L20: =L14 -> 0.14687447 | N20: =IFERROR(AVERAGE(C20:L20),0) -> 0.16649382 | O20: =IFERROR(MEDIAN(C20:L20),0) -> 0.16803144
B22: Return on Capital Employed | C22: =IFERROR(HistoricalFS!C27/SUM(HistoricalFS!C50:C52),0) -> 0.35768409 | D22: =IFERROR(HistoricalFS!D27/SUM(HistoricalFS!D50:D52),0) -> 0.32568534 | E22: =IFERROR(HistoricalFS!E27/SUM(HistoricalFS!E50:E52),0) -> 0.31793919 | F22: =IFERROR(HistoricalFS!F27/SUM(HistoricalFS!F50:F52),0) -> 0.29126565 | G22: =IFERROR(HistoricalFS!G27/SUM(HistoricalFS!G50:G52),0) -> 0.30015308 | H22: =IFERROR(HistoricalFS!H27/SUM(HistoricalFS!H50:H52),0) -> 0.29241025 | I22: =IFERROR(HistoricalFS!I27/SUM(HistoricalFS!I50:I52),0) -> 0.25893857 | J22: =IFERROR(HistoricalFS!J27/SUM(HistoricalFS!J50:J52),0) -> 0.30135929 | ... L22: =IFERROR(HistoricalFS!L27/SUM(HistoricalFS!L50:L52),0) -> 0.22959184 | N22: =IFERROR(AVERAGE(C22:L22),0) -> 0.29925334 | O22: =IFERROR(MEDIAN(C22:L22),0) -> 0.30075619
B23: Retained Earnings % | C23: =IFERROR(HistoricalFS!C47,0) -> 0.53765175 | D23: =IFERROR(HistoricalFS!D47,0) -> 0.41133852 | E23: =IFERROR(HistoricalFS!E47,0) -> 0.52615112 | F23: =IFERROR(HistoricalFS!F47,0) -> 0.47930744 | G23: =IFERROR(HistoricalFS!G47,0) -> 0.52419455 | H23: =IFERROR(HistoricalFS!H47,0) -> 0.40448332 | I23: =IFERROR(HistoricalFS!I47,0) -> 0.34137106 | J23: =IFERROR(HistoricalFS!J47,0) -> 0.34632439 | ... L23: =IFERROR(HistoricalFS!L47,0) -> 0.29191038 | N23: =IFERROR(AVERAGE(C23:L23),0) -> 0.41883981 | O23: =IFERROR(MEDIAN(C23:L23),0) -> 0.40791092
B24: Return on Equity % | C24: =IFERROR(HistoricalFS!C36/SUM(HistoricalFS!C50:C51),0) -> 0.23846941 | D24: =IFERROR(HistoricalFS!D36/SUM(HistoricalFS!D50:D51),0) -> 0.22072255 | E24: =IFERROR(HistoricalFS!E36/SUM(HistoricalFS!E50:E51),0) -> 0.20940093 | F24: =IFERROR(HistoricalFS!F36/SUM(HistoricalFS!F50:F51),0) -> 0.20424051 | G24: =IFERROR(HistoricalFS!G36/SUM(HistoricalFS!G50:G51),0) -> 0.2388057 | H24: =IFERROR(HistoricalFS!H36/SUM(HistoricalFS!H50:H51),0) -> 0.22450686 | I24: =IFERROR(HistoricalFS!I36/SUM(HistoricalFS!I50:I51),0) -> 0.20192723 | J24: =IFERROR(HistoricalFS!J36/SUM(HistoricalFS!J50:J51),0) -> 0.23535617 | ... L24: =IFERROR(HistoricalFS!L36/SUM(HistoricalFS!L50:L51),0) -> 0.17317128 | N24: =IFERROR(AVERAGE(C24:L24),0) -> 0.2199519 | O24: =IFERROR(MEDIAN(C24:L24),0) -> 0.22261471
B25: Self Sustained Growth Rate | C25: =IFERROR(C23*C24,0) -> 0.1282135 | D25: =IFERROR(D23*D24,0) -> 0.090791687 | E25: =IFERROR(E23*E24,0) -> 0.11017654 | F25: =IFERROR(F23*F24,0) -> 0.097893998 | G25: =IFERROR(G23*G24,0) -> 0.12518065 | H25: =IFERROR(H23*H24,0) -> 0.090809282 | I25: =IFERROR(I23*I24,0) -> 0.068932112 | J25: =IFERROR(J23*J24,0) -> 0.081509583 | ... L25: =IFERROR(L23*L24,0) -> 0.050550495 | N25: =IFERROR(AVERAGE(C25:L25),0) -> 0.092642463 | O25: =IFERROR(MEDIAN(C25:L25),0) -> 0.090800484
B26: Interest Coverage Ratio | C26: =IFERROR(HistoricalFS!C27/HistoricalFS!C21,0) -> 49.98898 | D26: =IFERROR(HistoricalFS!D27/HistoricalFS!D21,0) -> 71.22877 | E26: =IFERROR(HistoricalFS!E27/HistoricalFS!E21,0) -> 68.568604 | F26: =IFERROR(HistoricalFS!F27/HistoricalFS!F21,0) -> 28.449353 | G26: =IFERROR(HistoricalFS!G27/HistoricalFS!G21,0) -> 32.99443 | H26: =IFERROR(HistoricalFS!H27/HistoricalFS!H21,0) -> 44.355888 | I26: =IFERROR(HistoricalFS!I27/HistoricalFS!I21,0) -> 41.790693 | J26: =IFERROR(HistoricalFS!J27/HistoricalFS!J21,0) -> 37.395777 | ... L26: =IFERROR(HistoricalFS!L27/HistoricalFS!L21,0) -> 21.935821 | N26: =IFERROR(AVERAGE(C26:L26),0) -> 42.952003 | O26: =IFERROR(MEDIAN(C26:L26),0) -> 39.593235
B28: Debtor Turnover Ratio | C28: =IFERROR(HistoricalFS!C6/HistoricalFS!C62,0) -> 12.02478 | D28: =IFERROR(HistoricalFS!D6/HistoricalFS!D62,0) -> 10.411994 | E28: =IFERROR(HistoricalFS!E6/HistoricalFS!E62,0) -> 9.7216332 | F28: =IFERROR(HistoricalFS!F6/HistoricalFS!F62,0) -> 10.087468 | G28: =IFERROR(HistoricalFS!G6/HistoricalFS!G62,0) -> 11.258369 | H28: =IFERROR(HistoricalFS!H6/HistoricalFS!H62,0) -> 8.344109 | I28: =IFERROR(HistoricalFS!I6/HistoricalFS!I62,0) -> 7.5169136 | J28: =IFERROR(HistoricalFS!J6/HistoricalFS!J62,0) -> 7.4377909 | ... L28: =IFERROR(HistoricalFS!L6/HistoricalFS!L62,0) -> 7.8600767 | N28: =IFERROR(AVERAGE(C28:L28),0) -> 9.1923181 | O28: =IFERROR(MEDIAN(C28:L28),0) -> 9.0328711
B29: Creditor Turnover Ratio | C29: =IFERROR(HistoricalFS!C9/HistoricalFS!C53,0) -> 2.5367941 | D29: =IFERROR(HistoricalFS!D9/HistoricalFS!D53,0) -> 2.2949191 | E29: =IFERROR(HistoricalFS!E9/HistoricalFS!E53,0) -> 2.3225286 | F29: =IFERROR(HistoricalFS!F9/HistoricalFS!F53,0) -> 2.3642687 | G29: =IFERROR(HistoricalFS!G9/HistoricalFS!G53,0) -> 2.6911814 | H29: =IFERROR(HistoricalFS!H9/HistoricalFS!H53,0) -> 2.1739811 | I29: =IFERROR(HistoricalFS!I9/HistoricalFS!I53,0) -> 2.723624 | J29: =IFERROR(HistoricalFS!J9/HistoricalFS!J53,0) -> 3.0258782 | ... L29: =IFERROR(HistoricalFS!L9/HistoricalFS!L53,0) -> 2.624452 | N29: =IFERROR(AVERAGE(C29:L29),0) -> 2.5403034 | O29: =IFERROR(MEDIAN(C29:L29),0) -> 2.580623
B30: Inventory Turnover | C30: =IFERROR(HistoricalFS!C9/HistoricalFS!C63,0) -> 4.7110657 | D30: =IFERROR(HistoricalFS!D9/HistoricalFS!D63,0) -> 3.7049419 | E30: =IFERROR(HistoricalFS!E9/HistoricalFS!E63,0) -> 4.21101 | F30: =IFERROR(HistoricalFS!F9/HistoricalFS!F63,0) -> 4.0972646 | G30: =IFERROR(HistoricalFS!G9/HistoricalFS!G63,0) -> 3.8816394 | H30: =IFERROR(HistoricalFS!H9/HistoricalFS!H63,0) -> 3.6948007 | I30: =IFERROR(HistoricalFS!I9/HistoricalFS!I63,0) -> 3.3464386 | J30: =IFERROR(HistoricalFS!J9/HistoricalFS!J63,0) -> 3.8267715 | ... L30: =IFERROR(HistoricalFS!L9/HistoricalFS!L63,0) -> 3.3844852 | N30: =IFERROR(AVERAGE(C30:L30),0) -> 3.8743003 | O30: =IFERROR(MEDIAN(C30:L30),0) -> 3.8542054
B31: Fixed Asset Turnover | C31: =IFERROR(HistoricalFS!C6/HistoricalFS!C56,0) -> 4.1774086 | D31: =IFERROR(HistoricalFS!D6/HistoricalFS!D56,0) -> 4.5590724 | E31: =IFERROR(HistoricalFS!E6/HistoricalFS!E56,0) -> 4.5078961 | F31: =IFERROR(HistoricalFS!F6/HistoricalFS!F56,0) -> 2.9615874 | G31: =IFERROR(HistoricalFS!G6/HistoricalFS!G56,0) -> 3.2222977 | H31: =IFERROR(HistoricalFS!H6/HistoricalFS!H56,0) -> 3.7061903 | I31: =IFERROR(HistoricalFS!I6/HistoricalFS!I56,0) -> 5.2728689 | J31: =IFERROR(HistoricalFS!J6/HistoricalFS!J56,0) -> 5.9767488 | ... L31: =IFERROR(HistoricalFS!L6/HistoricalFS!L56,0) -> 3.6773592 | N31: =IFERROR(AVERAGE(C31:L31),0) -> 4.3028075 | O31: =IFERROR(MEDIAN(C31:L31),0) -> 4.3426524
B32: Capital Turnover Ratio | C32: =IFERROR(HistoricalFS!C6/SUM(HistoricalFS!C50:C51),0) -> 2.1872619 | D32: =IFERROR(HistoricalFS!D6/SUM(HistoricalFS!D50:D51),0) -> 1.9808269 | E32: =IFERROR(HistoricalFS!E6/SUM(HistoricalFS!E50:E51),0) -> 2.0004863 | F32: =IFERROR(HistoricalFS!F6/SUM(HistoricalFS!F50:F51),0) -> 2.0315747 | G32: =IFERROR(HistoricalFS!G6/SUM(HistoricalFS!G50:G51),0) -> 1.995156 | H32: =IFERROR(HistoricalFS!H6/SUM(HistoricalFS!H50:H51),0) -> 1.6954785 | I32: =IFERROR(HistoricalFS!I6/SUM(HistoricalFS!I50:I51),0) -> 2.1070234 | J32: =IFERROR(HistoricalFS!J6/SUM(HistoricalFS!J50:J51),0) -> 2.1565842 | ... L32: =IFERROR(HistoricalFS!L6/SUM(HistoricalFS!L50:L51),0) -> 1.7477295 | N32: =IFERROR(AVERAGE(C32:L32),0) -> 1.9797367 | O32: =IFERROR(MEDIAN(C32:L32),0) -> 1.9978212
B34: Debtor Days | C34: =IFERROR(365/C28,0) -> 30.353985 | D34: =IFERROR(365/D28,0) -> 35.055726 | E34: =IFERROR(365/E28,0) -> 37.545132 | F34: =IFERROR(365/F28,0) -> 36.183511 | G34: =IFERROR(365/G28,0) -> 32.420325 | H34: =IFERROR(365/H28,0) -> 43.743436 | I34: =IFERROR(365/I28,0) -> 48.557163 | J34: =IFERROR(365/J28,0) -> 49.073711 | ... L34: =IFERROR(365/L28,0) -> 46.437206 | N34: =IFERROR(AVERAGE(C34:L34),0) -> 40.964536 | O34: =IFERROR(MEDIAN(C34:L34),0) -> 40.644284
B35: Payable Days | C35: =IFERROR(365/C29,0) -> 143.88239 | D35: =IFERROR(365/D29,0) -> 159.047 | E35: =IFERROR(365/E29,0) -> 157.1563 | F35: =IFERROR(365/F29,0) -> 154.38177 | G35: =IFERROR(365/G29,0) -> 135.62817 | H35: =IFERROR(365/H29,0) -> 167.89474 | I35: =IFERROR(365/I29,0) -> 134.01263 | J35: =IFERROR(365/J29,0) -> 120.62614 | ... L35: =IFERROR(365/L29,0) -> 139.07665 | N35: =IFERROR(AVERAGE(C35:L35),0) -> 144.96808 | O35: =IFERROR(MEDIAN(C35:L35),0) -> 141.47952
B36: Inventory Days | C36: =IFERROR(365/C30,0) -> 77.477161 | D36: =IFERROR(365/D30,0) -> 98.517065 | E36: =IFERROR(365/E30,0) -> 86.677543 | F36: =IFERROR(365/F30,0) -> 89.083823 | G36: =IFERROR(365/G30,0) -> 94.032434 | H36: =IFERROR(365/H30,0) -> 98.787466 | I36: =IFERROR(365/I30,0) -> 109.07118 | J36: =IFERROR(365/J30,0) -> 95.380663 | ... L36: =IFERROR(365/L30,0) -> 107.84506 | N36: =IFERROR(AVERAGE(C36:L36),0) -> 95.083352 | O36: =IFERROR(MEDIAN(C36:L36),0) -> 94.706549
B37: Cash Conversion Cycle (in days) | C37: =IFERROR(SUM(C34,C36)-C35,0) -> -36.051243 | D37: =IFERROR(SUM(D34,D36)-D35,0) -> -25.474211 | E37: =IFERROR(SUM(E34,E36)-E35,0) -> -32.933622 | F37: =IFERROR(SUM(F34,F36)-F35,0) -> -29.11444 | G37: =IFERROR(SUM(G34,G36)-G35,0) -> -9.1754087 | H37: =IFERROR(SUM(H34,H36)-H35,0) -> -25.363839 | I37: =IFERROR(SUM(I34,I36)-I35,0) -> 23.615714 | J37: =IFERROR(SUM(J34,J36)-J35,0) -> 23.828237 | ... L37: =IFERROR(SUM(L34,L36)-L35,0) -> 15.205608 | N37: =IFERROR(AVERAGE(C37:L37),0) -> -8.9201892 | O37: =IFERROR(MEDIAN(C37:L37),0) -> -17.269624
B39: CFO/Sales | C39: =IFERROR(HistoricalFS!C73/HistoricalFS!C6,0) -> 0.15716299 | D39: =IFERROR(HistoricalFS!D73/HistoricalFS!D6,0) -> 0.10140294 | E39: =IFERROR(HistoricalFS!E73/HistoricalFS!E6,0) -> 0.12561644 | F39: =IFERROR(HistoricalFS!F73/HistoricalFS!F6,0) -> 0.1283536 | G39: =IFERROR(HistoricalFS!G73/HistoricalFS!G6,0) -> 0.15031975 | H39: =IFERROR(HistoricalFS!H73/HistoricalFS!H6,0) -> 0.16963965 | I39: =IFERROR(HistoricalFS!I73/HistoricalFS!I6,0) -> 0.033898509 | J39: =IFERROR(HistoricalFS!J73/HistoricalFS!J6,0) -> 0.12158891 | ... L39: =IFERROR(HistoricalFS!L73/HistoricalFS!L6,0) -> 0.13047866 | N39: =IFERROR(AVERAGE(C39:L39),0) -> 0.12904194 | O39: =IFERROR(MEDIAN(C39:L39),0) -> 0.12941613
B40: CFO/Total Assets | C40: =IFERROR(HistoricalFS!C73/HistoricalFS!C67,0) -> 0.21242008 | D40: =IFERROR(HistoricalFS!D73/HistoricalFS!D67,0) -> 0.12312024 | E40: =IFERROR(HistoricalFS!E73/HistoricalFS!E67,0) -> 0.15355419 | F40: =IFERROR(HistoricalFS!F73/HistoricalFS!F67,0) -> 0.15198254 | G40: =IFERROR(HistoricalFS!G73/HistoricalFS!G67,0) -> 0.18826098 | H40: =IFERROR(HistoricalFS!H73/HistoricalFS!H67,0) -> 0.18095252 | I40: =IFERROR(HistoricalFS!I73/HistoricalFS!I67,0) -> 0.042968531 | J40: =IFERROR(HistoricalFS!J73/HistoricalFS!J67,0) -> 0.16266637 | ... L40: =IFERROR(HistoricalFS!L73/HistoricalFS!L67,0) -> 0.14573953 | N40: =IFERROR(AVERAGE(C40:L40),0) -> 0.15657935 | O40: =IFERROR(MEDIAN(C40:L40),0) -> 0.15811028
B41: CFO/Total Debt | C41: =IFERROR(HistoricalFS!C73/HistoricalFS!C52,0) -> 6.9378886 | D41: =IFERROR(HistoricalFS!D73/HistoricalFS!D52,0) -> 2.7257201 | E41: =IFERROR(HistoricalFS!E73/HistoricalFS!E52,0) -> 3.9619819 | F41: =IFERROR(HistoricalFS!F73/HistoricalFS!F52,0) -> 1.8714307 | G41: =IFERROR(HistoricalFS!G73/HistoricalFS!G52,0) -> 2.7162718 | H41: =IFERROR(HistoricalFS!H73/HistoricalFS!H52,0) -> 3.3695752 | I41: =IFERROR(HistoricalFS!I73/HistoricalFS!I52,0) -> 0.62165381 | J41: =IFERROR(HistoricalFS!J73/HistoricalFS!J52,0) -> 2.1698161 | ... L41: =IFERROR(HistoricalFS!L73/HistoricalFS!L52,0) -> 1.9316156 | N41: =IFERROR(AVERAGE(C41:L41),0) -> 2.8772673 | O41: =IFERROR(MEDIAN(C41:L41),0) -> 2.5914954

Sheet Common Size Statement
A2: # | B2: ="Common Size Income Statement - "&'[1]Data Sheet'!$B$1 -> Common Size Income Statement - ASIAN PAINTS LTD
B3: Particulars | C3: ='[1]Data Sheet'!B$16 -> 42460 | D3: ='[1]Data Sheet'!C$16 -> 42825 | E3: ='[1]Data Sheet'!D$16 -> 43190 | F3: ='[1]Data Sheet'!E$16 -> 43555 | G3: ='[1]Data Sheet'!F$16 -> 43921 | H3: ='[1]Data Sheet'!G$16 -> 44286 | I3: ='[1]Data Sheet'!H$16 -> 44651 | J3: ='[1]Data Sheet'!I$16 -> 45016 | ... L3: ='[1]Data Sheet'!K$16 -> 45747
B5: ='[1]Data Sheet'!A17 -> Sales | C5: ='Data Sheet'!B17/'Data Sheet'!B$17 -> 1 | D5: ='Data Sheet'!C17/'Data Sheet'!C$17 -> 1 | E5: ='Data Sheet'!D17/'Data Sheet'!D$17 -> 1 | F5: ='Data Sheet'!E17/'Data Sheet'!E$17 -> 1 | G5: ='Data Sheet'!F17/'Data Sheet'!F$17 -> 1 | H5: ='Data Sheet'!G17/'Data Sheet'!G$17 -> 1 | I5: ='Data Sheet'!H17/'Data Sheet'!H$17 -> 1 | J5: ='Data Sheet'!I17/'Data Sheet'!I$17 -> 1 | ... L5: ='Data Sheet'!K17/'Data Sheet'!K$17 -> 1
B6: ='[1]Data Sheet'!A18 -> Raw Material Cost | C6: ='Data Sheet'!B18/'Data Sheet'!B$17 -> 0.46034647 | D6: ='Data Sheet'!C18/'Data Sheet'!C$17 -> 0.49479518 | E6: ='Data Sheet'!D18/'Data Sheet'!D$17 -> 0.48311366 | F6: ='Data Sheet'!E18/'Data Sheet'!E$17 -> 0.51841646 | G6: ='Data Sheet'!F18/'Data Sheet'!F$17 -> 0.49388286 | H6: ='Data Sheet'!G18/'Data Sheet'!G$17 -> 0.48015709 | I6: ='Data Sheet'!H18/'Data Sheet'!H$17 -> 0.58840195 | J6: ='Data Sheet'!I18/'Data Sheet'!I$17 -> 0.55048728 | ... L6: ='Data Sheet'!K18/'Data Sheet'!K$17 -> 0.51627164
B7: ='[1]Data Sheet'!A19 -> Change in Inventory | C7: ='Data Sheet'!B19/'Data Sheet'!B$17 -> -0.013967007 | D7: ='Data Sheet'!C19/'Data Sheet'!C$17 -> 0.035094964 | E7: ='Data Sheet'!D19/'Data Sheet'!D$17 -> -0.0084477742 | F7: ='Data Sheet'!E19/'Data Sheet'!E$17 -> 0.015242101 | G7: ='Data Sheet'!F19/'Data Sheet'!F$17 -> 0.011832519 | H7: ='Data Sheet'!G19/'Data Sheet'!G$17 -> 0.0042578591 | I7: ='Data Sheet'!H19/'Data Sheet'!H$17 -> 0.045529612 | J7: ='Data Sheet'!I19/'Data Sheet'!I$17 -> 0.0089806513 | ... L7: ='Data Sheet'!K19/'Data Sheet'!K$17 -> 0.0060461953
B8: ='[1]Data Sheet'!A20 -> Power and Fuel | C8: ='Data Sheet'!B20/'Data Sheet'!B$17 -> 0.0080215871 | D8: ='Data Sheet'!C20/'Data Sheet'!C$17 -> 0.0070389105 | E8: ='Data Sheet'!D20/'Data Sheet'!D$17 -> 0.006555896 | F8: ='Data Sheet'!E20/'Data Sheet'!E$17 -> 0.0062177335 | G8: ='Data Sheet'!F20/'Data Sheet'!F$17 -> 0.0048383945 | H8: ='Data Sheet'!G20/'Data Sheet'!G$17 -> 0.0039631019 | I8: ='Data Sheet'!H20/'Data Sheet'!H$17 -> 0.0040283451 | J8: ='Data Sheet'!I20/'Data Sheet'!I$17 -> 0.0040097319 | ... L8: ='Data Sheet'!K20/'Data Sheet'!K$17 -> 0.0043821644
B9: ='[1]Data Sheet'!A21 -> Other Mfr. Exp | C9: ='Data Sheet'!B21/'Data Sheet'!B$17 -> 0.10757251 | D9: ='Data Sheet'!C21/'Data Sheet'!C$17 -> 0.11039378 | E9: ='Data Sheet'!D21/'Data Sheet'!D$17 -> 0.10054831 | F9: ='Data Sheet'!E21/'Data Sheet'!E$17 -> 0.096795084 | G9: ='Data Sheet'!F21/'Data Sheet'!F$17 -> 0.096288948 | H9: ='Data Sheet'!G21/'Data Sheet'!G$17 -> 0.09525768 | I9: ='Data Sheet'!H21/'Data Sheet'!H$17 -> 0.098980182 | J9: ='Data Sheet'!I21/'Data Sheet'!I$17 -> 0.084555501 | ... L9: ='Data Sheet'!K21/'Data Sheet'!K$17 -> 0.079261196
B10: ='[1]Data Sheet'!A22 -> Employee Cost | C10: ='Data Sheet'!B22/'Data Sheet'!B$17 -> 0.069718018 | D10: ='Data Sheet'!C22/'Data Sheet'!C$17 -> 0.069040678 | E10: ='Data Sheet'!D22/'Data Sheet'!D$17 -> 0.066681724 | F10: ='Data Sheet'!E22/'Data Sheet'!E$17 -> 0.064588441 | G10: ='Data Sheet'!F22/'Data Sheet'!F$17 -> 0.067846867 | H10: ='Data Sheet'!G22/'Data Sheet'!G$17 -> 0.071276423 | I10: ='Data Sheet'!H22/'Data Sheet'!H$17 -> 0.061667734 | J10: ='Data Sheet'!I22/'Data Sheet'!I$17 -> 0.059045905 | ... L10: ='Data Sheet'!K22/'Data Sheet'!K$17 -> 0.076853926
B11: ='[1]Data Sheet'!A23 -> Selling and admin | C11: ='Data Sheet'!B23/'Data Sheet'!B$17 -> 0.27413396 | D11: ='Data Sheet'!C23/'Data Sheet'!C$17 -> 0.28973861 | E11: ='Data Sheet'!D23/'Data Sheet'!D$17 -> 0.13402558 | F11: ='Data Sheet'!E23/'Data Sheet'!E$17 -> 0.12301736 | G11: ='Data Sheet'!F23/'Data Sheet'!F$17 -> 0.11436749 | H11: ='Data Sheet'!G23/'Data Sheet'!G$17 -> 0.10342706 | I11: ='Data Sheet'!H23/'Data Sheet'!H$17 -> 0.10109452 | J11: ='Data Sheet'!I23/'Data Sheet'!I$17 -> 0.10150719 | ... L11: ='Data Sheet'!K23/'Data Sheet'!K$17 -> 0.11428607
B12: ='[1]Data Sheet'!A24 -> Other Expenses | C12: ='Data Sheet'!B24/'Data Sheet'!B$17 -> -0.12470247 | D12: ='Data Sheet'!C24/'Data Sheet'!C$17 -> -0.13467477 | E12: ='Data Sheet'!D24/'Data Sheet'!D$17 -> 0.010190466 | F12: ='Data Sheet'!E24/'Data Sheet'!E$17 -> 0.010525397 | G12: ='Data Sheet'!F24/'Data Sheet'!F$17 -> 0.028939328 | H12: ='Data Sheet'!G24/'Data Sheet'!G$17 -> 0.026547947 | I12: ='Data Sheet'!H24/'Data Sheet'!H$17 -> 0.026291627 | J12: ='Data Sheet'!I24/'Data Sheet'!I$17 -> 0.027870377 | ... L12: ='Data Sheet'!K24/'Data Sheet'!K$17 -> 0.037846233
B13: ='[1]Data Sheet'!A25 -> Other Income | C13: ='Data Sheet'!B25/'Data Sheet'!B$17 -> 0.014952188 | D13: ='Data Sheet'!C25/'Data Sheet'!C$17 -> 0.022433955 | E13: ='Data Sheet'!D25/'Data Sheet'!D$17 -> 0.019995186 | F13: ='Data Sheet'!E25/'Data Sheet'!E$17 -> 0.014229114 | G13: ='Data Sheet'!F25/'Data Sheet'!F$17 -> 0.017566949 | H13: ='Data Sheet'!G25/'Data Sheet'!G$17 -> 0.015274407 | I13: ='Data Sheet'!H25/'Data Sheet'!H$17 -> 0.01016725 | J13: ='Data Sheet'!I25/'Data Sheet'!I$17 -> 0.012510224 | ... L13: ='Data Sheet'!K25/'Data Sheet'!K$17 -> 0.010329261
B14: ='[1]Data Sheet'!A26 -> Depreciation | C14: ='Data Sheet'!B26/'Data Sheet'!B$17 -> 0.019309827 | D14: ='Data Sheet'!C26/'Data Sheet'!C$17 -> 0.022227475 | E14: ='Data Sheet'!D26/'Data Sheet'!D$17 -> 0.021425239 | F14: ='Data Sheet'!E26/'Data Sheet'!E$17 -> 0.03233554 | G14: ='Data Sheet'!F26/'Data Sheet'!F$17 -> 0.038617107 | H14: ='Data Sheet'!G26/'Data Sheet'!G$17 -> 0.036442576 | I14: ='Data Sheet'!H26/'Data Sheet'!H$17 -> 0.028052374 | J14: ='Data Sheet'!I26/'Data Sheet'!I$17 -> 0.024878373 | ... L14: ='Data Sheet'!K26/'Data Sheet'!K$17 -> 0.030270498
B15: ='[1]Data Sheet'!A27 -> Interest | C15: ='Data Sheet'!B27/'Data Sheet'!B$17 -> 0.0034334187 | D15: ='Data Sheet'!C27/'Data Sheet'!C$17 -> 0.0024784242 | E15: ='Data Sheet'!D27/'Data Sheet'!D$17 -> 0.0024648505 | F15: ='Data Sheet'!E27/'Data Sheet'!E$17 -> 0.0057416452 | G15: ='Data Sheet'!F27/'Data Sheet'!F$17 -> 0.0050630218 | H15: ='Data Sheet'!G27/'Data Sheet'!G$17 -> 0.0042200933 | I15: ='Data Sheet'!H27/'Data Sheet'!H$17 -> 0.0032785499 | J15: ='Data Sheet'!I27/'Data Sheet'!I$17 -> 0.0041883417 | ... L15: ='Data Sheet'!K27/'Data Sheet'!K$17 -> 0.0066956451
B16: ='[1]Data Sheet'!A28 -> Profit before tax | C16: ='Data Sheet'!B28/'Data Sheet'!B$17 -> 0.18315186 | D16: ='Data Sheet'!C28/'Data Sheet'!C$17 -> 0.19649064 | E16: ='Data Sheet'!D28/'Data Sheet'!D$17 -> 0.18654169 | F16: ='Data Sheet'!E28/'Data Sheet'!E$17 -> 0.17183356 | G16: ='Data Sheet'!F28/'Data Sheet'!F$17 -> 0.17955545 | H16: ='Data Sheet'!G28/'Data Sheet'!G$17 -> 0.1982403 | I16: ='Data Sheet'!H28/'Data Sheet'!H$17 -> 0.14390157 | J16: ='Data Sheet'!I28/'Data Sheet'!I$17 -> 0.16494818 | ... L16: ='Data Sheet'!K28/'Data Sheet'!K$17 -> 0.15050809
... B19: ='[1]Data Sheet'!A31 -> Dividend Amount | C19: ='Data Sheet'!B31/'Data Sheet'!B$17 -> 0.050408191 | D19: ='Data Sheet'!C31/'Data Sheet'!C$17 -> 0.065594254 | E19: ='Data Sheet'!D31/'Data Sheet'!D$17 -> 0.049600138 | F19: ='Data Sheet'!E31/'Data Sheet'!E$17 -> 0.05234684 | G19: ='Data Sheet'!F31/'Data Sheet'!F$17 -> 0.056950461 | H19: ='Data Sheet'!G31/'Data Sheet'!G$17 -> 0.078855366 | I19: ='Data Sheet'!H31/'Data Sheet'!H$17 -> 0.063119904 | J19: ='Data Sheet'!I31/'Data Sheet'!I$17 -> 0.071338086 | ... L19: ='Data Sheet'!K31/'Data Sheet'!K$17 -> 0.07016005
B20: EBITDA | C20: =HistoricalFS!C12/'Data Sheet'!B17 -> 0.34037441 | D20: =HistoricalFS!D12/'Data Sheet'!C17 -> 0.35382642 | E20: =HistoricalFS!E12/'Data Sheet'!D17 -> 0.33465264 | F20: =HistoricalFS!F12/'Data Sheet'!E17 -> 0.32922439 | G20: =HistoricalFS!G12/'Data Sheet'!F17 -> 0.34897545 | H20: =HistoricalFS!H12/'Data Sheet'!G17 -> 0.35360357 | I20: =HistoricalFS!I12/'Data Sheet'!H17 -> 0.2924514 | J20: =HistoricalFS!J12/'Data Sheet'!I17 -> 0.31088224 | ... L20: =HistoricalFS!L12/'Data Sheet'!K17 -> 0.32927727
A23: # | B23: ="Common Size Balance Sheet - "&'[1]Data Sheet'!$B$1 -> Common Size Balance Sheet - ASIAN PAINTS LTD
B24: Particulars | C24: ='[1]Data Sheet'!B$16 -> 42460 | D24: ='[1]Data Sheet'!C$16 -> 42825 | E24: ='[1]Data Sheet'!D$16 -> 43190 | F24: ='[1]Data Sheet'!E$16 -> 43555 | G24: ='[1]Data Sheet'!F$16 -> 43921 | H24: ='[1]Data Sheet'!G$16 -> 44286 | I24: ='[1]Data Sheet'!H$16 -> 44651 | J24: ='[1]Data Sheet'!I$16 -> 45016 | ... L24: ='[1]Data Sheet'!K$16 -> 45747
B26: Total Liabilities | C26: ='Data Sheet'!B61/'Data Sheet'!B$61 -> 1 | D26: ='Data Sheet'!C61/'Data Sheet'!C$61 -> 1 | E26: ='Data Sheet'!D61/'Data Sheet'!D$61 -> 1 | F26: ='Data Sheet'!E61/'Data Sheet'!E$61 -> 1 | G26: ='Data Sheet'!F61/'Data Sheet'!F$61 -> 1 | H26: ='Data Sheet'!G61/'Data Sheet'!G$61 -> 1 | I26: ='Data Sheet'!H61/'Data Sheet'!H$61 -> 1 | J26: ='Data Sheet'!I61/'Data Sheet'!I$61 -> 1 | ... L26: ='Data Sheet'!K61/'Data Sheet'!K$61 -> 1
B27: ='[1]Data Sheet'!A57 -> Equity Share Capital | C27: ='Data Sheet'!B57/'Data Sheet'!B$61 -> 0.0090841678 | D27: ='Data Sheet'!C57/'Data Sheet'!C$61 -> 0.0077322476 | E27: ='Data Sheet'!D57/'Data Sheet'!D$61 -> 0.0069691677 | F27: ='Data Sheet'!E57/'Data Sheet'!E$61 -> 0.0059031906 | G27: ='Data Sheet'!F57/'Data Sheet'!F$61 -> 0.0059437463 | H27: ='Data Sheet'!G57/'Data Sheet'!G$61 -> 0.004712277 | I27: ='Data Sheet'!H57/'Data Sheet'!H$61 -> 0.004177986 | J27: ='Data Sheet'!I57/'Data Sheet'!I$61 -> 0.0037208104 | ... L27: ='Data Sheet'!K57/'Data Sheet'!K$61 -> 0.0031599147
B28: ='[1]Data Sheet'!A58 -> Reserves | C28: ='Data Sheet'!B58/'Data Sheet'!B$61 -> 0.60885328 | D28: ='Data Sheet'!C58/'Data Sheet'!C$61 -> 0.60522813 | E28: ='Data Sheet'!D58/'Data Sheet'!D$61 -> 0.60408487 | F28: ='Data Sheet'!E58/'Data Sheet'!E$61 -> 0.57694149 | G28: ='Data Sheet'!F58/'Data Sheet'!F$61 -> 0.62177833 | H28: ='Data Sheet'!G58/'Data Sheet'!G$61 -> 0.62442435 | I28: ='Data Sheet'!H58/'Data Sheet'!H$61 -> 0.59741193 | J28: ='Data Sheet'!I58/'Data Sheet'!I$61 -> 0.61663007 | ... L28: ='Data Sheet'!K58/'Data Sheet'!K$61 -> 0.6359325
B29: ='[1]Data Sheet'!A59 -> Borrowings | C29: ='Data Sheet'!B59/'Data Sheet'!B$61 -> 0.030617396 | D29: ='Data Sheet'!C59/'Data Sheet'!C$61 -> 0.045169804 | E29: ='Data Sheet'!D59/'Data Sheet'!D$61 -> 0.038756913 | F29: ='Data Sheet'!E59/'Data Sheet'!E$61 -> 0.081211951 | G29: ='Data Sheet'!F59/'Data Sheet'!F$61 -> 0.069308593 | H29: ='Data Sheet'!G59/'Data Sheet'!G$61 -> 0.053701879 | I29: ='Data Sheet'!H59/'Data Sheet'!H$61 -> 0.069119709 | J29: ='Data Sheet'!I59/'Data Sheet'!I$61 -> 0.074967813 | ... L29: ='Data Sheet'!K59/'Data Sheet'!K$61 -> 0.075449552
B30: ='[1]Data Sheet'!A60 -> Other Liabilities | C30: ='Data Sheet'!B60/'Data Sheet'!B$61 -> 0.35144516 | D30: ='Data Sheet'!C60/'Data Sheet'!C$61 -> 0.34186981 | E30: ='Data Sheet'!D60/'Data Sheet'!D$61 -> 0.35018905 | F30: ='Data Sheet'!E60/'Data Sheet'!E$61 -> 0.33594337 | G30: ='Data Sheet'!F60/'Data Sheet'!F$61 -> 0.30296933 | H30: ='Data Sheet'!G60/'Data Sheet'!G$61 -> 0.31716149 | I30: ='Data Sheet'!H60/'Data Sheet'!H$61 -> 0.32929037 | J30: ='Data Sheet'!I60/'Data Sheet'!I$61 -> 0.30468131 | ... L30: ='Data Sheet'!K60/'Data Sheet'!K$61 -> 0.28545803
B32: Total Assets | C32: ='Data Sheet'!B66/'Data Sheet'!B$66 -> 1 | D32: ='Data Sheet'!C66/'Data Sheet'!C$66 -> 1 | E32: ='Data Sheet'!D66/'Data Sheet'!D$66 -> 1 | F32: ='Data Sheet'!E66/'Data Sheet'!E$66 -> 1 | G32: ='Data Sheet'!F66/'Data Sheet'!F$66 -> 1 | H32: ='Data Sheet'!G66/'Data Sheet'!G$66 -> 1 | I32: ='Data Sheet'!H66/'Data Sheet'!H$66 -> 1 | J32: ='Data Sheet'!I66/'Data Sheet'!I$66 -> 1 | ... L32: ='Data Sheet'!K66/'Data Sheet'!K$66 -> 1
B33: ='[1]Data Sheet'!A62 -> Net Block | C33: ='Data Sheet'!B62/'Data Sheet'!B$66 -> 0.32354771 | D33: ='Data Sheet'!C62/'Data Sheet'!C$66 -> 0.26631918 | E33: ='Data Sheet'!D62/'Data Sheet'!D$66 -> 0.27116979 | F33: ='Data Sheet'!E62/'Data Sheet'!E$66 -> 0.39981685 | G33: ='Data Sheet'!F62/'Data Sheet'!F$66 -> 0.38866784 | H33: ='Data Sheet'!G62/'Data Sheet'!G$66 -> 0.28781244 | I33: ='Data Sheet'!H62/'Data Sheet'!H$66 -> 0.24039362 | J33: ='Data Sheet'!I62/'Data Sheet'!I$66 -> 0.22384057 | ... L33: ='Data Sheet'!K62/'Data Sheet'!K$66 -> 0.30373988
B34: ='[1]Data Sheet'!A63 -> Capital Work in Progress | C34: ='Data Sheet'!B63/'Data Sheet'!B$66 -> 0.010094677 | D34: ='Data Sheet'!C63/'Data Sheet'!C$66 -> 0.020760665 | E34: ='Data Sheet'!D63/'Data Sheet'!D$66 -> 0.10208973 | F34: ='Data Sheet'!E63/'Data Sheet'!E$66 -> 0.01290369 | G34: ='Data Sheet'!F63/'Data Sheet'!F$66 -> 0.0086900645 | H34: ='Data Sheet'!G63/'Data Sheet'!G$66 -> 0.0089892873 | I34: ='Data Sheet'!H63/'Data Sheet'!H$66 -> 0.018574005 | J34: ='Data Sheet'!I63/'Data Sheet'!I$66 -> 0.039550679 | ... L34: ='Data Sheet'!K63/'Data Sheet'!K$66 -> 0.041326953
B35: ='[1]Data Sheet'!A64 -> Investments | C35: ='Data Sheet'!B64/'Data Sheet'!B$66 -> 0.25685409 | D35: ='Data Sheet'!C64/'Data Sheet'!C$66 -> 0.21378068 | E35: ='Data Sheet'!D64/'Data Sheet'!D$66 -> 0.15553479 | F35: ='Data Sheet'!E64/'Data Sheet'!E$66 -> 0.15807775 | G35: ='Data Sheet'!F64/'Data Sheet'!F$66 -> 0.12509938 | H35: ='Data Sheet'!G64/'Data Sheet'!G$66 -> 0.23270552 | I35: ='Data Sheet'!H64/'Data Sheet'!H$66 -> 0.14145262 | J35: ='Data Sheet'!I64/'Data Sheet'!I$66 -> 0.165315 | ... L35: ='Data Sheet'!K64/'Data Sheet'!K$66 -> 0.15564853
B36: ='[1]Data Sheet'!A65 -> Other Assets | C36: =HistoricalFS!C59/'Data Sheet'!B$66 -> 0.067684248 | D36: =HistoricalFS!D59/'Data Sheet'!C$66 -> 0.10617895 | E36: =HistoricalFS!E59/'Data Sheet'!D$66 -> 0.1229224 | F36: =HistoricalFS!F59/'Data Sheet'!E$66 -> 0.09058862 | G36: =HistoricalFS!G59/'Data Sheet'!F$66 -> 0.10774032 | H36: =HistoricalFS!H59/'Data Sheet'!G$66 -> 0.12603671 | I36: =HistoricalFS!I59/'Data Sheet'!H$66 -> 0.12529864 | J36: =HistoricalFS!J59/'Data Sheet'!I$66 -> 0.11777536 | ... L36: =HistoricalFS!L59/'Data Sheet'!K$66 -> 0.11006366
B37: ='[1]Data Sheet'!A67 -> Receivables | C37: ='Data Sheet'!B67/'Data Sheet'!B$66 -> 0.11240048 | D37: ='Data Sheet'!C67/'Data Sheet'!C$66 -> 0.11661248 | E37: ='Data Sheet'!D67/'Data Sheet'!D$66 -> 0.12574073 | F37: ='Data Sheet'!E67/'Data Sheet'!E$66 -> 0.11738253 | G37: ='Data Sheet'!F67/'Data Sheet'!F$66 -> 0.111242 | H37: ='Data Sheet'!G67/'Data Sheet'!G$66 -> 0.12783722 | I37: ='Data Sheet'!H67/'Data Sheet'!H$66 -> 0.16862826 | J37: ='Data Sheet'!I67/'Data Sheet'!I$66 -> 0.17987046 | ... L37: ='Data Sheet'!K67/'Data Sheet'!K$66 -> 0.14210557
B38: ='[1]Data Sheet'!A68 -> Inventory | C38: ='Data Sheet'!B68/'Data Sheet'!B$66 -> 0.18924466 | D38: ='Data Sheet'!C68/'Data Sheet'!C$66 -> 0.21176137 | E38: ='Data Sheet'!D68/'Data Sheet'!D$66 -> 0.19314229 | F38: ='Data Sheet'!E68/'Data Sheet'!E$66 -> 0.19385138 | G38: ='Data Sheet'!F68/'Data Sheet'!F$66 -> 0.21005182 | H38: ='Data Sheet'!G68/'Data Sheet'!G$66 -> 0.18661442 | I38: ='Data Sheet'!H68/'Data Sheet'!H$66 -> 0.26800526 | J38: ='Data Sheet'!I68/'Data Sheet'!I$66 -> 0.24091549 | ... L38: ='Data Sheet'!K68/'Data Sheet'!K$66 -> 0.22135446
B39: ='[1]Data Sheet'!A69 -> Cash & Bank | C39: ='Data Sheet'!B69/'Data Sheet'!B$66 -> 0.040174145 | D39: ='Data Sheet'!C69/'Data Sheet'!C$66 -> 0.064586677 | E39: ='Data Sheet'!D69/'Data Sheet'!D$66 -> 0.029400268 | F39: ='Data Sheet'!E69/'Data Sheet'!E$66 -> 0.027379185 | G39: ='Data Sheet'!F69/'Data Sheet'!F$66 -> 0.048508579 | H39: ='Data Sheet'!G69/'Data Sheet'!G$66 -> 0.030004412 | I39: ='Data Sheet'!H69/'Data Sheet'!H$66 -> 0.037647609 | J39: ='Data Sheet'!I69/'Data Sheet'!I$66 -> 0.032732426 | ... L39: ='Data Sheet'!K69/'Data Sheet'!K$66 -> 0.025760947

Sheet FCF
B7: Unlevered Free Cash Flow Statement (Cr.)
B8: Years | C8: ='Data Sheet'!I16 -> 45016 | D8: ='Data Sheet'!J16 -> 45382 | E8: ='Data Sheet'!K16 -> 45747 | F8: =E8+365 -> 46112 | G8: =F8+365 -> 46477 | H8: =G8+365 -> 46842 | I8: =H8+365 -> 47207 | J8: =I8+365 -> 47572
B10: ='Data Sheet'!A17 -> Sales | C10: =IFERROR('Data Sheet'!I17,0) -> 34488.59 | D10: =IFERROR('Data Sheet'!J17,0) -> 35494.73 | E10: =IFERROR('Data Sheet'!K17,0) -> 33905.62 | F10: =E10*(1+$C$35) -> 36558.832 | G10: =F10*(1+$C$35) -> 39419.666 | H10: =G10*(1+$C$35) -> 42504.368 | I10: =H10*(1+$C$35) -> 45830.456 | J10: =I10*(1+$C$35) -> 49416.821
B11: COGS | C11: =IFERROR(SUM('Data Sheet'!I18,'Data Sheet'!I20:I22)-1*'Data Sheet'!I19,0) -> 23766.7 | D11: =IFERROR(SUM('Data Sheet'!J18,'Data Sheet'!J20:J22)-1*'Data Sheet'!J19,0) -> 23009.99 | E11: =IFERROR(SUM('Data Sheet'!K18,'Data Sheet'!K20:K22)-1*'Data Sheet'!K19,0) -> 22741.27 | F11: =E11*(1+$C$36) -> 24556.213 | G11: =F11*(1+$C$36) -> 26516.004 | H11: =G11*(1+$C$36) -> 28632.203 | I11: =H11*(1+$C$36) -> 30917.292 | J11: =I11*(1+$C$36) -> 33384.75
B13: Gross Profit | C13: =C10-C11 -> 10721.89 | D13: =D10-D11 -> 12484.74 | E13: =E10-E11 -> 11164.35 | F13: =F10-F11 -> 12002.619 | G13: =G10-G11 -> 12903.661 | H13: =H10-H11 -> 13872.165 | I13: =I10-I11 -> 14913.165 | J13: =J10-J11 -> 16032.071
B14: Selling & General Expenses | C14: =IFERROR(SUM('Data Sheet'!I23:I24),0) -> 4462.05 | D14: =IFERROR(SUM('Data Sheet'!J23:J24),0) -> 4899.76 | E14: =IFERROR(SUM('Data Sheet'!K23:K24),0) -> 5158.14 | F14: =E14*(1+$C$37) -> 5438.936 | G14: =F14*(1+$C$37) -> 5735.0178 | H14: =G14*(1+$C$37) -> 6047.2175 | I14: =H14*(1+$C$37) -> 6376.4126 | J14: =I14*(1+$C$37) -> 6723.5282
B16: EBITDA | C16: =C13-C14 -> 6259.84 | D16: =D13-D14 -> 7584.98 | E16: =E13-E14 -> 6006.21 | F16: =F13-F14 -> 6563.6828 | G16: =G13-G14 -> 7168.6437 | H16: =H13-H14 -> 7824.9473 | I16: =I13-I14 -> 8536.7521 | J16: =J13-J14 -> 9308.5431
B17: ='Data Sheet'!A27 -> Interest | C17: =IFERROR('Data Sheet'!I27,0) -> 144.45 | D17: =IFERROR('Data Sheet'!J27,0) -> 205.17 | E17: =IFERROR('Data Sheet'!K27,0) -> 227.02 | F17: =E17*(1+$C$38) -> 239.76881 | G17: =F17*(1+$C$38) -> 253.23356 | H17: =G17*(1+$C$38) -> 267.45445 | I17: =H17*(1+$C$38) -> 282.47395 | J17: =I17*(1+$C$38) -> 298.3369
B18: ='Data Sheet'!A26 -> Depreciation | C18: =IFERROR('Data Sheet'!I26,0) -> 858.02 | D18: =IFERROR('Data Sheet'!J26,0) -> 853 | E18: =IFERROR('Data Sheet'!K26,0) -> 1026.34 | F18: =E18*(1+$C$39) -> 1099.4069 | G18: =F18*(1+$C$39) -> 1177.6756 | H18: =G18*(1+$C$39) -> 1261.5164 | I18: =H18*(1+$C$39) -> 1351.3259 | J18: =I18*(1+$C$39) -> 1447.5292
B20: EBIT | C20: =C16-C18 -> 5401.82 | D20: =D16-D18 -> 6731.98 | E20: =E16-E18 -> 4979.87 | F20: =F16-F18 -> 5464.2759 | G20: =G16-G18 -> 5990.9681 | H20: =H16-H18 -> 6563.431 | I20: =I16-I18 -> 7185.4262 | J20: =J16-J18 -> 7861.014
B22: EBT | C22: =C16-SUM(C17:C18) -> 5257.37 | D22: =D16-SUM(D17:D18) -> 6526.81 | E22: =E16-SUM(E17:E18) -> 4752.85 | F22: =F16-SUM(F17:F18) -> 5224.5071 | G22: =G16-SUM(G17:G18) -> 5737.7345 | H22: =H16-SUM(H17:H18) -> 6295.9765 | I22: =I16-SUM(I17:I18) -> 6902.9522 | J22: =J16-SUM(J17:J18) -> 7562.6771
B23: Tax | C23: 0.25 | D23: 0.25 | E23: 0.25 | F23: 0.25 | G23: 0.25 | H23: 0.25 | I23: 0.25 | J23: 0.25
B25: NOPAT | C25: =C20*(1-C23) -> 4051.365 | D25: =D20*(1-D23) -> 5048.985 | E25: =E20*(1-E23) -> 3734.9025 | F25: =F20*(1-F23) -> 4098.2069 | G25: =G20*(1-G23) -> 4493.226 | H25: =H20*(1-H23) -> 4922.5732 | I25: =I20*(1-I23) -> 5389.0696 | J25: =J20*(1-J23) -> 5895.7605
B26: Add: Depriciation and amortisation | C26: =C18 -> 858.02 | D26: =D18 -> 853 | E26: =E18 -> 1026.34 | F26: =F18 -> 1099.4069 | G26: =G18 -> 1177.6756 | H26: =H18 -> 1261.5164 | I26: =I18 -> 1351.3259 | J26: =J18 -> 1447.5292
B27: Less: Capital Expenditure | C27: =IFERROR(-SUM('Raw CF'!L13:L14),0) -> 1420 | D27: =IFERROR(-SUM('Raw CF'!M13:M14),0) -> 2491 | E27: =IFERROR(-SUM('Raw CF'!N13:N14),0) -> 1820 | F27: ='Fixed Assets'!F7 -> 2478.7781 | G27: ='Fixed Assets'!G7 -> 2688.4951 | H27: ='Fixed Assets'!H7 -> 2915.9553 | I27: ='Fixed Assets'!I7 -> 3162.6597 | J27: ='Fixed Assets'!J7 -> 3430.2366
B28: Less: Change in Working Capital | D28: ='Change in WC'!D17 -> -56 | E28: ='Change in WC'!E17 -> 5 | F28: ='Change in WC'!F17 -> 387.58802 | G28: ='Change in WC'!G17 -> 546.32688 | H28: ='Change in WC'!H17 -> 589.40933 | I28: ='Change in WC'!I17 -> 635.88951 | J28: ='Change in WC'!J17 -> 686.0354
B30: Unlevered Free Cash Flow | D30: =D25+D26-D27-D28 -> 3466.985 | E30: =E25+E26-E27-E28 -> 2936.2425 | F30: =F25+F26-F27-F28 -> 2331.2477 | G30: =G25+G26-G27-G28 -> 2436.0796 | H30: =H25+H26-H27-H28 -> 2678.725 | I30: =I25+I26-I27-I28 -> 2941.8463 | J30: =J25+J26-J27-J28 -> 3227.0177
B33: Forecasts %
B35: Sales Growth % | C35: =Forecasts!C21 -> 0.07825287
B36: COGS Growth % | C36: =Forecasts!G21 -> 0.079808351
B37: Selling & General Exp. Growth % | C37: =Forecasts!K21 -> 0.054437449
B38: Interest Growth % | C38: =Forecasts!O21 -> 0.056157217
B39: Depriciation Growth % | C39: =Forecasts!S21 -> 0.071191734

Sheet Forecasts
B2: Sales Forecasting | F2: COGS Forecasting | J2: S&G Expenses Forecasting | N2: Interest Forecasting | R2: Depriciation Forecasting
B3: Fiscal Years | C3: Sales | D3: Growth % | F3: Fiscal Years | G3: COGS | H3: Growth % | J3: Fiscal Years | K3: Expenses | L3: Growth % | N3: Fiscal Years | O3: Interests | P3: Growth % | R3: Fiscal Years | S3: Interests | T3: Growth %
B5: 2016 | C5: {=IFERROR(TRANSPOSE('Data Sheet'!B17:K17),0)} -> 14271.49 | D5: =0 -> 0 | F5: 2016 | G5: {=IFERROR(TRANSPOSE(HistoricalFS!C9:L9),0)} -> 9413.84 | H5: =0 -> 0 | J5: 2016 | K5: {=IFERROR(TRANSPOSE(HistoricalFS!C15:L15),0)} -> 2132.61 | L5: =0 -> 0 | N5: 2016 | O5: {=IFERROR(TRANSPOSE(HistoricalFS!C21:L21),0)} -> 49 | P5: =0 -> 0 | R5: 2016 | S5: {=IFERROR(TRANSPOSE(HistoricalFS!C24:L24),0)} -> 275.58 | T5: =0 -> 0
B6: 2017 | C6: 15061.99 | D6: =C6/C5-1 -> 0.055390152 | F6: 2017 | G6: 9732.66 | H6: =G6/G5-1 -> 0.033867157 | J6: 2017 | K6: 2335.57 | L6: =K6/K5-1 -> 0.095169768 | N6: 2017 | O6: 37.33 | P6: =O6/O5-1 -> -0.23816327 | R6: 2017 | S6: 334.79 | T6: =S6/S5-1 -> 0.21485594
B7: 2018 | C7: 16824.55 | D7: =C7/C6-1 -> 0.11702039 | F7: 2018 | G7: 11194.17 | H7: =G7/G6-1 -> 0.15016553 | J7: 2018 | K7: 2426.37 | L7: =K7/K6-1 -> 0.038877019 | N7: 2018 | O7: 41.47 | P7: =O7/O6-1 -> 0.11090276 | R7: 2018 | S7: 360.47 | T7: =S7/S6-1 -> 0.0767048
B8: 2019 | C8: 19240.13 | D8: =C8/C7-1 -> 0.14357472 | F8: 2019 | G8: 12905.81 | H8: =G8/G7-1 -> 0.15290459 | J8: 2019 | K8: 2569.38 | L8: =K8/K7-1 -> 0.058939898 | N8: 2019 | O8: 110.47 | P8: =O8/O7-1 -> 1.6638534 | R8: 2019 | S8: 622.14 | T8: =S8/S7-1 -> 0.72591339
B9: 2020 | C9: 20211.25 | D9: =C9/C8-1 -> 0.050473671 | F9: 2020 | G9: 13158.02 | H9: =G9/G8-1 -> 0.019542361 | J9: 2020 | K9: 2896.41 | L9: =K9/K8-1 -> 0.12727973 | N9: 2020 | O9: 102.33 | P9: =O9/O8-1 -> -0.073685163 | R9: 2020 | S9: 780.5 | T9: =S9/S8-1 -> 0.25454078
B10: 2021 | C10: 21712.79 | D10: =C10/C9-1 -> 0.074292288 | F10: 2021 | G10: 14035.07 | H10: =G10/G9-1 -> 0.066655165 | J10: 2021 | K10: 2822.12 | L10: =K10/K9-1 -> -0.025648993 | N10: 2021 | O10: 91.63 | P10: =O10/O9-1 -> -0.10456367 | R10: 2021 | S10: 791.27 | T10: =S10/S9-1 -> 0.013798847
B11: 2022 | C11: 29101.28 | D11: =C11/C10-1 -> 0.34028285 | F11: 2022 | G11: 20590.57 | H11: =G11/G10-1 -> 0.46707996 | J11: 2022 | K11: 3707.1 | L11: =K11/K10-1 -> 0.31358695 | N11: 2022 | O11: 95.41 | P11: =O11/O10-1 -> 0.041252865 | R11: 2022 | S11: 816.36 | T11: =S11/S10-1 -> 0.031708519
B12: 2023 | C12: 34488.59 | D12: =C12/C11-1 -> 0.18512278 | F12: 2023 | G12: 23766.7 | H12: =G12/G11-1 -> 0.15425168 | J12: 2023 | K12: 4462.05 | L12: =K12/K11-1 -> 0.20364975 | N12: 2023 | O12: 144.45 | P12: =O12/O11-1 -> 0.51399224 | R12: 2023 | S12: 858.02 | T12: =S12/S11-1 -> 0.051031408
B13: 2024 | C13: 35494.73 | D13: =C13/C12-1 -> 0.029173127 | F13: 2024 | G13: 23009.99 | H13: =G13/G12-1 -> -0.031839086 | J13: 2024 | K13: 4899.76 | L13: =K13/K12-1 -> 0.098096167 | N13: 2024 | O13: 205.17 | P13: =O13/O12-1 -> 0.42035306 | R13: 2024 | S13: 853 | T13: =S13/S12-1 -> -0.0058506795
B14: 2025 | C14: 33905.62 | D14: =C14/C13-1 -> -0.044770308 | F14: 2025 | G14: 22741.27 | H14: =G14/G13-1 -> -0.011678406 | J14: 2025 | K14: 5158.14 | L14: =K14/K13-1 -> 0.052733195 | N14: 2025 | O14: 227.02 | P14: =O14/O13-1 -> 0.10649705 | R14: 2025 | S14: 1026.34 | T14: =S14/S13-1 -> 0.20321219
B15: 2026 | C15: =FORECAST(B15,_xlfn.ANCHORARRAY($C$5),$B$5:B14) -> 38669.293 | D15: =C15/C14-1 -> 0.14049805 | F15: 2026 | G15: =FORECAST(F15,$G$5:G14,$F$5:F14) -> 26044.215 | H15: =G15/G14-1 -> 0.14524014 | J15: 2026 | K15: =FORECAST(J15,$K$5:K14,$J$5:J14) -> 5297.4967 | L15: =K15/K14-1 -> 0.027016845 | N15: 2026 | O15: =FORECAST(N15,$O$5:O14,$N$5:N14) -> 218.29733 | P15: =O15/O14-1 -> -0.038422459 | R15: 2026 | S15: =FORECAST(R15,$S$5:S14,$R$5:R14) -> 1120.6967 | T15: =S15/S14-1 -> 0.091935096
B16: 2027 | C16: =FORECAST(B16,$C$5:C15,$B$5:B15) -> 41330.757 | D16: =C16/C15-1 -> 0.068826287 | F16: 2027 | G16: =FORECAST(F16,$G$5:G15,$F$5:F15) -> 27860.471 | H16: =G16/G15-1 -> 0.069737387 | J16: 2027 | K16: =FORECAST(J16,$K$5:K15,$J$5:J15) -> 5653.2322 | L16: =K16/K15-1 -> 0.067151637 | N16: 2027 | O16: =FORECAST(N16,$O$5:O15,$N$5:N15) -> 237.90994 | P16: =O16/O15-1 -> 0.089843544 | R16: 2027 | S16: =FORECAST(R16,$S$5:S15,$R$5:R15) -> 1202.3057 | T16: =S16/S15-1 -> 0.07281991
B17: 2028 | C17: =FORECAST(B17,$C$5:C16,$B$5:B16) -> 43992.221 | D17: =C17/C16-1 -> 0.064394269 | F17: 2028 | G17: =FORECAST(F17,$G$5:G16,$F$5:F16) -> 29676.726 | H17: =G17/G16-1 -> 0.065191128 | J17: 2028 | K17: =FORECAST(J17,$K$5:K16,$J$5:J16) -> 6008.9678 | L17: =K17/K16-1 -> 0.06292605 | N17: 2028 | O17: =FORECAST(N17,$O$5:O16,$N$5:N16) -> 257.52255 | P17: =O17/O16-1 -> 0.082437103 | R17: 2028 | S17: =FORECAST(R17,$S$5:S16,$R$5:R16) -> 1283.9147 | T17: =S17/S16-1 -> 0.067877105
B18: 2029 | C18: =FORECAST(B18,$C$5:C17,$B$5:B17) -> 46653.685 | D18: =C18/C17-1 -> 0.060498511 | F18: 2029 | G18: =FORECAST(F18,$G$5:G17,$F$5:F17) -> 31492.982 | H18: =G18/G17-1 -> 0.061201343 | J18: 2029 | K18: =FORECAST(J18,$K$5:K17,$J$5:J17) -> 6364.7034 | L18: =K18/K17-1 -> 0.059200779 | N18: 2029 | O18: =FORECAST(N18,$O$5:O17,$N$5:N17) -> 277.13515 | P18: =O18/O17-1 -> 0.076158792 | R18: 2029 | S18: =FORECAST(R18,$S$5:S17,$R$5:R17) -> 1365.5238 | T18: =S18/S17-1 -> 0.063562656
B19: 2030 | C19: =FORECAST(B19,$C$5:C18,$B$5:B18) -> 49315.149 | D19: =C19/C18-1 -> 0.057047238 | F19: 2030 | G19: =FORECAST(F19,$G$5:G18,$F$5:F18) -> 33309.237 | H19: =G19/G18-1 -> 0.057671754 | J19: 2030 | K19: =FORECAST(J19,$K$5:K18,$J$5:J18) -> 6720.439 | L19: =K19/K18-1 -> 0.055891933 | N19: 2030 | O19: =FORECAST(N19,$O$5:O18,$N$5:N18) -> 296.74776 | P19: =O19/O18-1 -> 0.070769103 | R19: 2030 | S19: =FORECAST(R19,$S$5:S18,$R$5:R18) -> 1447.1328 | T19: =S19/S18-1 -> 0.059763904
B21: Average | C21: =AVERAGE(D15:D19) -> 0.07825287 | F21: Average | G21: =AVERAGE(H15:H19) -> 0.079808351 | J21: Average | K21: =AVERAGE(L15:L19) -> 0.054437449 | N21: Average | O21: =AVERAGE(P15:P19) -> 0.056157217 | R21: Average | S21: =AVERAGE(T15:T19) -> 0.071191734
B22: Median | C22: =MEDIAN(D15:D19) -> 0.064394269 | F22: Median | G22: =MEDIAN(H15:H19) -> 0.065191128 | J22: Median | K22: =MEDIAN(L15:L19) -> 0.059200779 | N22: Median | O22: =MEDIAN(P15:P19) -> 0.076158792 | R22: Median | S22: =MEDIAN(T15:T19) -> 0.067877105

Sheet Change in WC
B2: Change in Working capital (Cr.)
B3: Years | C3: =FCF!C8 -> 45016 | D3: =FCF!D8 -> 45382 | E3: =FCF!E8 -> 45747 | F3: =FCF!F8 -> 46112 | G3: =FCF!G8 -> 46477 | H3: =FCF!H8 -> 46842 | I3: =FCF!I8 -> 47207 | J3: =FCF!J8 -> 47572
B5: ='Raw Bs'!B35 -> Trade receivables | C5: ='Raw Bs'!L35 -> 4637 | D5: ='Raw Bs'!M35 -> 4889 | E5: ='Raw Bs'!N35 -> 4314 | F5: =F21*F23/360 -> 4867.4985 | G5: =G21*G23/360 -> 5248.3943 | H5: =H21*H23/360 -> 5659.0962 | I5: =I21*I23/360 -> 6101.9367 | J5: =J21*J23/360 -> 6579.4307
B6: ='Raw Bs'!B34 -> Inventories | C6: ='Raw Bs'!L34 -> 6211 | D6: ='Raw Bs'!M34 -> 5923 | E6: ='Raw Bs'!N34 -> 6719 | F6: =F22*F24/360 -> 6664.5235 | G6: =G22*G24/360 -> 7196.4082 | H6: =H22*H24/360 -> 7770.7417 | I6: =I22*I24/360 -> 8390.9117 | J6: =J22*J24/360 -> 9060.5766
B7: ='Raw Bs'!B37 -> Loans n Advances | C7: ='Raw Bs'!L37 -> 12 | D7: ='Raw Bs'!M37 -> 17 | E7: ='Raw Bs'!N37 -> 22 | F7: =F21*$F26 -> 17.983844 | G7: =G21*$F26 -> 19.391131 | H7: =H21*$F26 -> 20.908543 | I7: =I21*$F26 -> 22.544696 | J7: =J21*$F26 -> 24.308883
B8: ='Raw Bs'!B38 -> Other asset items | C8: ='Raw Bs'!L38 -> 3024 | D8: ='Raw Bs'!M38 -> 3555 | E8: ='Raw Bs'!N38 -> 3319 | F8: =F21*$F27 -> 3481.9395 | G8: =G21*$F27 -> 3754.4112 | H8: =H21*$F27 -> 4048.2047 | I8: =I21*$F27 -> 4364.9883 | J8: =J21*$F27 -> 4706.5612
B9: Current Assets | C9: =SUM(C5:C8) -> 13884 | D9: =SUM(D5:D8) -> 14384 | E9: =SUM(E5:E8) -> 14374 | F9: =SUM(F5:F8) -> 15031.945 | G9: =SUM(G5:G8) -> 16218.605 | H9: =SUM(H5:H8) -> 17498.951 | I9: =SUM(I5:I8) -> 18880.381 | J9: =SUM(J5:J8) -> 20370.877
B11: Trade Payables | C11: ='Raw Bs'!L13 -> 3635 | D11: ='Raw Bs'!M13 -> 3831 | E11: ='Raw Bs'!N13 -> 3848 | F11: =F25*F22/360 -> 3999.7633 | G11: =G25*G22/360 -> 4318.9778 | H11: =H25*H22/360 -> 4663.6683 | I11: =I25*I22/360 -> 5035.868 | J11: =J25*J22/360 -> 5437.7723
B12: Other Current Liabilities | C12: ='Raw Bs'!L15 -> 3657 | D12: ='Raw Bs'!M15 -> 4017 | E12: ='Raw Bs'!N15 -> 3985 | F12: =F$21*F28 -> 4103.5941 | G12: =G$21*G28 -> 4424.7121 | H12: =H$21*H28 -> 4770.9585 | I12: =I$21*I28 -> 5144.2997 | J12: =J$21*J28 -> 5546.8559
B13: Current Liabilities | C13: =SUM(C11:C12) -> 7292 | D13: =SUM(D11:D12) -> 7848 | E13: =SUM(E11:E12) -> 7833 | F13: =SUM(F11:F12) -> 8103.3574 | G13: =SUM(G11:G12) -> 8743.6899 | H13: =SUM(H11:H12) -> 9434.6268 | I13: =SUM(I11:I12) -> 10180.168 | J13: =SUM(J11:J12) -> 10984.628
B15: Working Capital | C15: =C9-C13 -> 6592 | D15: =D9-D13 -> 6536 | E15: =E9-E13 -> 6541 | F15: =F9-F13 -> 6928.588 | G15: =G9-G13 -> 7474.9149 | H15: =H9-H13 -> 8064.3242 | I15: =I9-I13 -> 8700.2137 | J15: =J9-J13 -> 9386.2491
B17: ΔWC | C17: 0 | D17: =D15-C15 -> -56 | E17: =E15-D15 -> 5 | F17: =F15-E15 -> 387.58802 | G17: =G15-F15 -> 546.32688 | H17: =H15-G15 -> 589.40933 | I17: =I15-H15 -> 635.88951 | J17: =J15-I15 -> 686.0354
B19: Working capital Assumptions
B20: =B3 -> Years | C20: =C3 -> 45016 | D20: =D3 -> 45382 | E20: =E3 -> 45747 | F20: =F3 -> 46112 | G20: =G3 -> 46477 | H20: =H3 -> 46842 | I20: =I3 -> 47207 | J20: =J3 -> 47572
B21: Revenue | C21: =FCF!C10 -> 34488.59 | D21: =FCF!D10 -> 35494.73 | E21: =FCF!E10 -> 33905.62 | F21: =FCF!F10 -> 36558.832 | G21: =FCF!G10 -> 39419.666 | H21: =FCF!H10 -> 42504.368 | I21: =FCF!I10 -> 45830.456 | J21: =FCF!J10 -> 49416.821
B22: COGS | C22: =FCF!C11 -> 23766.7 | D22: =FCF!D11 -> 23009.99 | E22: =FCF!E11 -> 22741.27 | F22: =FCF!F11 -> 24556.213 | G22: =FCF!G11 -> 26516.004 | H22: =FCF!H11 -> 28632.203 | I22: =FCF!I11 -> 30917.292 | J22: =FCF!J11 -> 33384.75
B23: Debtors Days | C23: =C5/C21*360 -> 48.402095 | D23: =D5/D21*360 -> 49.585953 | E23: =E5/E21*360 -> 45.804796 | F23: =AVERAGE(C23:E23) -> 47.930948 | G23: =F23 -> 47.930948 | H23: =G23 -> 47.930948 | I23: =H23 -> 47.930948 | J23: =I23 -> 47.930948
B24: Inventory Days | C24: =C6/C22*360 -> 94.079531 | D24: =D6/D22*360 -> 92.667576 | E24: =E6/E22*360 -> 106.36345 | F24: =AVERAGE(C24:E24) -> 97.70352 | G24: =F24 -> 97.70352 | H24: =G24 -> 97.70352 | I24: =H24 -> 97.70352 | J24: =I24 -> 97.70352
B25: Days Payable | C25: =C11/C22*360 -> 55.060231 | D25: =D11/D22*360 -> 59.937445 | E25: =E11/E22*360 -> 60.914804 | F25: =AVERAGE(C25:E25) -> 58.637493 | G25: =F25 -> 58.637493 | H25: =G25 -> 58.637493 | I25: =H25 -> 58.637493 | J25: =I25 -> 58.637493
B26: Loans n Advances % of Revenue | C26: =C7/C21 -> 0.00034794116 | D26: =D7/D21 -> 0.00047894434 | E26: =E7/E21 -> 0.00064885998 | F26: =AVERAGE($C$26:E26) -> 0.00049191516 | G26: =AVERAGE($C$26:F26) -> 0.00049191516 | H26: =AVERAGE($C$26:G26) -> 0.00049191516 | I26: =AVERAGE($C$26:H26) -> 0.00049191516 | J26: =AVERAGE($C$26:I26) -> 0.00049191516
B27: OCA % of Revenue | C27: =C8/C21 -> 0.087681172 | D27: =D8/D21 -> 0.10015571 | E27: =E8/E21 -> 0.097889376 | F27: =AVERAGE($C$27:E27) -> 0.095242087 | G27: =AVERAGE($C$27:F27) -> 0.095242087 | H27: =AVERAGE($C$27:G27) -> 0.095242087 | I27: =AVERAGE($C$27:H27) -> 0.095242087 | J27: =AVERAGE($C$27:I27) -> 0.095242087
B28: OCL % of Revenue | C28: =C12/C$21 -> 0.10603507 | D28: =D12/D$21 -> 0.11317173 | E28: =E12/E$21 -> 0.11753214 | F28: =AVERAGE($C$28:E28) -> 0.11224631 | G28: =AVERAGE($C$28:F28) -> 0.11224631 | H28: =AVERAGE($C$28:G28) -> 0.11224631 | I28: =AVERAGE($C$28:H28) -> 0.11224631 | J28: =AVERAGE($C$28:I28) -> 0.11224631

Sheet Fixed Assets
B3: Fixed Assests(Cr.)
B4: Years | C4: ='Data Sheet'!I16 -> 45016 | D4: ='Data Sheet'!J16 -> 45382 | E4: ='Data Sheet'!K16 -> 45747 | F4: =E4+365 -> 46112 | G4: =F4+365 -> 46477 | H4: =G4+365 -> 46842 | I4: =H4+365 -> 47207 | J4: =I4+365 -> 47572
B5: Beginning PP&E | C5: =IFERROR('Raw Bs'!L27,0) -> 9676 | D5: =IFERROR('Raw Bs'!M27,0) -> 11622 | E5: =IFERROR('Raw Bs'!N27,0) -> 14484 | F5: =E8 -> 15277.66 | G5: =F8 -> 16570.227 | H5: =G8 -> 17972.151 | I5: =H8 -> 19492.685 | J5: =I8 -> 21141.863
B6: D&A | C6: =IFERROR('Data Sheet'!I26,0) -> 858.02 | D6: =IFERROR('Data Sheet'!J26,0) -> 853 | E6: =IFERROR('Data Sheet'!K26,0) -> 1026.34 | F6: =F13*F5 -> 1186.2116 | G6: =G13*G5 -> 1286.571 | H6: =H13*H5 -> 1395.4214 | I6: =I13*I5 -> 1513.481 | J6: =J13*J5 -> 1641.5291
B7: Cap. Exp. | C7: =FCF!C27 -> 1420 | D7: =FCF!D27 -> 2491 | E7: =FCF!E27 -> 1820 | F7: =F14*F5 -> 2478.7781 | G7: =G14*G5 -> 2688.4951 | H7: =H14*H5 -> 2915.9553 | I7: =I14*I5 -> 3162.6597 | J7: =J14*J5 -> 3430.2366
B8: Ending PP&E | C8: =C5-C6+C7 -> 10237.98 | D8: =D5-D6+D7 -> 13260 | E8: =E5-E6+E7 -> 15277.66 | F8: =F5+F7-F6 -> 16570.227 | G8: =G5+G7-G6 -> 17972.151 | H8: =H5+H7-H6 -> 19492.685 | I8: =I5+I7-I6 -> 21141.863 | J8: =J5+J7-J6 -> 22930.571
B11: Assumptions
B12: =B4 -> Years | C12: =C4 -> 45016 | D12: =D4 -> 45382 | E12: =E4 -> 45747 | F12: =F4 -> 46112 | G12: =G4 -> 46477 | H12: =H4 -> 46842 | I12: =I4 -> 47207 | J12: =J4 -> 47572
B13: D&A as a % of Beginning PP&E | C13: =C6/C5 -> 0.088675072 | D13: =D6/D5 -> 0.073395285 | E13: =E6/E5 -> 0.07086026 | F13: =AVERAGE($C$13:E13) -> 0.077643539 | G13: =AVERAGE($C$13:F13) -> 0.077643539 | H13: =AVERAGE($C$13:G13) -> 0.077643539 | I13: =AVERAGE($C$13:H13) -> 0.077643539 | J13: =AVERAGE($C$13:I13) -> 0.077643539
B14: Cap. Exp. as a % of Beginning PP&E | C14: =C7/C5 -> 0.14675486 | D14: =D7/D5 -> 0.21433488 | E14: =E7/E5 -> 0.1256559 | F14: =AVERAGE($C$14:E14) -> 0.16224855 | G14: =AVERAGE($C$14:F14) -> 0.16224855 | H14: =AVERAGE($C$14:G14) -> 0.16224855 | I14: =AVERAGE($C$14:H14) -> 0.16224855 | J14: =AVERAGE($C$14:I14) -> 0.16224855

Sheet WACC
B2: Particulars | C2: FY2025
B4: Interest Expense | C4: ='Data Sheet'!K27 -> 227.02
B5: 10-year government bonds Rate | C5: 0.065
B6: Beta of Asian Paints LTD. | C6: 1.27
B7: Market Return | C7: 0.12
B8: Market Premium | C8: =C7-C5 -> 0.055
B10: Weighted Average Cost of Capital (WACC)
B12: Equity | C12: ='Data Sheet'!B9 -> 235134.19
B13: Debt | C13: ='Data Sheet'!K59 -> 2290.29
B14: Company's Valuation (V) | C14: =SUM(C12:C13) -> 237424.48
B15: Cost of Debt | C15: =C4/C13 -> 0.099122819
B16: Tax Rate | C16: 0.25
B17: D/V | C17: =C13/C14 -> 0.0096463937
B18: Cost of Equity | C18: =C5+C6*C8 -> 0.13485
B19: E/V | C19: =C12/C14 -> 0.99035361
B21: WACC | C21: =(C19*C18)+(C17*C15*(1-C16)) -> 0.13426632

Sheet DCF
B2: Unlevered Free Cash Flow (Cr.)
B3: Years | C3: ='Data Sheet'!I16 -> 45016 | D3: ='Data Sheet'!J16 -> 45382 | E3: ='Data Sheet'!K16 -> 45747 | F3: =E3+365 -> 46112 | G3: =F3+365 -> 46477 | H3: =G3+365 -> 46842 | I3: =H3+365 -> 47207 | J3: =I3+365 -> 47572
B4: Unlevered Free Cash Flow | C4: 0 | D4: =FCF!D30 -> 3466.985 | E4: =FCF!E30 -> 2936.2425 | F4: =FCF!F30 -> 2331.2477 | G4: =FCF!G30 -> 2436.0796 | H4: =FCF!H30 -> 2678.725 | I4: =FCF!I30 -> 2941.8463 | J4: =FCF!J30 -> 3227.0177
B6: Year- End Convention | F6: =IF(B6="mid-year convention",0.5,1) -> 1 | G6: =F6+1 -> 2 | H6: =G6+1 -> 3 | I6: =H6+1 -> 4 | J6: =I6+1 -> 5
B7: PV of Free Cash Flow | F7: =F4/(1+$C$13)^F6 -> 2055.2913 | G7: =G4/(1+$C$13)^G6 -> 1893.483 | H7: =H4/(1+$C$13)^H6 -> 1835.621 | I7: =I4/(1+$C$13)^I6 -> 1777.2963 | J7: =J4/(1+$C$13)^J6 -> 1718.8033
B10: Implied Share Price Calculations
B11: Sum of PV of FCF | C11: =SUM(F7:J7) -> 9280.4949
B12: Growth Rate | C12: 0.06
B13: WACC | C13: =WACC!C21 -> 0.13426632
B14: Terminal Value | C14: =(J4*(1+C12))/(C13-C12) -> 46059.087
B15: PV of Terminal value | C15: =C14/(1+C13) -> 40606.942
B16: Enterprise Value | C16: =C15+C11 -> 49887.437
B17: Add: Cash & Cash Equivalents | C17: ='Data Sheet'!K69 -> 781.98
B18: Less: Debt | C18: ='Data Sheet'!K59 -> 2290.29
B19: Equity Value | C19: =C16+C17-C18 -> 48379.127
B20: Total shares | C20: ='Data Sheet'!B6 -> 95.980974
B22: Implied Share Value | C22: =C19/C20 -> 504.04914
B24: Share Price | C24: ='Data Sheet'!B8 -> 2449.8
B25: =IF(C24>C22, "Premium", "Discount") -> Premium | C25: =C24/C22 -> 4.8602404

Sheet Data Sources-->

Sheet Data Sheet
A1: COMPANY NAME | B1: ASIAN PAINTS LTD | E1: =IF(B2<>B3, "A NEW VERSION OF THE WORKSHEET IS AVAILABLE", "")
A2: LATEST VERSION | B2: 2.1 | E2: PLEASE DO NOT MAKE ANY CHANGES TO THIS SHEET
A3: CURRENT VERSION | B3: 2.1
A5: META
A6: Number of shares | B6: =IF(B9>0, B9/B8, 0) -> 95.980974
A7: Face Value | B7: 1
A8: Current Price | B8: 2449.8
A9: Market Capitalization | B9: 235134.19
A15: PROFIT & LOSS
A16: Report Date | B16: 42460 | C16: 42825 | D16: 43190 | E16: 43555 | F16: 43921 | G16: 44286 | H16: 44651 | I16: 45016 | J16: 45382 | K16: 45747
A17: Sales | B17: 14271.49 | C17: 15061.99 | D17: 16824.55 | E17: 19240.13 | F17: 20211.25 | G17: 21712.79 | H17: 29101.28 | I17: 34488.59 | J17: 35494.73 | K17: 33905.62
A18: Raw Material Cost | B18: 6569.83 | C18: 7452.6 | D18: 8128.17 | E18: 9974.4 | F18: 9981.99 | G18: 10425.55 | H18: 17123.25 | I18: 18985.53 | J18: 17410.84 | K18: 17504.51
A19: Change in Inventory | B19: -199.33 | C19: 528.6 | D19: -142.13 | E19: 293.26 | F19: 239.15 | G19: 92.45 | H19: 1324.97 | I19: 309.73 | J19: -363.8 | K19: 205
A20: Power and Fuel | B20: 114.48 | C20: 106.02 | D20: 110.3 | E20: 119.63 | F20: 97.79 | G20: 86.05 | H20: 117.23 | I20: 138.29 | J20: 133.25 | K20: 148.58
A21: Other Mfr. Exp | B21: 1535.22 | C21: 1662.75 | D21: 1691.68 | E21: 1862.35 | F21: 1946.12 | G21: 2068.31 | H21: 2880.45 | I21: 2916.2 | J21: 2767.18 | K21: 2687.4
A22: Employee Cost | B22: 994.98 | C22: 1039.89 | D22: 1121.89 | E22: 1242.69 | F22: 1371.27 | G22: 1547.61 | H22: 1794.61 | I22: 2036.41 | J22: 2334.92 | K22: 2605.78
A23: Selling and admin | B23: 3912.3 | C23: 4364.04 | D23: 2254.92 | E23: 2366.87 | F23: 2311.51 | G23: 2245.69 | H23: 2941.98 | I23: 3500.84 | J23: 3811.86 | K23: 3874.94
A24: Other Expenses | B24: -1779.69 | C24: -2028.47 | D24: 171.45 | E24: 202.51 | F24: 584.9 | G24: 576.43 | H24: 765.12 | I24: 961.21 | J24: 1087.9 | K24: 1283.2
A25: Other Income | B25: 213.39 | C25: 337.9 | D25: 336.41 | E25: 273.77 | F25: 355.05 | G25: 331.65 | H25: 295.88 | I25: 431.46 | J25: 820.96 | K25: 350.22
A26: Depreciation | B26: 275.58 | C26: 334.79 | D26: 360.47 | E26: 622.14 | F26: 780.5 | G26: 791.27 | H26: 816.36 | I26: 858.02 | J26: 853 | K26: 1026.34
A27: Interest | B27: 49 | C27: 37.33 | D27: 41.47 | E27: 110.47 | F27: 102.33 | G27: 91.63 | H27: 95.41 | I27: 144.45 | J27: 205.17 | K27: 227.02
... A31: Dividend Amount | B31: 719.4 | C31: 987.98 | D31: 834.5 | E31: 1007.16 | F31: 1151.04 | G31: 1712.17 | H31: 1836.87 | I31: 2460.35 | J31: 3194.14 | K31: 2378.82
A40: Quarters
A41: Report Date | B41: 45016 | C41: 45107 | D41: 45199 | E41: 45291 | F41: 45382 | G41: 45473 | H41: 45565 | I41: 45657 | J41: 45747 | K41: 45838
A42: Sales | B42: 8787.34 | C42: 9182.31 | D42: 8478.57 | E42: 9103.09 | F42: 8730.76 | G42: 8969.73 | H42: 8027.54 | I42: 8549.44 | J42: 8358.91 | K42: 8938.55
A43: Expenses | B43: 6922.58 | C43: 7061.02 | D43: 6762.34 | E43: 7047 | F43: 7039.39 | G43: 7275.96 | H43: 6788.03 | I43: 6912.71 | J43: 6922.71 | K43: 7313.58
A44: Other Income | B44: 104.17 | C44: 227.74 | D44: 194.33 | E44: 186.46 | F44: 212.43 | G44: 192.93 | H44: 24.53 | I44: 192.82 | J44: -60.06 | K44: 229.11
A45: Depreciation | B45: 220.17 | C45: 198.32 | D45: 208.72 | E45: 220.35 | F45: 225.61 | G45: 227.7 | H45: 241.99 | I45: 255.55 | J45: 301.1 | K45: 300.87
A46: Interest | B46: 38.91 | C46: 45.75 | D46: 50.9 | E46: 54.42 | F46: 54.1 | G46: 55.38 | H46: 63.01 | I46: 55.84 | J46: 52.79 | K46: 44.5
A47: Profit before tax | B47: 1709.85 | C47: 2104.96 | D47: 1650.94 | E47: 1967.78 | F47: 1624.09 | G47: 1603.62 | H47: 959.04 | I47: 1518.16 | J47: 1022.25 | K47: 1508.71
A48: Tax | B48: 451.44 | C48: 530.12 | D48: 418.55 | E48: 492.62 | F48: 348.79 | G48: 416.83 | H48: 265.38 | I48: 389.73 | J48: 321.42 | K48: 391.66
A49: Net profit | B49: 1234.14 | C49: 1550.37 | D49: 1205.42 | E49: 1447.72 | F49: 1256.72 | G49: 1169.98 | H49: 694.64 | I49: 1110.48 | J49: 692.13 | K49: 1099.77
A50: Operating Profit | B50: 1864.76 | C50: 2121.29 | D50: 1716.23 | E50: 2056.09 | F50: 1691.37 | G50: 1693.77 | H50: 1239.51 | I50: 1636.73 | J50: 1436.2 | K50: 1624.97
A55: BALANCE SHEET
A56: Report Date | B56: 42460 | C56: 42825 | D56: 43190 | E56: 43555 | F56: 43921 | G56: 44286 | H56: 44651 | I56: 45016 | J56: 45382 | K56: 45747
A57: Equity Share Capital | B57: 95.92 | C57: 95.92 | D57: 95.92 | E57: 95.92 | F57: 95.92 | G57: 95.92 | H57: 95.92 | I57: 95.92 | J57: 95.92 | K57: 95.92
A58: Reserves | B58: 6428.9 | C58: 7507.97 | D58: 8314.31 | E58: 9374.63 | F58: 10034.24 | G58: 12710.37 | H58: 13715.64 | I58: 15896.31 | J58: 18632.38 | K58: 19303.89
A59: Borrowings | B59: 323.29 | C59: 560.34 | D59: 533.43 | E59: 1319.6 | F59: 1118.5 | G59: 1093.12 | H59: 1586.88 | I59: 1932.62 | J59: 2474.38 | K59: 2290.29
A60: Other Liabilities | B60: 3710.92 | C60: 4240.96 | D60: 4819.82 | E60: 5458.69 | F60: 4889.31 | G60: 6455.93 | H60: 7559.99 | I60: 7854.48 | J60: 8698.09 | K60: 8665.15
A61: Total | B61: 10559.03 | C61: 12405.19 | D61: 13763.48 | E61: 16248.84 | F61: 16137.97 | G61: 20355.34 | H61: 22958.43 | I61: 25779.33 | J61: 29900.77 | K61: 30355.25
A62: Net Block | B62: 3416.35 | C62: 3303.74 | D62: 3732.24 | E62: 6496.56 | F62: 6272.31 | G62: 5858.52 | H62: 5519.06 | I62: 5770.46 | J62: 7146.62 | K62: 9220.1
A63: Capital Work in Progress | B63: 106.59 | C63: 257.54 | D63: 1405.11 | E63: 209.67 | F63: 140.24 | G63: 182.98 | H63: 426.43 | I63: 1019.59 | J63: 2698.37 | K63: 1254.49
A64: Investments | B64: 2712.13 | C64: 2651.99 | D64: 2140.7 | E64: 2568.58 | F64: 2018.85 | G64: 4736.8 | H64: 3247.53 | I64: 4261.71 | J64: 4587.92 | K64: 4724.75
A65: Other Assets | B65: 4323.96 | C65: 6191.92 | D65: 6485.43 | E65: 6974.03 | F65: 7706.57 | G65: 9577.04 | H65: 13765.41 | I65: 14727.57 | J65: 15467.86 | K65: 15155.91
A66: Total | B66: 10559.03 | C66: 12405.19 | D66: 13763.48 | E66: 16248.84 | F66: 16137.97 | G66: 20355.34 | H66: 22958.43 | I66: 25779.33 | J66: 29900.77 | K66: 30355.25
A67: Receivables | B67: 1186.84 | C67: 1446.6 | D67: 1730.63 | E67: 1907.33 | F67: 1795.22 | G67: 2602.17 | H67: 3871.44 | I67: 4636.94 | J67: 4889.05 | K67: 4313.65
... A70: No. of Equity Shares | B70: 959197790 | C70: 959197790 | D70: 959197790 | E70: 959197790 | F70: 959197790 | G70: 959197790 | H70: 959197790 | I70: 959197790 | J70: 959197790 | K70: 959197790
A71: New Bonus Shares
A72: Face value | B72: 1 | C72: 1 | D72: 1 | E72: 1 | F72: 1 | G72: 1 | H72: 1 | I72: 1 | J72: 1 | K72: 1
A80: CASH FLOW:
A81: Report Date | B81: 42460 | C81: 42825 | D81: 43190 | E81: 43555 | F81: 43921 | G81: 44286 | H81: 44651 | I81: 45016 | J81: 45382 | K81: 45747
A82: Cash from Operating Activity | B82: 2242.95 | C82: 1527.33 | D82: 2113.44 | E82: 2469.54 | F82: 3038.15 | G82: 3683.35 | H82: 986.49 | I82: 4193.43 | J82: 6103.6 | K82: 4423.96
A83: Cash from Investing Activity | B83: -866.21 | C83: -681.11 | D83: -1556.14 | E83: -917.79 | F83: -517.91 | G83: -540.54 | H83: -316.75 | I83: -1282.34 | J83: -2548.48 | K83: -940.91
A84: Cash from Financing Activity | B84: -848.98 | C84: -756.43 | D84: -1379.14 | E84: -1117.46 | F84: -2871.46 | G84: -650.4 | H84: -1807.61 | I84: -2140.05 | J84: -2982.5 | K84: -3752.58
A85: Net Cash Flow | B85: 527.76 | C85: 89.79 | D85: -821.84 | E85: 434.29 | F85: -351.22 | G85: 2492.41 | H85: -1137.87 | I85: 771.04 | J85: 572.62 | K85: -269.53
A90: PRICE: | B90: 868.4 | C90: 1073.5 | D90: 1120.4 | E90: 1492.7 | F90: 1666.5 | G90: 2537.4 | H90: 3079.95 | I90: 2761.65 | J90: 2846.75 | K90: 2340.65
A92: DERIVED:
A93: Adjusted Equity Shares in Cr | B93: 95.92 | C93: 95.92 | D93: 95.92 | E93: 95.92 | F93: 95.92 | G93: 95.92 | H93: 95.92 | I93: 95.92 | J93: 95.92 | K93: 95.92

Sheet Raw Bs
B2: Particulars | C2: 41699 | D2: 42064 | E2: 42430 | F2: 42795 | G2: 43160 | H2: 43525 | I2: 43891 | J2: 44256 | K2: 44621 | L2: 44986 | M2: 45352 | N2: 45717
B4: Equity Capital | C4: 96 | D4: 96 | E4: 96 | F4: 96 | G4: 96 | H4: 96 | I4: 96 | J4: 96 | K4: 96 | L4: 96 | M4: 96 | N4: 96
B5: Reserves | C5: 3943 | D5: 4646 | E5: 6429 | F5: 7508 | G5: 8314 | H5: 9375 | I5: 10034 | J5: 12710 | K5: 13716 | L5: 15896 | M5: 18632 | N5: 19304
B6: Borrowings -
B7: Long term Borrowings | C7: 41 | D7: 78 | E7: 73 | F7: 41 | G7: 28 | H7: 19 | I7: 19 | J7: 15 | K7: 45 | L7: 76 | M7: 54 | N7: 260
B8: Short term Borrowings | C8: 199 | D8: 332 | E8: 231 | F8: 504 | G8: 492 | H8: 597 | I8: 321 | J8: 334 | K8: 731 | L8: 896 | M8: 1053 | N8: 604
B9: Lease Liabilities | C9: 0 | D9: 0 | E9: 0 | F9: 0 | G9: 0 | H9: 693 | I9: 764 | J9: 745 | K9: 811 | L9: 960 | M9: 1367 | N9: 1427
B10: Other Borrowings | C10: 9 | D10: 8 | E10: 20 | F10: 15 | G10: 13 | H10: 11 | I10: 15 | J10: 0 | K10: 0 | L10: 0 | M10: 0 | N10: 0
B11: Other Liabilities -
B12: Non controlling int | C12: 246 | D12: 264 | E12: 384 | F12: 375 | G12: 328 | H12: 361 | I12: 404 | J12: 423 | K12: 388 | L12: 454 | M12: 695 | N12: 659
B13: Trade Payables | C13: 1746 | D13: 1549 | E13: 1565 | F13: 1923 | G13: 2160 | H13: 2394 | I13: 2137 | J13: 3379 | K13: 4164 | L13: 3635 | M13: 3831 | N13: 3848
B14: Advance from Customers | C14: 0 | D14: 5 | E14: 12 | F14: 17 | G14: 16 | H14: 13 | I14: 29 | J14: 41 | K14: 76 | L14: 108 | M14: 154 | N14: 173
B15: Other liability items | C15: 1795 | D15: 1937 | E15: 1750 | F15: 1925 | G15: 2316 | H15: 2690 | I15: 2320 | J15: 2613 | K15: 2932 | L15: 3657 | M15: 4017 | N15: 3985
B16: Total Liabilities | C16: 8075 | D16: 8914 | E16: 10559 | F16: 12405 | G16: 13763 | H16: 16249 | I16: 16138 | J16: 20355 | K16: 22958 | L16: 25779 | M16: 29901 | N16: 30355
B18: Fixed Assets -
B19: Land | C19: 247 | D19: 251 | E19: 429 | F19: 408 | G19: 586 | H19: 605 | I19: 640 | J19: 644 | K19: 644 | L19: 804 | M19: 1126 | N19: 1050
B20: Building | C20: 931 | D20: 962 | E20: 923 | F20: 931 | G20: 957 | H20: 2402 | I20: 2257 | J20: 2249 | K20: 2325 | L20: 2883 | M20: 3390 | N20: 4136
B21: Plant Machinery | C21: 2054 | D21: 2132 | E21: 1793 | F21: 1980 | G21: 2157 | H21: 4006 | I21: 4208 | J21: 4340 | K21: 4531 | L21: 4825 | M21: 5422 | N21: 7576
B22: Equipments | C22: 155 | D22: 171 | E22: 97 | F22: 119 | G22: 200 | H22: 221 | I22: 241 | J22: 243 | K22: 253 | L22: 270 | M22: 298 | N22: 325
B23: Furniture n fittings | C23: 71 | D23: 83 | E23: 49 | F23: 59 | G23: 72 | H23: 88 | I23: 94 | J23: 99 | K23: 113 | L23: 146 | M23: 175 | N23: 203
B24: Vehicles | C24: 14 | D24: 18 | E24: 11 | F24: 14 | G24: 27 | H24: 47 | I24: 43 | J24: 38 | K24: 32 | L24: 36 | M24: 40 | N24: 39
B25: Intangible Assets | C25: 203 | D25: 351 | E25: 339 | F25: 276 | G25: 468 | H25: 512 | I25: 505 | J25: 476 | K25: 345 | L25: 422 | M25: 850 | N25: 827
B26: Other fixed assets | C26: 128 | D26: 145 | E26: 103 | F26: 128 | G26: 238 | H26: 261 | I26: 293 | J26: 302 | K26: 294 | L26: 289 | M26: 321 | N26: 328
B27: Gross Block | C27: 3804 | D27: 4112 | E27: 3744 | F27: 3914 | G27: 4705 | H27: 8141 | I27: 8282 | J27: 8392 | K27: 8538 | L27: 9676 | M27: 11622 | N27: 14484
B28: Accumulated Depreciation | C28: 1223 | D28: 1438 | E28: 275 | F28: 610 | G28: 973 | H28: 1592 | I28: 2010 | J28: 2533 | K28: 3019 | L28: 3814 | M28: 4381 | N28: 4945
B29: Net Block | C29: =SUM(C27:C28) -> 5027 | D29: =SUM(D27:D28) -> 5550 | E29: =SUM(E27:E28) -> 4019 | F29: =SUM(F27:F28) -> 4524 | G29: =SUM(G27:G28) -> 5678 | H29: =SUM(H27:H28) -> 9733 | I29: =SUM(I27:I28) -> 10292 | J29: =SUM(J27:J28) -> 10925 | ... N29: =SUM(N27:N28) -> 19429
B31: CWIP | C31: 72 | D31: 196 | E31: 107 | F31: 258 | G31: 1405 | H31: 210 | I31: 140 | J31: 183 | K31: 426 | L31: 1020 | M31: 2698 | N31: 1254
B32: Investments | C32: 1424 | D32: 1588 | E32: 2712 | F32: 2652 | G32: 2141 | H32: 2569 | I32: 2019 | J32: 4737 | K32: 3248 | L32: 4262 | M32: 4588 | N32: 4725
B33: Other Assets -
B34: Inventories | C34: 2070 | D34: 2259 | E34: 1998 | F34: 2627 | G34: 2658 | H34: 3150 | I34: 3390 | J34: 3799 | K34: 6153 | L34: 6211 | M34: 5923 | N34: 6719
B35: Trade receivables | C35: 1110 | D35: 1182 | E35: 1187 | F35: 1447 | G35: 1731 | H35: 1907 | I35: 1795 | J35: 2602 | K35: 3871 | L35: 4637 | M35: 4889 | N35: 4314
B36: Cash Equivalents | C36: 229 | D36: 204 | E36: 424 | F36: 801 | G36: 405 | H36: 445 | I36: 783 | J36: 611 | K36: 864 | L36: 844 | M36: 1084 | N36: 782
B37: Loans n Advances | C37: 7 | D37: 8 | E37: 9 | F37: 14 | G37: 13 | H37: 16 | I37: 12 | J37: 11 | K37: 8 | L37: 12 | M37: 17 | N37: 22
B38: Other asset items | C38: 603 | D38: 817 | E38: 705 | F38: 1303 | G38: 1678 | H38: 1456 | I38: 1727 | J38: 2555 | K38: 2869 | L38: 3024 | M38: 3555 | N38: 3319
B39: Total Assets | C39: 8075 | D39: 8914 | E39: 10559 | F39: 12405 | G39: 13763 | H39: 16249 | I39: 16138 | J39: 20355 | K39: 22958 | L39: 25779 | M39: 29901 | N39: 30355

Sheet Raw CF
B1: ='Data Sheet'!B1 -> ASIAN PAINTS LTD
B2: Particulars | C2: 41699 | D2: =C2+366 -> 42065 | E2: =D2+366 -> 42431 | F2: =E2+366 -> 42797 | G2: =F2+366 -> 43163 | H2: =G2+366 -> 43529 | I2: =H2+366 -> 43895 | J2: =I2+366 -> 44261 | K2: =J2+366 -> 44627 | ... N2: =M2+366 -> 45725
B3: Cash from Operating Activity - | C3: 1402 | D3: 1188 | E3: 2243 | F3: 1527 | G3: 2113 | H3: 2470 | I3: 3038 | J3: 3683 | K3: 986 | L3: 4193 | M3: 6104 | N3: 4424
B4: Profit from operations | C4: 2051 | D4: 2271 | E4: 2848 | F4: 3056 | G4: 3274 | H4: 3861 | I4: 4380 | J4: 4970 | K4: 4957 | L4: 6460 | M4: 7929 | N4: 6390
B5: Receivables | C5: -254 | D5: -155 | E5: -146 | F5: -475 | G5: -483 | H5: -205 | I5: 160 | J5: -849 | K5: -1326 | L5: -834 | M5: -362 | N5: 282
B6: Inventory | C6: -231 | D6: -144 | E6: 202 | F6: -629 | G6: -39 | H6: -492 | I6: -251 | J6: -409 | K6: -2354 | L6: -56 | M6: 315 | N6: -805
B7: Payables | C7: 317 | D7: -151 | E7: 142 | F7: 501 | G7: 442 | H7: 287 | I7: -241 | J7: 1143 | K7: 644 | L7: -539 | M7: 269 | N7: -160
B8: Other WC items | C8: 0 | D8: 0 | E8: 0 | F8: 0 | G8: 0 | H8: 0 | I8: 0 | J8: -92 | K8: 242 | L8: 657 | M8: -212 | N8: 114
B9: Working capital changes | C9: -168 | D9: -450 | E9: 198 | F9: -603 | G9: -80 | H9: -410 | I9: -331 | J9: -206 | K9: -2795 | L9: -772 | M9: 10 | N9: -570
B10: Direct taxes | C10: -480 | D10: -633 | E10: -802 | F10: -925 | G10: -1081 | H10: -982 | I10: -1011 | J10: -1080 | K10: -1176 | L10: -1494 | M10: -1835 | N10: -1396
B12: Cash from Investing Activity - | C12: -586 | D12: -465 | E12: -866 | F12: -681 | G12: -1556 | H12: -918 | I12: -518 | J12: -541 | K12: -317 | L12: -1282 | M12: -2548 | N12: -941
B13: Fixed assets purchased | C13: -251 | D13: -454 | E13: -817 | F13: -684 | G13: -1426 | H13: -1151 | I13: -404 | J13: -282 | K13: -551 | L13: -1446 | M13: -2496 | N13: -1830
B14: Fixed assets sold | C14: 16 | D14: 16 | E14: 15 | F14: 17 | G14: 17 | H14: 17 | I14: 37 | J14: 28 | K14: 40 | L14: 26 | M14: 5 | N14: 10
B15: Investments purchased | C15: -872 | D15: -243 | E15: -282 | F15: -153 | G15: -320 | H15: -573 | I15: -25 | J15: -140 | K15: 0 | L15: -146 | M15: -212 | N15: -1
... B32: Net Cash Flow | C32: 190 | D32: 147 | E32: 528 | F32: 90 | G32: -822 | H32: 434 | I32: -351 | J32: 2492 | K32: -1138 | L32: 771 | M32: 573 | N32: -270
