Workbook
Name UPDATE: 'Data Sheet'!$E$1

Sheet Financials>

Sheet One Page Profile
B2: ='Data Sheet'!B1& " - "& "One Page Profile" -> ITC LTD - One Page Profile
C4: =Input!C2 -> ITC Limited is an Indian conglomerate, headquartered in Kolkata. It has a presence across six business segments, namely FMCG, agribusiness, information technology, paper products, and packaging. It generates a plurality of its revenue from tobacco products. In terms of market capitalization, ITC is the second largest FMCG company in India and the third-largest tobacco company in the world. It employs 36,500 people at more than 60 locations across India.
B5: (INR Crs.)
B6: Key Financial Metrics | C6: ='Data Sheet'!G$16 -> 44286 | D6: ='Data Sheet'!H$16 -> 44651 | E6: ='Data Sheet'!I$16 -> 45016 | F6: ='Data Sheet'!J$16 -> 45382 | G6: ='Data Sheet'!K$16 -> 45747 | I6: Share Price - 5Y
B8: Total Sales | C8: ='Data Sheet'!G17 -> 49257.45 | D8: ='Data Sheet'!H17 -> 60644.54 | E8: ='Data Sheet'!I17 -> 70919.03 | F8: ='Data Sheet'!J17 -> 67931.94 | G8: ='Data Sheet'!K17 -> 75323.34
B9: Sales Growth (Y-on-Y) | C9: ='Ratio Analysis'!H10 -> -0.0026372963 | D9: ='Ratio Analysis'!I10 -> 0.23117498 | E9: ='Ratio Analysis'!J10 -> 0.16942152 | F9: ='Ratio Analysis'!K10 -> -0.042119724 | G9: ='Ratio Analysis'!L10 -> 0.10880596
B10: Gross Profit Margins (%) | C10: ='Ratio Analysis'!H17 -> 0.45426509 | D10: ='Ratio Analysis'!I17 -> 0.43848102 | E10: ='Ratio Analysis'!J17 -> 0.45991746 | F10: ='Ratio Analysis'!K17 -> 0.47497466 | G10: ='Ratio Analysis'!L17 -> 0.44945073
B11: EBIDTA Margins (%) | C11: ='Ratio Analysis'!H18 -> 0.34644059 | D11: ='Ratio Analysis'!I18 -> 0.34006606 | E11: ='Ratio Analysis'!J18 -> 0.36244517 | F11: ='Ratio Analysis'!K18 -> 0.37077596 | G11: ='Ratio Analysis'!L18 -> 0.34304706
B12: EBIT Margins | C12: ='Ratio Analysis'!H19 -> 0.31303265 | D12: ='Ratio Analysis'!I19 -> 0.31149944 | E12: ='Ratio Analysis'!J19 -> 0.33693707 | F12: ='Ratio Analysis'!K19 -> 0.34842932 | G12: ='Ratio Analysis'!L19 -> 0.32119035
B13: Net Profit Margins (%) | C13: ='Ratio Analysis'!H21 -> 0.21937656 | D13: ='Ratio Analysis'!I21 -> 0.22414895 | E13: ='Ratio Analysis'!J21 -> 0.24505524 | F13: ='Ratio Analysis'!K21 -> 0.25644653 | G13: ='Ratio Analysis'!L21 -> 0.22911358
B14: Earning Per Share (In Rs) | C14: =HistoricalFS!H45 -> 8.779028 | D14: =HistoricalFS!I45 -> 11.030657 | E14: =HistoricalFS!J45 -> 13.983811 | F14: =HistoricalFS!K45 -> 13.953807 | G14: =HistoricalFS!L45 -> 13.790524
B15: EPS Growth (Y-on-Y) | C15: =HistoricalFS!H46 -> 0.81904972 | D15: =HistoricalFS!I46 -> 1.2564782 | E15: =HistoricalFS!J46 -> 1.2677223 | F15: =HistoricalFS!K46 -> 0.99785443 | G15: =HistoricalFS!L46 -> 0.98829831
B16: Dividend Per Share (In Rs) | C16: =HistoricalFS!H48 -> 10.75 | D16: =HistoricalFS!I48 -> 11.500004 | E16: =HistoricalFS!J48 -> 15.5 | F16: =HistoricalFS!K48 -> 13.749998 | G16: =HistoricalFS!L48 -> 14.349997
B17: DPS Growth (Y-on-Y) | C17: =HistoricalFS!H49 -> 1.2245091 | D17: =HistoricalFS!I49 -> 1.0425493 | E17: =HistoricalFS!J49 -> 1.1084246 | F17: =HistoricalFS!K49 -> 0.98539399 | G17: =HistoricalFS!L49 -> 1.0405694
B19: Key Financial Ratios | C19: ='Data Sheet'!G$16 -> 44286 | D19: ='Data Sheet'!H$16 -> 44651 | E19: ='Data Sheet'!I$16 -> 45016 | F19: ='Data Sheet'!J$16 -> 45382 | G19: ='Data Sheet'!K$16 -> 45747 | I19: Volume - 5Y
B21: =Input!B14 -> Price to Earning | C21: =Input!H14 -> 23.330601 | D21: =Input!I14 -> 21.300634 | E21: =Input!J14 -> 25.707585 | F21: =Input!K14 -> 28.775659 | G21: =Input!L14 -> 29.712431
B22: =Input!B9 -> EV/EBITDA | C22: =Input!C9 -> 16.627944 | D22: =Input!D9 -> 20.443521 | E22: =Input!E9 -> 17.519308 | F22: =Input!F9 -> 18.202942 | G22: =Input!G9 -> 9.8659847
B23: =Input!B10 -> EV/Sales | C23: =Input!C10 -> 6.1652425 | D23: =Input!D10 -> 7.3946458 | E23: =Input!E10 -> 6.6613663 | F23: =Input!F10 -> 6.9805125 | G23: =Input!G10 -> 3.8641822
B24: =Input!B12 -> Price to Book Value | C24: =Input!C12 -> 5.8015723 | D24: =Input!D12 -> 6.8768107 | E24: =Input!E12 -> 5.5664135 | F24: =Input!F12 -> 5.7755936 | G24: =Input!G12 -> 3.0309955
B25: Return on Equity (%) | C25: ='Ratio Analysis'!H29 -> 0.17906224 | D25: ='Ratio Analysis'!I29 -> 0.21764928 | E25: ='Ratio Analysis'!J29 -> 0.25130525 | F25: ='Ratio Analysis'!K29 -> 0.23381575 | G25: ='Ratio Analysis'!L29 -> 0.24643135
B26: Return on Capital Employed (%) | C26: ='Ratio Analysis'!H27 -> 0.25436581 | D26: ='Ratio Analysis'!I27 -> 0.30126365 | E26: ='Ratio Analysis'!J27 -> 0.3440081 | F26: ='Ratio Analysis'!K27 -> 0.31639278 | G26: ='Ratio Analysis'!L27 -> 0.34406984
B28: Top Shareholders | C28: Shares Held (Crs.) | E28: % Holdings | F28: Market Value (Crs.) | I28: Shareholding Pattern
B30: =Input!B17 -> Tobacco Manufacturers Ltd. | C30: =Input!C17 -> 222.84959 | E30: =Input!D17 -> 0.1781 | F30: =Input!E17 -> 91312.618
B31: =Input!B18 -> Life Insurance Corporation of India | C31: =Input!C18 -> 197.70109 | E31: =Input!D18 -> 0.158 | F31: =Input!E18 -> 81008.021
B32: =Input!B19 -> SUUTI | C32: =Input!C19 -> 97.453143 | E32: =Input!D19 -> 0.0779 | F32: =Input!E19 -> 39931.425
B33: =Input!B20 -> Myddleton Investment Company Ltd | C33: =Input!C20 -> 48.631194 | E33: =Input!D20 -> 0.0389 | F33: =Input!E20 -> 19926.632
B34: =Input!B21 -> SBI Mutual Funds | C34: =Input!C21 -> 43.517441 | E34: =Input!D21 -> 0.0348 | F34: =Input!E21 -> 17831.272
B35: =Input!B22 -> ICICI Prudential Mutual Funds | C35: =Input!C22 -> 27.619721 | E35: =Input!D22 -> 0.0221 | F35: =Input!E22 -> 11317.181
B36: =Input!B23 -> GQG Partners Equity Fund | C36: =Input!C23 -> 26.390174 | E36: =Input!D23 -> 0.0211 | F36: =Input!E23 -> 10813.374
B38: Managerial Remuneration | C38: Designation | D38: Remuneration (Lakh) | F38: X of Median Salary | I38: Capital Structure
B40: Mr. Sanjeev Puri | C40: CMD | D40: 2566.47 | F40: 377 | I40: Share Price (03-09-2025) | K40: ='Data Sheet'!B8 -> 409.75
B41: Mr. Supratim Dutta | C41: ED & CFO | D41: 853.14 | F41: 132 | I41: Number of Shares O/S | K41: ='Data Sheet'!B6 -> 1252.6663
B42: Mr. Hemant Malik | C42: ED | D42: 494.13 | F42: 99 | I42: Market Capitalization | K42: =K40*K41 -> 513280.01
B43: Mr. B Sumant | C43: ED | D43: 1181.4 | F43: 174 | I43: Less: Cash & Equivalents | K43: =-'Data Sheet'!K69 -> -4012.36
B44: Mr. H Bharagva | C44: Indep. Director | D44: 104.1 | F44: 14 | I44: Add: Total Debt | K44: ='Data Sheet'!K59 -> 284.54
B45: Mr. A M Bharucha | C45: Indep. Director | D45: 66.8 | F45: 9 | I45: Add: Minority Interest | K45: ='Raw Bs'!L12 -> 368
B46: Mr. C K Mishra | C46: Indep. Director | D46: 3 | F46: 9 | I46: Enterprise Value | K46: =K42+K43+K44+K45 -> 509920.19
B48: Peer Comparison (FMCG Industry)
B49: Companies | C49: ='Comps Data'!E2 -> CMP (INR) | D49: ='Comps Data'!G2 -> Market Capitalization | F49: ='Comps Data'!H2 -> Debt | G49: ='Comps Data'!I2 -> Cash at End | I49: ='Comps Data'!K2 -> Sales | J49: ='Comps Data'!N2 -> ROE % | K49: ='Comps Data'!O2 -> ROCE %
B51: ='Comps Data'!C4 -> Hind. Unilever | C51: ='Comps Data'!E4 -> 2659.8 | D51: ='Comps Data'!G4 -> 624946.61 | F51: ='Comps Data'!H4 -> 1648 | G51: ='Comps Data'!I4 -> 7554 | I51: ='Comps Data'!K4 -> 63928 | J51: ='Comps Data'!N4 -> 0.2732 | K51: ='Comps Data'!O4 -> 0.3679
B52: ='Comps Data'!C5 -> Nestle India | C52: ='Comps Data'!E5 -> 1156.2 | D52: ='Comps Data'!G5 -> 222950.05 | F52: ='Comps Data'!H5 -> 1166.85 | G52: ='Comps Data'!I5 -> 95.65 | I52: ='Comps Data'!K5 -> 20483.77 | J52: ='Comps Data'!N5 -> 0.8302 | K52: ='Comps Data'!O5 -> 0.9566
B53: ='Comps Data'!C6 -> Varun Beverages | C53: ='Comps Data'!E6 -> 487.15 | D53: ='Comps Data'!G6 -> 164754.13 | F53: ='Comps Data'!H6 -> 2138.25 | G53: ='Comps Data'!I6 -> 2450.05 | I53: ='Comps Data'!K6 -> 21077.78 | J53: ='Comps Data'!N6 -> 0.2249 | K53: ='Comps Data'!O6 -> 0.2485
B54: ='Comps Data'!C7 -> Britannia Inds. | C54: ='Comps Data'!E7 -> 5824 | D54: ='Comps Data'!G7 -> 140300.16 | F54: ='Comps Data'!H7 -> 1246.51 | G54: ='Comps Data'!I7 -> 312.48 | I54: ='Comps Data'!K7 -> 18314.59 | J54: ='Comps Data'!N7 -> 0.5294 | K54: ='Comps Data'!O7 -> 0.5299
B55: ='Comps Data'!C8 -> Godrej Consumer | C55: ='Comps Data'!E8 -> 1242.6 | D55: ='Comps Data'!G8 -> 127130.41 | F55: ='Comps Data'!H8 -> 4009.19 | G55: ='Comps Data'!I8 -> 483.06 | I55: ='Comps Data'!K8 -> 14694.57 | J55: ='Comps Data'!N8 -> 0.1521 | K55: ='Comps Data'!O8 -> 0.1921
B57: Recent Updates
B69: Source: The Valuation School, Screener.in, Investing.com

Sheet HistoricalFS
B2: ='Data Sheet'!B1 -> ITC LTD
B3: (ITC | BSE Code: 540376)
B4: =CONCATENATE("INR"," ", 'Data Sheet'!B8) -> INR 409.75
B5: 52 Week (High - INR 410.45 & Low - INR 401.90)
B7: ="Historical Financials Statements - "&'Data Sheet'!B1 -> Historical Financials Statements - ITC LTD
B8: Years | C8: ='Data Sheet'!B16 -> 42460 | D8: ='Data Sheet'!C16 -> 42825 | E8: ='Data Sheet'!D16 -> 43190 | F8: ='Data Sheet'!E16 -> 43555 | G8: ='Data Sheet'!F16 -> 43921 | H8: ='Data Sheet'!G16 -> 44286 | I8: ='Data Sheet'!H16 -> 44651 | J8: ='Data Sheet'!I16 -> 45016 | ... L8: ='Data Sheet'!K16 -> 45747
A9: # | B9: Income Statement
B10: Sales | C10: =IFERROR('Data Sheet'!B17,0) -> 39192.1 | D10: =IFERROR('Data Sheet'!C17,0) -> 42767.6 | E10: =IFERROR('Data Sheet'!D17,0) -> 43448.94 | F10: =IFERROR('Data Sheet'!E17,0) -> 48339.58 | G10: =IFERROR('Data Sheet'!F17,0) -> 49387.7 | H10: =IFERROR('Data Sheet'!G17,0) -> 49257.45 | I10: =IFERROR('Data Sheet'!H17,0) -> 60644.54 | J10: =IFERROR('Data Sheet'!I17,0) -> 70919.03 | ... L10: =IFERROR('Data Sheet'!K17,0) -> 75323.34
B11: Sales Growth % | C11: - | D11: =D10/C10-1 -> 0.09123012 | E11: =E10/D10-1 -> 0.015931219 | F11: =F10/E10-1 -> 0.11256063 | G11: =G10/F10-1 -> 0.021682439 | H11: =H10/G10-1 -> -0.0026372963 | I11: =I10/H10-1 -> 0.23117498 | J11: =J10/I10-1 -> 0.16942152 | K11: =K10/J10-1 -> -0.042119724 | L11: =L10/K10-1 -> 0.10880596
B13: COGS | C13: =IFERROR(SUM('Data Sheet'!B18,'Data Sheet'!B20:B22)-1*'Data Sheet'!B19,0) -> 19162.94 | D13: =IFERROR(SUM('Data Sheet'!C18,'Data Sheet'!C20:C22)-1*'Data Sheet'!C19,0) -> 21949.12 | E13: =IFERROR(SUM('Data Sheet'!D18,'Data Sheet'!D20:D22)-1*'Data Sheet'!D19,0) -> 21967.5 | F13: =IFERROR(SUM('Data Sheet'!E18,'Data Sheet'!E20:E22)-1*'Data Sheet'!E19,0) -> 24215.95 | G13: =IFERROR(SUM('Data Sheet'!F18,'Data Sheet'!F20:F22)-1*'Data Sheet'!F19,0) -> 24330.4 | H13: =IFERROR(SUM('Data Sheet'!G18,'Data Sheet'!G20:G22)-1*'Data Sheet'!G19,0) -> 26881.51 | I13: =IFERROR(SUM('Data Sheet'!H18,'Data Sheet'!H20:H22)-1*'Data Sheet'!H19,0) -> 34053.06 | J13: =IFERROR(SUM('Data Sheet'!I18,'Data Sheet'!I20:I22)-1*'Data Sheet'!I19,0) -> 38302.13 | ... L13: =IFERROR(SUM('Data Sheet'!K18,'Data Sheet'!K20:K22)-1*'Data Sheet'!K19,0) -> 41469.21
B14: COGS % of Sales | C14: =C13/C10 -> 0.48894905 | D14: =D13/D10 -> 0.51321842 | E14: =E13/E10 -> 0.50559346 | F14: =F13/F10 -> 0.50095491 | G14: =G13/G10 -> 0.49264088 | H14: =H13/H10 -> 0.54573491 | I14: =I13/I10 -> 0.56151898 | J14: =J13/J10 -> 0.54008254 | ... L14: =L13/L10 -> 0.55054927
B16: Gross Profit | C16: =C10-C13 -> 20029.16 | D16: =D10-D13 -> 20818.48 | E16: =E10-E13 -> 21481.44 | F16: =F10-F13 -> 24123.63 | G16: =G10-G13 -> 25057.3 | H16: =H10-H13 -> 22375.94 | I16: =I10-I13 -> 26591.48 | J16: =J10-J13 -> 32616.9 | ... L16: =L10-L13 -> 33854.13
B17: Gross Margins | C17: =C16/C10 -> 0.51105095 | D17: =D16/D10 -> 0.48678158 | E17: =E16/E10 -> 0.49440654 | F17: =F16/F10 -> 0.49904509 | G17: =G16/G10 -> 0.50735912 | H17: =H16/H10 -> 0.45426509 | I17: =I16/I10 -> 0.43848102 | J17: =J16/J10 -> 0.45991746 | ... L17: =L16/L10 -> 0.44945073
B19: Selling & General Expenses | C19: =IFERROR(SUM('Data Sheet'!B23:B24),0) -> 5497.67 | D19: =IFERROR(SUM('Data Sheet'!C23:C24),0) -> 5348.97 | E19: =IFERROR(SUM('Data Sheet'!D23:D24),0) -> 4960.85 | F19: =IFERROR(SUM('Data Sheet'!E23:E24),0) -> 5586.24 | G19: =IFERROR(SUM('Data Sheet'!F23:F24),0) -> 5713.76 | H19: =IFERROR(SUM('Data Sheet'!G23:G24),0) -> 5311.16 | I19: =IFERROR(SUM('Data Sheet'!H23:H24),0) -> 5968.33 | J19: =IFERROR(SUM('Data Sheet'!I23:I24),0) -> 6912.64 | ... L19: =IFERROR(SUM('Data Sheet'!K23:K24),0) -> 8014.68
B20: S&G Exp % of Sales | C20: =C19/C10 -> 0.14027495 | D20: =D19/D10 -> 0.12507061 | E20: =E19/E10 -> 0.11417655 | F20: =F19/F10 -> 0.11556244 | G20: =G19/G10 -> 0.11569196 | H20: =H19/H10 -> 0.1078245 | I20: =I19/I10 -> 0.09841496 | J20: =J19/J10 -> 0.097472286 | ... L20: =L19/L10 -> 0.10640367
B22: EBITDA | C22: =C16-C19 -> 14531.49 | D22: =D16-D19 -> 15469.51 | E22: =E16-E19 -> 16520.59 | F22: =F16-F19 -> 18537.39 | G22: =G16-G19 -> 19343.54 | H22: =H16-H19 -> 17064.78 | I22: =I16-I19 -> 20623.15 | J22: =J16-J19 -> 25704.26 | ... L22: =L16-L19 -> 25839.45
B23: EBITDA % of Sales | C23: =C22/C10 -> 0.370776 | D23: =D22/D10 -> 0.36171097 | E23: =E22/E10 -> 0.38022999 | F23: =F22/F10 -> 0.38348265 | G23: =G22/G10 -> 0.39166716 | H23: =H22/H10 -> 0.34644059 | I23: =I22/I10 -> 0.34006606 | J23: =J22/J10 -> 0.36244517 | ... L23: =L22/L10 -> 0.34304706
B25: Interest | C25: =IFERROR('Data Sheet'!B27,0) -> 78.13 | D25: =IFERROR('Data Sheet'!C27,0) -> 49.03 | E25: =IFERROR('Data Sheet'!D27,0) -> 115.01 | F25: =IFERROR('Data Sheet'!E27,0) -> 71.4 | G25: =IFERROR('Data Sheet'!F27,0) -> 81.38 | H25: =IFERROR('Data Sheet'!G27,0) -> 57.97 | I25: =IFERROR('Data Sheet'!H27,0) -> 59.99 | J25: =IFERROR('Data Sheet'!I27,0) -> 77.77 | ... L25: =IFERROR('Data Sheet'!K27,0) -> 45.06
B26: Interest % of Sales | C26: =C25/C10 -> 0.001993514 | D26: =D25/D10 -> 0.0011464286 | E26: =E25/E10 -> 0.0026470151 | F26: =F25/F10 -> 0.0014770505 | G26: =G25/G10 -> 0.0016477787 | H26: =H25/H10 -> 0.0011768778 | I26: =I25/I10 -> 0.00098920694 | J26: =J25/J10 -> 0.0010966027 | ... L26: =L25/L10 -> 0.00059822095
B28: Depriciation | C28: =IFERROR('Data Sheet'!B26,0) -> 1077.4 | D28: =IFERROR('Data Sheet'!C26,0) -> 1152.79 | E28: =IFERROR('Data Sheet'!D26,0) -> 1236.28 | F28: =IFERROR('Data Sheet'!E26,0) -> 1396.61 | G28: =IFERROR('Data Sheet'!F26,0) -> 1644.91 | H28: =IFERROR('Data Sheet'!G26,0) -> 1645.59 | I28: =IFERROR('Data Sheet'!H26,0) -> 1732.41 | J28: =IFERROR('Data Sheet'!I26,0) -> 1809.01 | ... L28: =IFERROR('Data Sheet'!K26,0) -> 1646.32
B29: Depriciation % of Sales | C29: =C28/C10 -> 0.027490234 | D29: =D28/D10 -> 0.026954751 | E29: =E28/E10 -> 0.028453629 | F29: =F28/F10 -> 0.028891645 | G29: =G28/G10 -> 0.033306066 | H29: =H28/H10 -> 0.033407941 | I29: =I28/I10 -> 0.028566628 | J29: =J28/J10 -> 0.025508104 | ... L29: =L28/L10 -> 0.021856705
B31: EBIT | C31: =C22-C28 -> 13454.09 | D31: =D22-D28 -> 14316.72 | E31: =E22-E28 -> 15284.31 | F31: =F22-F28 -> 17140.78 | G31: =G22-G28 -> 17698.63 | H31: =H22-H28 -> 15419.19 | I31: =I22-I28 -> 18890.74 | J31: =J22-J28 -> 23895.25 | ... L31: =L22-L28 -> 24193.13
B32: EBIT % of Sales | C32: =IFERROR(C31/C10,0) -> 0.34328576 | D32: =IFERROR(D31/D10,0) -> 0.33475622 | E32: =IFERROR(E31/E10,0) -> 0.35177636 | F32: =IFERROR(F31/F10,0) -> 0.354591 | G32: =IFERROR(G31/G10,0) -> 0.35836109 | H32: =IFERROR(H31/H10,0) -> 0.31303265 | I32: =IFERROR(I31/I10,0) -> 0.31149944 | J32: =IFERROR(J31/J10,0) -> 0.33693707 | ... L32: =IFERROR(L31/L10,0) -> 0.32119035
B34: EBT | C34: =IFERROR(C22-SUM(C25,C28),0) -> 13375.96 | D34: =IFERROR(D22-SUM(D25,D28),0) -> 14267.69 | E34: =IFERROR(E22-SUM(E25,E28),0) -> 15169.3 | F34: =IFERROR(F22-SUM(F25,F28),0) -> 17069.38 | G34: =IFERROR(G22-SUM(G25,G28),0) -> 17617.25 | H34: =IFERROR(H22-SUM(H25,H28),0) -> 15361.22 | I34: =IFERROR(I22-SUM(I25,I28),0) -> 18830.75 | J34: =IFERROR(J22-SUM(J25,J28),0) -> 23817.48 | ... L34: =IFERROR(L22-SUM(L25,L28),0) -> 24148.07
B35: EBT % of Sales | C35: =C34/C10 -> 0.34129225 | D35: =D34/D10 -> 0.33360979 | E35: =E34/E10 -> 0.34912935 | F35: =F34/F10 -> 0.35311395 | G35: =G34/G10 -> 0.35671331 | H35: =H34/H10 -> 0.31185577 | I35: =I34/I10 -> 0.31051023 | J35: =J34/J10 -> 0.33584046 | ... L35: =L34/L10 -> 0.32059213
B37: Tax | C37: =IFERROR('Data Sheet'!B29,0) -> 5358.21 | D37: =IFERROR('Data Sheet'!C29,0) -> 5549.09 | E37: =IFERROR('Data Sheet'!D29,0) -> 5916.43 | F37: =IFERROR('Data Sheet'!E29,0) -> 6313.92 | G37: =IFERROR('Data Sheet'!F29,0) -> 4441.79 | H37: =IFERROR('Data Sheet'!G29,0) -> 4555.29 | I37: =IFERROR('Data Sheet'!H29,0) -> 5237.34 | J37: =IFERROR('Data Sheet'!I29,0) -> 6438.4 | ... L37: =IFERROR('Data Sheet'!K29,0) -> 6890.47
B38: Effective Tax Rate | C38: =C37/C34 -> 0.40058508 | D38: =D37/D34 -> 0.38892701 | E38: =E37/E34 -> 0.39002657 | F38: =F37/F34 -> 0.36989744 | G38: =G37/G34 -> 0.25212732 | H38: =H37/H34 -> 0.29654481 | I38: =I37/I34 -> 0.278127 | J38: =J37/J34 -> 0.27032247 | ... L38: =L37/L34 -> 0.28534247
B40: Net Profit | C40: =C34-C37 -> 8017.75 | D40: =D34-D37 -> 8718.6 | E40: =E34-E37 -> 9252.87 | F40: =F34-F37 -> 10755.46 | G40: =G34-G37 -> 13175.46 | H40: =H34-H37 -> 10805.93 | I40: =I34-I37 -> 13593.41 | J40: =J34-J37 -> 17379.08 | ... L40: =L34-L37 -> 17257.6
B41: Net Margins | C41: =C40/C10 -> 0.20457567 | D41: =D40/D10 -> 0.20385993 | E41: =E40/E10 -> 0.21295963 | F41: =F40/F10 -> 0.222498 | G41: =G40/G10 -> 0.26677614 | H41: =H40/H10 -> 0.21937656 | I41: =I40/I10 -> 0.22414895 | J41: =J40/J10 -> 0.24505524 | ... L41: =L40/L10 -> 0.22911358
B43: No. of Equity Shares | C43: =IFERROR('Data Sheet'!B93,0) -> 1207.08 | D43: =IFERROR('Data Sheet'!C93,0) -> 1214.74 | E43: =IFERROR('Data Sheet'!D93,0) -> 1220.43 | F43: =IFERROR('Data Sheet'!E93,0) -> 1225.86 | G43: =IFERROR('Data Sheet'!F93,0) -> 1229.22 | H43: =IFERROR('Data Sheet'!G93,0) -> 1230.88 | I43: =IFERROR('Data Sheet'!H93,0) -> 1232.33 | J43: =IFERROR('Data Sheet'!I93,0) -> 1242.8 | ... L43: =IFERROR('Data Sheet'!K93,0) -> 1251.41
B45: EPS | C45: =IFERROR(C40/C43,0) -> 6.6422689 | D45: =IFERROR(D40/D43,0) -> 7.1773384 | E45: =IFERROR(E40/E43,0) -> 7.5816475 | F45: =IFERROR(F40/F43,0) -> 8.7738078 | G45: =IFERROR(G40/G43,0) -> 10.718553 | H45: =IFERROR(H40/H43,0) -> 8.779028 | I45: =IFERROR(I40/I43,0) -> 11.030657 | J45: =IFERROR(J40/J43,0) -> 13.983811 | ... L45: =IFERROR(L40/L43,0) -> 13.790524
B46: EPS Growth % | C46: - | D46: =IFERROR(D45/C45,0) -> 1.0805552 | E46: =IFERROR(E45/D45,0) -> 1.0563313 | F46: =IFERROR(F45/E45,0) -> 1.1572429 | G46: =IFERROR(G45/F45,0) -> 1.2216535 | H46: =IFERROR(H45/G45,0) -> 0.81904972 | I46: =IFERROR(I45/H45,0) -> 1.2564782 | J46: =IFERROR(J45/I45,0) -> 1.2677223 | K46: =IFERROR(K45/J45,0) -> 0.99785443 | L46: =IFERROR(L45/K45,0) -> 0.98829831
B48: Divided per Share | C48: =IFERROR('Data Sheet'!B31/HistoricalFS!C43,0) -> 5.6666667 | D48: =IFERROR('Data Sheet'!C31/HistoricalFS!D43,0) -> 4.7500041 | E48: =IFERROR('Data Sheet'!D31/HistoricalFS!E43,0) -> 5.1499963 | F48: =IFERROR('Data Sheet'!E31/HistoricalFS!F43,0) -> 5.7500041 | G48: =IFERROR('Data Sheet'!F31/HistoricalFS!G43,0) -> 10.149998 | H48: =IFERROR('Data Sheet'!G31/HistoricalFS!H43,0) -> 10.75 | I48: =IFERROR('Data Sheet'!H31/HistoricalFS!I43,0) -> 11.500004 | J48: =IFERROR('Data Sheet'!I31/HistoricalFS!J43,0) -> 15.5 | ... L48: =IFERROR('Data Sheet'!K31/HistoricalFS!L43,0) -> 14.349997
B49: Dividend Payout Ratio | C49: =IFERROR(C48/C45,0) -> 0.85312214 | D49: =IFERROR(D48/D45,0) -> 0.66180579 | E49: =IFERROR(E48/E45,0) -> 0.6792714 | F49: =IFERROR(F48/F45,0) -> 0.65536016 | G49: =IFERROR(G48/G45,0) -> 0.94695593 | H49: =IFERROR(H48/H45,0) -> 1.2245091 | I49: =IFERROR(I48/I45,0) -> 1.0425493 | J49: =IFERROR(J48/J45,0) -> 1.1084246 | ... L49: =IFERROR(L48/L45,0) -> 1.0405694
B51: Retained Earnings | C51: =IFERROR(IF(C45>C48,1-C49,0),0) -> 0.14687786 | D51: =IFERROR(IF(D45>D48,1-D49,0),0) -> 0.33819421 | E51: =IFERROR(IF(E45>E48,1-E49,0),0) -> 0.3207286 | F51: =IFERROR(IF(F45>F48,1-F49,0),0) -> 0.34463984 | G51: =IFERROR(IF(G45>G48,1-G49,0),0) -> 0.053044068 | H51: =IFERROR(IF(H45>H48,1-H49,0),0) -> 0 | I51: =IFERROR(IF(I45>I48,1-I49,0),0) -> 0 | J51: =IFERROR(IF(J45>J48,1-J49,0),0) -> 0 | ... L51: =IFERROR(IF(L45>L48,1-L49,0),0) -> 0
A53: # | B53: Balance Sheet
B54: Equity Share Capital | C54: =IFERROR('Data Sheet'!B57,0) -> 804.72 | D54: =IFERROR('Data Sheet'!C57,0) -> 1214.74 | E54: =IFERROR('Data Sheet'!D57,0) -> 1220.43 | F54: =IFERROR('Data Sheet'!E57,0) -> 1225.86 | G54: =IFERROR('Data Sheet'!F57,0) -> 1229.22 | H54: =IFERROR('Data Sheet'!G57,0) -> 1230.88 | I54: =IFERROR('Data Sheet'!H57,0) -> 1232.33 | J54: =IFERROR('Data Sheet'!I57,0) -> 1242.8 | ... L54: =IFERROR('Data Sheet'!K57,0) -> 1251.41
B55: Reserves | C55: =IFERROR('Data Sheet'!B58,0) -> 41874.8 | D55: =IFERROR('Data Sheet'!C58,0) -> 45198.19 | E55: =IFERROR('Data Sheet'!D58,0) -> 51289.68 | F55: =IFERROR('Data Sheet'!E58,0) -> 57915.01 | G55: =IFERROR('Data Sheet'!F58,0) -> 64044.04 | H55: =IFERROR('Data Sheet'!G58,0) -> 59116.46 | I55: =IFERROR('Data Sheet'!H58,0) -> 61223.24 | J55: =IFERROR('Data Sheet'!I58,0) -> 67912.46 | ... L55: =IFERROR('Data Sheet'!K58,0) -> 68778.64
B56: Borrowings | C56: =IFERROR('Data Sheet'!B59,0) -> 83.78 | D56: =IFERROR('Data Sheet'!C59,0) -> 45.72 | E56: =IFERROR('Data Sheet'!D59,0) -> 35.92 | F56: =IFERROR('Data Sheet'!E59,0) -> 13.44 | G56: =IFERROR('Data Sheet'!F59,0) -> 277.45 | H56: =IFERROR('Data Sheet'!G59,0) -> 270.83 | I56: =IFERROR('Data Sheet'!H59,0) -> 249.44 | J56: =IFERROR('Data Sheet'!I59,0) -> 306.04 | ... L56: =IFERROR('Data Sheet'!K59,0) -> 284.54
B57: Other Liabilities | C57: =IFERROR('Data Sheet'!B60,0) -> 8888.04 | D57: =IFERROR('Data Sheet'!C60,0) -> 9439.67 | E57: =IFERROR('Data Sheet'!D60,0) -> 11694.85 | F57: =IFERROR('Data Sheet'!E60,0) -> 12584.73 | G57: =IFERROR('Data Sheet'!F60,0) -> 11760.04 | H57: =IFERROR('Data Sheet'!G60,0) -> 13142.59 | I57: =IFERROR('Data Sheet'!H60,0) -> 14491.01 | J57: =IFERROR('Data Sheet'!I60,0) -> 16369.66 | ... L57: =IFERROR('Data Sheet'!K60,0) -> 17688.11
B58: Total Liabilities | C58: =SUM(C54:C57) -> 51651.34 | D58: =SUM(D54:D57) -> 55898.32 | E58: =SUM(E54:E57) -> 64240.88 | F58: =SUM(F54:F57) -> 71739.04 | G58: =SUM(G54:G57) -> 77310.75 | H58: =SUM(H54:H57) -> 73760.76 | I58: =SUM(I54:I57) -> 77196.02 | J58: =SUM(J54:J57) -> 85830.96 | ... L58: =SUM(L54:L57) -> 88002.7
B60: Fixed Assets Net Block | C60: =IFERROR('Data Sheet'!B62,0) -> 15106.63 | D60: =IFERROR('Data Sheet'!C62,0) -> 15893.48 | E60: =IFERROR('Data Sheet'!D62,0) -> 16523.96 | F60: =IFERROR('Data Sheet'!E62,0) -> 19374.19 | G60: =IFERROR('Data Sheet'!F62,0) -> 21713.34 | H60: =IFERROR('Data Sheet'!G62,0) -> 23298.48 | I60: =IFERROR('Data Sheet'!H62,0) -> 24231.59 | J60: =IFERROR('Data Sheet'!I62,0) -> 25851.27 | ... L60: =IFERROR('Data Sheet'!K62,0) -> 21954.85
B61: Capital Work in Progress | C61: =IFERROR('Data Sheet'!B63,0) -> 2559.72 | D61: =IFERROR('Data Sheet'!C63,0) -> 3729.89 | E61: =IFERROR('Data Sheet'!D63,0) -> 5508.33 | F61: =IFERROR('Data Sheet'!E63,0) -> 4136.42 | G61: =IFERROR('Data Sheet'!F63,0) -> 3256.46 | H61: =IFERROR('Data Sheet'!G63,0) -> 4011.29 | I61: =IFERROR('Data Sheet'!H63,0) -> 3225.54 | J61: =IFERROR('Data Sheet'!I63,0) -> 3003.3 | ... L61: =IFERROR('Data Sheet'!K63,0) -> 1090.91
B62: Investments | C62: =IFERROR('Data Sheet'!B64,0) -> 11747.59 | D62: =IFERROR('Data Sheet'!C64,0) -> 17581.38 | E62: =IFERROR('Data Sheet'!D64,0) -> 22052.86 | F62: =IFERROR('Data Sheet'!E64,0) -> 25043.49 | G62: =IFERROR('Data Sheet'!F64,0) -> 28663.35 | H62: =IFERROR('Data Sheet'!G64,0) -> 24870.87 | I62: =IFERROR('Data Sheet'!H64,0) -> 24841.01 | J62: =IFERROR('Data Sheet'!I64,0) -> 29415.02 | ... L62: =IFERROR('Data Sheet'!K64,0) -> 34719.82
B63: Other Assets | C63: =IFERROR('Data Sheet'!B65-SUM('Data Sheet'!B67:B69),0) -> 5194.82 | D63: =IFERROR('Data Sheet'!C65-SUM('Data Sheet'!C67:C69),0) -> 5135.78 | E63: =IFERROR('Data Sheet'!D65-SUM('Data Sheet'!D67:D69),0) -> 7078.75 | F63: =IFERROR('Data Sheet'!E65-SUM('Data Sheet'!E67:E69),0) -> 7138.07 | G63: =IFERROR('Data Sheet'!F65-SUM('Data Sheet'!F67:F69),0) -> 4958.45 | H63: =IFERROR('Data Sheet'!G65-SUM('Data Sheet'!G67:G69),0) -> 4022.24 | I63: =IFERROR('Data Sheet'!H65-SUM('Data Sheet'!H67:H69),0) -> 6917.41 | J63: =IFERROR('Data Sheet'!I65-SUM('Data Sheet'!I67:I69),0) -> 7953.85 | ... L63: =IFERROR('Data Sheet'!K65-SUM('Data Sheet'!K67:K69),0) -> 5867.53
B64: Total Non-Current Assets | C64: =SUM(C60:C63) -> 34608.76 | D64: =SUM(D60:D63) -> 42340.53 | E64: =SUM(E60:E63) -> 51163.9 | F64: =SUM(F60:F63) -> 55692.17 | G64: =SUM(G60:G63) -> 58591.6 | H64: =SUM(H60:H63) -> 56202.88 | I64: =SUM(I60:I63) -> 59215.55 | J64: =SUM(J60:J63) -> 66223.44 | ... L64: =SUM(L60:L63) -> 63633.11
B66: Receivables | C66: =IFERROR('Data Sheet'!B67,0) -> 1917.18 | D66: =IFERROR('Data Sheet'!C67,0) -> 2474.29 | E66: =IFERROR('Data Sheet'!D67,0) -> 2682.29 | F66: =IFERROR('Data Sheet'!E67,0) -> 4035.28 | G66: =IFERROR('Data Sheet'!F67,0) -> 2562.48 | H66: =IFERROR('Data Sheet'!G67,0) -> 2501.7 | I66: =IFERROR('Data Sheet'!H67,0) -> 2461.9 | J66: =IFERROR('Data Sheet'!I67,0) -> 2956.17 | ... L66: =IFERROR('Data Sheet'!K67,0) -> 4719.67
B67: Inventory | C67: =IFERROR('Data Sheet'!B68,0) -> 9062.1 | D67: =IFERROR('Data Sheet'!C68,0) -> 8116.1 | E67: =IFERROR('Data Sheet'!D68,0) -> 7495.09 | F67: =IFERROR('Data Sheet'!E68,0) -> 7859.56 | G67: =IFERROR('Data Sheet'!F68,0) -> 8879.33 | H67: =IFERROR('Data Sheet'!G68,0) -> 10397.16 | I67: =IFERROR('Data Sheet'!H68,0) -> 10864.15 | J67: =IFERROR('Data Sheet'!I68,0) -> 11771.16 | ... L67: =IFERROR('Data Sheet'!K68,0) -> 15637.56
B68: Cash & Bank | C68: =IFERROR('Data Sheet'!B69,0) -> 6063.3 | D68: =IFERROR('Data Sheet'!C69,0) -> 2967.4 | E68: =IFERROR('Data Sheet'!D69,0) -> 2899.6 | F68: =IFERROR('Data Sheet'!E69,0) -> 4152.03 | G68: =IFERROR('Data Sheet'!F69,0) -> 7277.34 | H68: =IFERROR('Data Sheet'!G69,0) -> 4659.02 | I68: =IFERROR('Data Sheet'!H69,0) -> 4654.42 | J68: =IFERROR('Data Sheet'!I69,0) -> 4880.19 | ... L68: =IFERROR('Data Sheet'!K69,0) -> 4012.36
B69: Total Current Assets | C69: =SUM(C66:C68) -> 17042.58 | D69: =SUM(D66:D68) -> 13557.79 | E69: =SUM(E66:E68) -> 13076.98 | F69: =SUM(F66:F68) -> 16046.87 | G69: =SUM(G66:G68) -> 18719.15 | H69: =SUM(H66:H68) -> 17557.88 | I69: =SUM(I66:I68) -> 17980.47 | J69: =SUM(J66:J68) -> 19607.52 | ... L69: =SUM(L66:L68) -> 24369.59
B71: Total Assets | C71: =SUM(C69,C64) -> 51651.34 | D71: =SUM(D69,D64) -> 55898.32 | E71: =SUM(E69,E64) -> 64240.88 | F71: =SUM(F69,F64) -> 71739.04 | G71: =SUM(G69,G64) -> 77310.75 | H71: =SUM(H69,H64) -> 73760.76 | I71: =SUM(I69,I64) -> 77196.02 | J71: =SUM(J69,J64) -> 85830.96 | ... L71: =SUM(L69,L64) -> 88002.7
B73: Check | C73: =C71=C58 -> TRUE | D73: =D71=D58 -> TRUE | E73: =E71=E58 -> TRUE | F73: =F71=F58 -> TRUE | G73: =G71=G58 -> TRUE | H73: =H71=H58 -> TRUE | I73: =I71=I58 -> TRUE | J73: =J71=J58 -> TRUE | ... L73: =L71=L58 -> TRUE
A75: # | B75: Cash Flows Statement
B77: Cash Flow from Operating Activity | C77: =IFERROR('Data Sheet'!B82,0) -> 9799.04 | D77: =IFERROR('Data Sheet'!C82,0) -> 10627.31 | E77: =IFERROR('Data Sheet'!D82,0) -> 13169.4 | F77: =IFERROR('Data Sheet'!E82,0) -> 12583.41 | G77: =IFERROR('Data Sheet'!F82,0) -> 14689.66 | H77: =IFERROR('Data Sheet'!G82,0) -> 12526.97 | I77: =IFERROR('Data Sheet'!H82,0) -> 15775.51 | J77: =IFERROR('Data Sheet'!I82,0) -> 18877.55 | ... L77: =IFERROR('Data Sheet'!K82,0) -> 17627.04
B78: Cash Flow from Investing Activity | C78: =IFERROR('Data Sheet'!B83,0) -> -3920.73 | D78: =IFERROR('Data Sheet'!C83,0) -> -3250.93 | E78: =IFERROR('Data Sheet'!D83,0) -> -7113.89 | F78: =IFERROR('Data Sheet'!E83,0) -> -5545.68 | G78: =IFERROR('Data Sheet'!F83,0) -> -6174.02 | H78: =IFERROR('Data Sheet'!G83,0) -> 5739.98 | I78: =IFERROR('Data Sheet'!H83,0) -> -2238.49 | J78: =IFERROR('Data Sheet'!I83,0) -> -5732.29 | ... L78: =IFERROR('Data Sheet'!K83,0) -> -563.84
B79: Cash Flow from Financing Activity | C79: =IFERROR('Data Sheet'!B84,0) -> -5612.52 | D79: =IFERROR('Data Sheet'!C84,0) -> -7301.03 | E79: =IFERROR('Data Sheet'!D84,0) -> -6221.13 | F79: =IFERROR('Data Sheet'!E84,0) -> -6868.64 | G79: =IFERROR('Data Sheet'!F84,0) -> -8181.48 | H79: =IFERROR('Data Sheet'!G84,0) -> -18633.83 | I79: =IFERROR('Data Sheet'!H84,0) -> -13580.5 | J79: =IFERROR('Data Sheet'!I84,0) -> -13006.03 | ... L79: =IFERROR('Data Sheet'!K84,0) -> -17037.4
B81: Net Cash Flows | C81: =SUM(C77:C79) -> 265.79 | D81: =SUM(D77:D79) -> 75.35 | E81: =SUM(E77:E79) -> -165.62 | F81: =SUM(F77:F79) -> 169.09 | G81: =SUM(G77:G79) -> 334.16 | H81: =SUM(H77:H79) -> -366.88 | I81: =SUM(I77:I79) -> -43.48 | J81: =SUM(J77:J79) -> 139.23 | ... L81: =SUM(L77:L79) -> 25.8
A83: # | B83: Cash Flows Statement (Expanded)
B85: Cash Flow from Operating Activity
B86: Profit from operations | C86: =IFERROR('Raw CF'!E4,0) -> 15154 | D86: =IFERROR('Raw CF'!F4,0) -> 16075 | E86: =IFERROR('Raw CF'!G4,0) -> 17433 | F86: =IFERROR('Raw CF'!H4,0) -> 18862 | G86: =IFERROR('Raw CF'!I4,0) -> 19416 | H86: =IFERROR('Raw CF'!J4,0) -> 17326 | I86: =IFERROR('Raw CF'!K4,0) -> 20857 | J86: =IFERROR('Raw CF'!L4,0) -> 26052 | ... L86: =IFERROR('Raw CF'!N4,0) -> 26719
B87: Receivables | C87: =IFERROR('Raw CF'!E5,0) -> -207 | D87: =IFERROR('Raw CF'!F5,0) -> -870 | E87: =IFERROR('Raw CF'!G5,0) -> -964 | F87: =IFERROR('Raw CF'!H5,0) -> -755 | G87: =IFERROR('Raw CF'!I5,0) -> 1411 | H87: =IFERROR('Raw CF'!J5,0) -> -66 | I87: =IFERROR('Raw CF'!K5,0) -> -732 | J87: =IFERROR('Raw CF'!L5,0) -> -884 | ... L87: =IFERROR('Raw CF'!N5,0) -> -1023
B88: Inventory | C88: =IFERROR('Raw CF'!E6,0) -> -693 | D88: =IFERROR('Raw CF'!F6,0) -> 593 | E88: =IFERROR('Raw CF'!G6,0) -> 602 | F88: =IFERROR('Raw CF'!H6,0) -> -359 | G88: =IFERROR('Raw CF'!I6,0) -> -508 | H88: =IFERROR('Raw CF'!J6,0) -> -1460 | I88: =IFERROR('Raw CF'!K6,0) -> -466 | J88: =IFERROR('Raw CF'!L6,0) -> -1098 | ... L88: =IFERROR('Raw CF'!N6,0) -> -2975
B89: Payables | C89: =IFERROR('Raw CF'!E7,0) -> 622 | D89: =IFERROR('Raw CF'!F7,0) -> 321 | E89: =IFERROR('Raw CF'!G7,0) -> 2098 | F89: =IFERROR('Raw CF'!H7,0) -> 639 | G89: =IFERROR('Raw CF'!I7,0) -> -607 | H89: =IFERROR('Raw CF'!J7,0) -> 1112 | I89: =IFERROR('Raw CF'!K7,0) -> 1099 | J89: =IFERROR('Raw CF'!L7,0) -> 1058 | ... L89: =IFERROR('Raw CF'!N7,0) -> 1256
B90: Working capital changes | C90: =IFERROR('Raw CF'!E8,0) -> -277 | D90: =IFERROR('Raw CF'!F8,0) -> 44 | E90: =IFERROR('Raw CF'!G8,0) -> 1736 | F90: =IFERROR('Raw CF'!H8,0) -> -476 | G90: =IFERROR('Raw CF'!I8,0) -> 296 | H90: =IFERROR('Raw CF'!J8,0) -> -413 | I90: =IFERROR('Raw CF'!K8,0) -> -100 | J90: =IFERROR('Raw CF'!L8,0) -> -924 | ... L90: =IFERROR('Raw CF'!N8,0) -> -2742
B91: Direct taxes | C91: =IFERROR('Raw CF'!E9,0) -> -5078 | D91: =IFERROR('Raw CF'!F9,0) -> -5492 | E91: =IFERROR('Raw CF'!G9,0) -> -6000 | F91: =IFERROR('Raw CF'!H9,0) -> -5803 | G91: =IFERROR('Raw CF'!I9,0) -> -5023 | H91: =IFERROR('Raw CF'!J9,0) -> -4387 | I91: =IFERROR('Raw CF'!K9,0) -> -4982 | J91: =IFERROR('Raw CF'!L9,0) -> -6250 | ... L91: =IFERROR('Raw CF'!N9,0) -> -6350
B92: Cash Generated from Operations | C92: =IFERROR(SUM(C86:C91),0) -> 9521 | D92: =IFERROR(SUM(D86:D91),0) -> 10671 | E92: =IFERROR(SUM(E86:E91),0) -> 14905 | F92: =IFERROR(SUM(F86:F91),0) -> 12108 | G92: =IFERROR(SUM(G86:G91),0) -> 14985 | H92: =IFERROR(SUM(H86:H91),0) -> 12112 | I92: =IFERROR(SUM(I86:I91),0) -> 15676 | J92: =IFERROR(SUM(J86:J91),0) -> 17954 | ... L92: =IFERROR(SUM(L86:L91),0) -> 14885
B94: Cash Flow from Investing Activity
B95: Fixed assets purchased | C95: =IFERROR('Raw CF'!E11,0) -> -2348 | D95: =IFERROR('Raw CF'!F11,0) -> -3122 | E95: =IFERROR('Raw CF'!G11,0) -> -2878 | F95: =IFERROR('Raw CF'!H11,0) -> -3169 | G95: =IFERROR('Raw CF'!I11,0) -> -2441 | H95: =IFERROR('Raw CF'!J11,0) -> -1837 | I95: =IFERROR('Raw CF'!K11,0) -> -2142 | J95: =IFERROR('Raw CF'!L11,0) -> -2743 | ... L95: =IFERROR('Raw CF'!N11,0) -> -2279
B96: Fixed assets sold | C96: =IFERROR('Raw CF'!E12,0) -> 8 | D96: =IFERROR('Raw CF'!F12,0) -> 50 | E96: =IFERROR('Raw CF'!G12,0) -> 80 | F96: =IFERROR('Raw CF'!H12,0) -> 28 | G96: =IFERROR('Raw CF'!I12,0) -> 27 | H96: =IFERROR('Raw CF'!J12,0) -> 3 | I96: =IFERROR('Raw CF'!K12,0) -> 133 | J96: =IFERROR('Raw CF'!L12,0) -> 49 | ... L96: =IFERROR('Raw CF'!N12,0) -> 175
B97: Investments purchased | C97: =IFERROR('Raw CF'!E13,0) -> -154081 | D97: =IFERROR('Raw CF'!F13,0) -> -85683 | E97: =IFERROR('Raw CF'!G13,0) -> -98330 | F97: =IFERROR('Raw CF'!H13,0) -> -94187 | G97: =IFERROR('Raw CF'!I13,0) -> -79835 | H97: =IFERROR('Raw CF'!J13,0) -> -57553 | I97: =IFERROR('Raw CF'!K13,0) -> -69776 | J97: =IFERROR('Raw CF'!L13,0) -> -80932 | ... L97: =IFERROR('Raw CF'!N13,0) -> -66373
B98: Investments sold | C98: =IFERROR('Raw CF'!E14,0) -> 150651 | D98: =IFERROR('Raw CF'!F14,0) -> 81034 | E98: =IFERROR('Raw CF'!G14,0) -> 95017 | F98: =IFERROR('Raw CF'!H14,0) -> 92454 | G98: =IFERROR('Raw CF'!I14,0) -> 75835 | H98: =IFERROR('Raw CF'!J14,0) -> 62797 | I98: =IFERROR('Raw CF'!K14,0) -> 70992 | J98: =IFERROR('Raw CF'!L14,0) -> 77230 | ... L98: =IFERROR('Raw CF'!N14,0) -> 67311
B99: Interest received | C99: =IFERROR('Raw CF'!E15,0) -> 741 | D99: =IFERROR('Raw CF'!F15,0) -> 756 | E99: =IFERROR('Raw CF'!G15,0) -> 736 | F99: =IFERROR('Raw CF'!H15,0) -> 1184 | G99: =IFERROR('Raw CF'!I15,0) -> 1513 | H99: =IFERROR('Raw CF'!J15,0) -> 1275 | I99: =IFERROR('Raw CF'!K15,0) -> 1035 | J99: =IFERROR('Raw CF'!L15,0) -> 1324 | ... L99: =IFERROR('Raw CF'!N15,0) -> 1072
B100: Dividends received | C100: =IFERROR('Raw CF'!E16,0) -> 64 | D100: =IFERROR('Raw CF'!F16,0) -> 4 | E100: =IFERROR('Raw CF'!G16,0) -> 13 | F100: =IFERROR('Raw CF'!H16,0) -> 13 | G100: =IFERROR('Raw CF'!I16,0) -> 17 | H100: =IFERROR('Raw CF'!J16,0) -> 7 | I100: =IFERROR('Raw CF'!K16,0) -> 16 | J100: =IFERROR('Raw CF'!L16,0) -> 19 | ... L100: =IFERROR('Raw CF'!N16,0) -> 38
B101: Invest in subsidiaries | C101: =IFERROR('Raw CF'!E17,0) -> -8 | D101: =IFERROR('Raw CF'!F17,0) -> 0 | E101: =IFERROR('Raw CF'!G17,0) -> 0 | F101: =IFERROR('Raw CF'!H17,0) -> 0 | G101: =IFERROR('Raw CF'!I17,0) -> 0 | H101: =IFERROR('Raw CF'!J17,0) -> 0 | I101: =IFERROR('Raw CF'!K17,0) -> 0 | J101: =IFERROR('Raw CF'!L17,0) -> 0 | ... L101: =IFERROR('Raw CF'!N17,0) -> 0
B102: Investment in group cos | C102: =IFERROR('Raw CF'!E18,0) -> 0 | D102: =IFERROR('Raw CF'!F18,0) -> 0 | E102: =IFERROR('Raw CF'!G18,0) -> 0 | F102: =IFERROR('Raw CF'!H18,0) -> 0 | G102: =IFERROR('Raw CF'!I18,0) -> 0 | H102: =IFERROR('Raw CF'!J18,0) -> -2 | I102: =IFERROR('Raw CF'!K18,0) -> -2 | J102: =IFERROR('Raw CF'!L18,0) -> -2 | ... L102: =IFERROR('Raw CF'!N18,0) -> -30
B103: Redemp n Canc of Shares | C103: =IFERROR('Raw CF'!E19,0) -> 0 | D103: =IFERROR('Raw CF'!F19,0) -> 129 | E103: =IFERROR('Raw CF'!G19,0) -> 18 | F103: =IFERROR('Raw CF'!H19,0) -> 18 | G103: =IFERROR('Raw CF'!I19,0) -> 0 | H103: =IFERROR('Raw CF'!J19,0) -> 0 | I103: =IFERROR('Raw CF'!K19,0) -> 0 | J103: =IFERROR('Raw CF'!L19,0) -> 56 | ... L103: =IFERROR('Raw CF'!N19,0) -> 0
B104: Other investing items | C104: =IFERROR('Raw CF'!E20,0) -> 1052 | D104: =IFERROR('Raw CF'!F20,0) -> 3579 | E104: =IFERROR('Raw CF'!G20,0) -> -1769 | F104: =IFERROR('Raw CF'!H20,0) -> -1887 | G104: =IFERROR('Raw CF'!I20,0) -> -1290 | H104: =IFERROR('Raw CF'!J20,0) -> 1051 | I104: =IFERROR('Raw CF'!K20,0) -> -2494 | J104: =IFERROR('Raw CF'!L20,0) -> -733 | ... L104: =IFERROR('Raw CF'!N20,0) -> -478
B105: Cash from Investments | C105: =SUM(C95:C104) -> -3921 | D105: =SUM(D95:D104) -> -3253 | E105: =SUM(E95:E104) -> -7113 | F105: =SUM(F95:F104) -> -5546 | G105: =SUM(G95:G104) -> -6174 | H105: =SUM(H95:H104) -> 5741 | I105: =SUM(I95:I104) -> -2238 | J105: =SUM(J95:J104) -> -5732 | ... L105: =SUM(L95:L104) -> -564
B107: Cash Flow from Financing Activity
B108: Proceeds from shares | C108: =IFERROR('Raw CF'!E22,0) -> 532 | D108: =IFERROR('Raw CF'!F22,0) -> 1067 | E108: =IFERROR('Raw CF'!G22,0) -> 913 | F108: =IFERROR('Raw CF'!H22,0) -> 969 | G108: =IFERROR('Raw CF'!I22,0) -> 625 | H108: =IFERROR('Raw CF'!J22,0) -> 291 | I108: =IFERROR('Raw CF'!K22,0) -> 292 | J108: =IFERROR('Raw CF'!L22,0) -> 2477 | ... L108: =IFERROR('Raw CF'!N22,0) -> 797
B109: Proceeds from borrowings | C109: =IFERROR('Raw CF'!E23,0) -> 0 | D109: =IFERROR('Raw CF'!F23,0) -> 0 | E109: =IFERROR('Raw CF'!G23,0) -> 11 | F109: =IFERROR('Raw CF'!H23,0) -> 0 | G109: =IFERROR('Raw CF'!I23,0) -> 0 | H109: =IFERROR('Raw CF'!J23,0) -> 0 | I109: =IFERROR('Raw CF'!K23,0) -> 0 | J109: =IFERROR('Raw CF'!L23,0) -> 0 | ... L109: =IFERROR('Raw CF'!N23,0) -> 90
B110: Repayment of borrowings | C110: =IFERROR('Raw CF'!E24,0) -> -13 | D110: =IFERROR('Raw CF'!F24,0) -> -13 | E110: =IFERROR('Raw CF'!G24,0) -> -8 | F110: =IFERROR('Raw CF'!H24,0) -> -18 | G110: =IFERROR('Raw CF'!I24,0) -> -3 | H110: =IFERROR('Raw CF'!J24,0) -> -2 | I110: =IFERROR('Raw CF'!K24,0) -> -1 | J110: =IFERROR('Raw CF'!L24,0) -> -1 | ... L110: =IFERROR('Raw CF'!N24,0) -> -54
B111: Interest paid fin | C111: =IFERROR('Raw CF'!E25,0) -> -28 | D111: =IFERROR('Raw CF'!F25,0) -> -25 | E111: =IFERROR('Raw CF'!G25,0) -> -49 | F111: =IFERROR('Raw CF'!H25,0) -> -98 | G111: =IFERROR('Raw CF'!I25,0) -> -44 | H111: =IFERROR('Raw CF'!J25,0) -> -41 | I111: =IFERROR('Raw CF'!K25,0) -> -40 | J111: =IFERROR('Raw CF'!L25,0) -> -41 | ... L111: =IFERROR('Raw CF'!N25,0) -> -50
B112: Dividends paid | C112: =IFERROR('Raw CF'!E26,0) -> -5133 | D112: =IFERROR('Raw CF'!F26,0) -> -6994 | E112: =IFERROR('Raw CF'!G26,0) -> -5952 | F112: =IFERROR('Raw CF'!H26,0) -> -6519 | G112: =IFERROR('Raw CF'!I26,0) -> -7302 | H112: =IFERROR('Raw CF'!J26,0) -> -18881 | I112: =IFERROR('Raw CF'!K26,0) -> -13788 | J112: =IFERROR('Raw CF'!L26,0) -> -15418 | ... L112: =IFERROR('Raw CF'!N26,0) -> -17782
B113: Financial liabilities | C113: =IFERROR('Raw CF'!E27,0) -> 0 | D113: =IFERROR('Raw CF'!F27,0) -> 0 | E113: =IFERROR('Raw CF'!G27,0) -> 0 | F113: =IFERROR('Raw CF'!H27,0) -> 0 | G113: =IFERROR('Raw CF'!I27,0) -> -49 | H113: =IFERROR('Raw CF'!J27,0) -> -55 | I113: =IFERROR('Raw CF'!K27,0) -> -59 | J113: =IFERROR('Raw CF'!L27,0) -> -59 | ... L113: =IFERROR('Raw CF'!N27,0) -> -66
B114: Other financing items | C114: =IFERROR('Raw CF'!E28,0) -> -971 | D114: =IFERROR('Raw CF'!F28,0) -> -1335 | E114: =IFERROR('Raw CF'!G28,0) -> -1136 | F114: =IFERROR('Raw CF'!H28,0) -> -1203 | G114: =IFERROR('Raw CF'!I28,0) -> -1409 | H114: =IFERROR('Raw CF'!J28,0) -> 55 | I114: =IFERROR('Raw CF'!K28,0) -> 15 | J114: =IFERROR('Raw CF'!L28,0) -> 35 | ... L114: =IFERROR('Raw CF'!N28,0) -> 28
B115: Cash from Financing | C115: =SUM(C108:C114) -> -5613 | D115: =SUM(D108:D114) -> -7300 | E115: =SUM(E108:E114) -> -6221 | F115: =SUM(F108:F114) -> -6869 | G115: =SUM(G108:G114) -> -8182 | H115: =SUM(H108:H114) -> -18633 | I115: =SUM(I108:I114) -> -13581 | J115: =SUM(J108:J114) -> -13007 | ... L115: =SUM(L108:L114) -> -17037
B117: Net Cash Flows | C117: =IFERROR(SUM(C92,C105,C115),0) -> -13 | D117: =IFERROR(SUM(D92,D105,D115),0) -> 118 | E117: =IFERROR(SUM(E92,E105,E115),0) -> 1571 | F117: =IFERROR(SUM(F92,F105,F115),0) -> -307 | G117: =IFERROR(SUM(G92,G105,G115),0) -> 629 | H117: =IFERROR(SUM(H92,H105,H115),0) -> -780 | I117: =IFERROR(SUM(I92,I105,I115),0) -> -143 | J117: =IFERROR(SUM(J92,J105,J115),0) -> -785 | ... L117: =IFERROR(SUM(L92,L105,L115),0) -> -2716

Sheet Common Size Statement
B2: ='Data Sheet'!B1 -> ITC LTD
B3: (ITC | BSE Code: 540376)
B4: =CONCATENATE("INR"," ", 'Data Sheet'!B8) -> INR 409.75
B5: 52 Week (High - INR 410.45 & Low - INR 401.90)
A7: # | B7: ="Common Size Income Statement - "&'Data Sheet'!$B$1 -> Common Size Income Statement - ITC LTD
B8: Particulars | C8: ='Data Sheet'!B$16 -> 42460 | D8: ='Data Sheet'!C$16 -> 42825 | E8: ='Data Sheet'!D$16 -> 43190 | F8: ='Data Sheet'!E$16 -> 43555 | G8: ='Data Sheet'!F$16 -> 43921 | H8: ='Data Sheet'!G$16 -> 44286 | I8: ='Data Sheet'!H$16 -> 44651 | J8: ='Data Sheet'!I$16 -> 45016 | ... L8: ='Data Sheet'!K$16 -> 45747
B10: ='Data Sheet'!A17 -> Sales | C10: ='Data Sheet'!B17/'Data Sheet'!B$17 -> 1 | D10: ='Data Sheet'!C17/'Data Sheet'!C$17 -> 1 | E10: ='Data Sheet'!D17/'Data Sheet'!D$17 -> 1 | F10: ='Data Sheet'!E17/'Data Sheet'!E$17 -> 1 | G10: ='Data Sheet'!F17/'Data Sheet'!F$17 -> 1 | H10: ='Data Sheet'!G17/'Data Sheet'!G$17 -> 1 | I10: ='Data Sheet'!H17/'Data Sheet'!H$17 -> 1 | J10: ='Data Sheet'!I17/'Data Sheet'!I$17 -> 1 | ... L10: ='Data Sheet'!K17/'Data Sheet'!K$17 -> 1
B11: ='Data Sheet'!A18 -> Raw Material Cost | C11: ='Data Sheet'!B18/'Data Sheet'!B$17 -> 0.35119016 | D11: ='Data Sheet'!C18/'Data Sheet'!C$17 -> 0.36140887 | E11: ='Data Sheet'!D18/'Data Sheet'!D$17 -> 0.3412677 | F11: ='Data Sheet'!E18/'Data Sheet'!E$17 -> 0.36457743 | G11: ='Data Sheet'!F18/'Data Sheet'!F$17 -> 0.36544727 | H11: ='Data Sheet'!G18/'Data Sheet'!G$17 -> 0.42179833 | I11: ='Data Sheet'!H18/'Data Sheet'!H$17 -> 0.44638924 | J11: ='Data Sheet'!I18/'Data Sheet'!I$17 -> 0.41405473 | ... L11: ='Data Sheet'!K18/'Data Sheet'!K$17 -> 0.4341864
B12: ='Data Sheet'!A19 -> Change in Inventory | C12: ='Data Sheet'!B19/'Data Sheet'!B$17 -> 0.0049851883 | D12: ='Data Sheet'!C19/'Data Sheet'!C$17 -> -0.013855582 | E12: ='Data Sheet'!D19/'Data Sheet'!D$17 -> -0.023654432 | F12: ='Data Sheet'!E19/'Data Sheet'!E$17 -> 0.0042033878 | G12: ='Data Sheet'!F19/'Data Sheet'!F$17 -> 0.014236946 | H12: ='Data Sheet'!G19/'Data Sheet'!G$17 -> 0.013099947 | I12: ='Data Sheet'!H19/'Data Sheet'!H$17 -> 0.011311818 | J12: ='Data Sheet'!I19/'Data Sheet'!I$17 -> 0.0050563297 | ... L12: ='Data Sheet'!K19/'Data Sheet'!K$17 -> 0.0096338001
B13: ='Data Sheet'!A20 -> Power and Fuel | C13: ='Data Sheet'!B20/'Data Sheet'!B$17 -> 0.014591716 | D13: ='Data Sheet'!C20/'Data Sheet'!C$17 -> 0.013662913 | E13: ='Data Sheet'!D20/'Data Sheet'!D$17 -> 0.015040643 | F13: ='Data Sheet'!E20/'Data Sheet'!E$17 -> 0.01544759 | G13: ='Data Sheet'!F20/'Data Sheet'!F$17 -> 0.015810617 | H13: ='Data Sheet'!G20/'Data Sheet'!G$17 -> 0.014202116 | I13: ='Data Sheet'!H20/'Data Sheet'!H$17 -> 0.01467189 | J13: ='Data Sheet'!I20/'Data Sheet'!I$17 -> 0.017376718 | ... L13: ='Data Sheet'!K20/'Data Sheet'!K$17 -> 0.012948842
B14: ='Data Sheet'!A21 -> Other Mfr. Exp | C14: ='Data Sheet'!B21/'Data Sheet'!B$17 -> 0.040354816 | D14: ='Data Sheet'!C21/'Data Sheet'!C$17 -> 0.039373264 | E14: ='Data Sheet'!D21/'Data Sheet'!D$17 -> 0.039071609 | F14: ='Data Sheet'!E21/'Data Sheet'!E$17 -> 0.038705549 | G14: ='Data Sheet'!F21/'Data Sheet'!F$17 -> 0.038638973 | H14: ='Data Sheet'!G21/'Data Sheet'!G$17 -> 0.032222131 | I14: ='Data Sheet'!H21/'Data Sheet'!H$17 -> 0.031126792 | J14: ='Data Sheet'!I21/'Data Sheet'!I$17 -> 0.032823348 | ... L14: ='Data Sheet'!K21/'Data Sheet'!K$17 -> 0.031137228
B15: ='Data Sheet'!A22 -> Employee Cost | C15: ='Data Sheet'!B22/'Data Sheet'!B$17 -> 0.087797541 | D15: ='Data Sheet'!C22/'Data Sheet'!C$17 -> 0.084917788 | E15: ='Data Sheet'!D22/'Data Sheet'!D$17 -> 0.086559074 | F15: ='Data Sheet'!E22/'Data Sheet'!E$17 -> 0.086427727 | G15: ='Data Sheet'!F22/'Data Sheet'!F$17 -> 0.086980969 | H15: ='Data Sheet'!G22/'Data Sheet'!G$17 -> 0.090612283 | I15: ='Data Sheet'!H22/'Data Sheet'!H$17 -> 0.080642874 | J15: ='Data Sheet'!I22/'Data Sheet'!I$17 -> 0.080884073 | ... L15: ='Data Sheet'!K22/'Data Sheet'!K$17 -> 0.0819106
B16: ='Data Sheet'!A23 -> Selling and admin | C16: ='Data Sheet'!B23/'Data Sheet'!B$17 -> 0.10874079 | D16: ='Data Sheet'!C23/'Data Sheet'!C$17 -> 0.09773146 | E16: ='Data Sheet'!D23/'Data Sheet'!D$17 -> 0.091023394 | F16: ='Data Sheet'!E23/'Data Sheet'!E$17 -> 0.094051086 | G16: ='Data Sheet'!F23/'Data Sheet'!F$17 -> 0.090885585 | H16: ='Data Sheet'!G23/'Data Sheet'!G$17 -> 0.086012776 | I16: ='Data Sheet'!H23/'Data Sheet'!H$17 -> 0.080112406 | J16: ='Data Sheet'!I23/'Data Sheet'!I$17 -> 0.079020821 | ... L16: ='Data Sheet'!K23/'Data Sheet'!K$17 -> 0.076912282
B17: ='Data Sheet'!A24 -> Other Expenses | C17: ='Data Sheet'!B24/'Data Sheet'!B$17 -> 0.031534161 | D17: ='Data Sheet'!C24/'Data Sheet'!C$17 -> 0.027339154 | E17: ='Data Sheet'!D24/'Data Sheet'!D$17 -> 0.023153154 | F17: ='Data Sheet'!E24/'Data Sheet'!E$17 -> 0.021511358 | G17: ='Data Sheet'!F24/'Data Sheet'!F$17 -> 0.024806379 | H17: ='Data Sheet'!G24/'Data Sheet'!G$17 -> 0.021811726 | I17: ='Data Sheet'!H24/'Data Sheet'!H$17 -> 0.018302555 | J17: ='Data Sheet'!I24/'Data Sheet'!I$17 -> 0.018451465 | ... L17: ='Data Sheet'!K24/'Data Sheet'!K$17 -> 0.02949139
B18: ='Data Sheet'!A25 -> Other Income | C18: ='Data Sheet'!B25/'Data Sheet'!B$17 -> 0.037842065 | D18: ='Data Sheet'!C25/'Data Sheet'!C$17 -> 0.041120615 | E18: ='Data Sheet'!D25/'Data Sheet'!D$17 -> 0.051550395 | F18: ='Data Sheet'!E25/'Data Sheet'!E$17 -> 0.043038024 | G18: ='Data Sheet'!F25/'Data Sheet'!F$17 -> 0.04894579 | H18: ='Data Sheet'!G25/'Data Sheet'!G$17 -> 0.052315944 | I18: ='Data Sheet'!H25/'Data Sheet'!H$17 -> 0.031490386 | J18: ='Data Sheet'!I25/'Data Sheet'!I$17 -> 0.029577957 | ... L18: ='Data Sheet'!K25/'Data Sheet'!K$17 -> 0.23624656
B19: ='Data Sheet'!A26 -> Depreciation | C19: ='Data Sheet'!B26/'Data Sheet'!B$17 -> 0.027490234 | D19: ='Data Sheet'!C26/'Data Sheet'!C$17 -> 0.026954751 | E19: ='Data Sheet'!D26/'Data Sheet'!D$17 -> 0.028453629 | F19: ='Data Sheet'!E26/'Data Sheet'!E$17 -> 0.028891645 | G19: ='Data Sheet'!F26/'Data Sheet'!F$17 -> 0.033306066 | H19: ='Data Sheet'!G26/'Data Sheet'!G$17 -> 0.033407941 | I19: ='Data Sheet'!H26/'Data Sheet'!H$17 -> 0.028566628 | J19: ='Data Sheet'!I26/'Data Sheet'!I$17 -> 0.025508104 | ... L19: ='Data Sheet'!K26/'Data Sheet'!K$17 -> 0.021856705
B20: ='Data Sheet'!A27 -> Interest | C20: ='Data Sheet'!B27/'Data Sheet'!B$17 -> 0.001993514 | D20: ='Data Sheet'!C27/'Data Sheet'!C$17 -> 0.0011464286 | E20: ='Data Sheet'!D27/'Data Sheet'!D$17 -> 0.0026470151 | F20: ='Data Sheet'!E27/'Data Sheet'!E$17 -> 0.0014770505 | G20: ='Data Sheet'!F27/'Data Sheet'!F$17 -> 0.0016477787 | H20: ='Data Sheet'!G27/'Data Sheet'!G$17 -> 0.0011768778 | I20: ='Data Sheet'!H27/'Data Sheet'!H$17 -> 0.00098920694 | J20: ='Data Sheet'!I27/'Data Sheet'!I$17 -> 0.0010966027 | ... L20: ='Data Sheet'!K27/'Data Sheet'!K$17 -> 0.00059822095
B21: ='Data Sheet'!A28 -> Profit before tax | C21: ='Data Sheet'!B28/'Data Sheet'!B$17 -> 0.37913432 | D21: ='Data Sheet'!C28/'Data Sheet'!C$17 -> 0.3747304 | E21: ='Data Sheet'!D28/'Data Sheet'!D$17 -> 0.40067974 | F21: ='Data Sheet'!E28/'Data Sheet'!E$17 -> 0.39615197 | G21: ='Data Sheet'!F28/'Data Sheet'!F$17 -> 0.4056591 | H21: ='Data Sheet'!G28/'Data Sheet'!G$17 -> 0.36417171 | I21: ='Data Sheet'!H28/'Data Sheet'!H$17 -> 0.34200062 | J21: ='Data Sheet'!I28/'Data Sheet'!I$17 -> 0.36541842 | ... L21: ='Data Sheet'!K28/'Data Sheet'!K$17 -> 0.55683869
... B24: ='Data Sheet'!A31 -> Dividend Amount | C24: ='Data Sheet'!B31/'Data Sheet'!B$17 -> 0.17452803 | D24: ='Data Sheet'!C31/'Data Sheet'!C$17 -> 0.13491568 | E24: ='Data Sheet'!D31/'Data Sheet'!D$17 -> 0.14465738 | F24: ='Data Sheet'!E31/'Data Sheet'!E$17 -> 0.14581633 | G24: ='Data Sheet'!F31/'Data Sheet'!F$17 -> 0.25262525 | H24: ='Data Sheet'!G31/'Data Sheet'!G$17 -> 0.2686286 | I24: ='Data Sheet'!H31/'Data Sheet'!H$17 -> 0.23368633 | J24: ='Data Sheet'!I31/'Data Sheet'!I$17 -> 0.27162526 | ... L24: ='Data Sheet'!K31/'Data Sheet'!K$17 -> 0.23840857
B25: EBITDA | C25: =HistoricalFS!C16/'Data Sheet'!B17 -> 0.51105095 | D25: =HistoricalFS!D16/'Data Sheet'!C17 -> 0.48678158 | E25: =HistoricalFS!E16/'Data Sheet'!D17 -> 0.49440654 | F25: =HistoricalFS!F16/'Data Sheet'!E17 -> 0.49904509 | G25: =HistoricalFS!G16/'Data Sheet'!F17 -> 0.50735912 | H25: =HistoricalFS!H16/'Data Sheet'!G17 -> 0.45426509 | I25: =HistoricalFS!I16/'Data Sheet'!H17 -> 0.43848102 | J25: =HistoricalFS!J16/'Data Sheet'!I17 -> 0.45991746 | ... L25: =HistoricalFS!L16/'Data Sheet'!K17 -> 0.44945073
A27: # | B27: ="Common Size Balance Sheet - "&'Data Sheet'!$B$1 -> Common Size Balance Sheet - ITC LTD
B28: Particulars | C28: ='Data Sheet'!B$16 -> 42460 | D28: ='Data Sheet'!C$16 -> 42825 | E28: ='Data Sheet'!D$16 -> 43190 | F28: ='Data Sheet'!E$16 -> 43555 | G28: ='Data Sheet'!F$16 -> 43921 | H28: ='Data Sheet'!G$16 -> 44286 | I28: ='Data Sheet'!H$16 -> 44651 | J28: ='Data Sheet'!I$16 -> 45016 | ... L28: ='Data Sheet'!K$16 -> 45747
B30: Total Liabilities | C30: ='Data Sheet'!B61/'Data Sheet'!B$61 -> 1 | D30: ='Data Sheet'!C61/'Data Sheet'!C$61 -> 1 | E30: ='Data Sheet'!D61/'Data Sheet'!D$61 -> 1 | F30: ='Data Sheet'!E61/'Data Sheet'!E$61 -> 1 | G30: ='Data Sheet'!F61/'Data Sheet'!F$61 -> 1 | H30: ='Data Sheet'!G61/'Data Sheet'!G$61 -> 1 | I30: ='Data Sheet'!H61/'Data Sheet'!H$61 -> 1 | J30: ='Data Sheet'!I61/'Data Sheet'!I$61 -> 1 | ... L30: ='Data Sheet'!K61/'Data Sheet'!K$61 -> 1
B31: ='Data Sheet'!A57 -> Equity Share Capital | C31: ='Data Sheet'!B57/'Data Sheet'!B$61 -> 0.015579847 | D31: ='Data Sheet'!C57/'Data Sheet'!C$61 -> 0.021731243 | E31: ='Data Sheet'!D57/'Data Sheet'!D$61 -> 0.018997716 | F31: ='Data Sheet'!E57/'Data Sheet'!E$61 -> 0.017087767 | G31: ='Data Sheet'!F57/'Data Sheet'!F$61 -> 0.015899729 | H31: ='Data Sheet'!G57/'Data Sheet'!G$61 -> 0.016687464 | I31: ='Data Sheet'!H57/'Data Sheet'!H$61 -> 0.015963647 | J31: ='Data Sheet'!I57/'Data Sheet'!I$61 -> 0.014479624 | ... L31: ='Data Sheet'!K57/'Data Sheet'!K$61 -> 0.014220132
B32: ='Data Sheet'!A58 -> Reserves | C32: ='Data Sheet'!B58/'Data Sheet'!B$61 -> 0.8107205 | D32: ='Data Sheet'!C58/'Data Sheet'!C$61 -> 0.80857868 | E32: ='Data Sheet'!D58/'Data Sheet'!D$61 -> 0.79839629 | F32: ='Data Sheet'!E58/'Data Sheet'!E$61 -> 0.80730116 | G32: ='Data Sheet'!F58/'Data Sheet'!F$61 -> 0.8283976 | H32: ='Data Sheet'!G58/'Data Sheet'!G$61 -> 0.80146219 | I32: ='Data Sheet'!H58/'Data Sheet'!H$61 -> 0.79308804 | J32: ='Data Sheet'!I58/'Data Sheet'!I$61 -> 0.791235 | ... L32: ='Data Sheet'!K58/'Data Sheet'!K$61 -> 0.78155148
B33: ='Data Sheet'!A59 -> Borrowings | C33: ='Data Sheet'!B59/'Data Sheet'!B$61 -> 0.0016220296 | D33: ='Data Sheet'!C59/'Data Sheet'!C$61 -> 0.00081791367 | E33: ='Data Sheet'!D59/'Data Sheet'!D$61 -> 0.00055914552 | F33: ='Data Sheet'!E59/'Data Sheet'!E$61 -> 0.00018734569 | G33: ='Data Sheet'!F59/'Data Sheet'!F$61 -> 0.0035887635 | H33: ='Data Sheet'!G59/'Data Sheet'!G$61 -> 0.0036717355 | I33: ='Data Sheet'!H59/'Data Sheet'!H$61 -> 0.0032312547 | J33: ='Data Sheet'!I59/'Data Sheet'!I$61 -> 0.0035656132 | ... L33: ='Data Sheet'!K59/'Data Sheet'!K$61 -> 0.0032333099
B34: ='Data Sheet'!A60 -> Other Liabilities | C34: ='Data Sheet'!B60/'Data Sheet'!B$61 -> 0.17207763 | D34: ='Data Sheet'!C60/'Data Sheet'!C$61 -> 0.16887216 | E34: ='Data Sheet'!D60/'Data Sheet'!D$61 -> 0.18204685 | F34: ='Data Sheet'!E60/'Data Sheet'!E$61 -> 0.17542373 | G34: ='Data Sheet'!F60/'Data Sheet'!F$61 -> 0.1521139 | H34: ='Data Sheet'!G60/'Data Sheet'!G$61 -> 0.17817861 | I34: ='Data Sheet'!H60/'Data Sheet'!H$61 -> 0.18771706 | J34: ='Data Sheet'!I60/'Data Sheet'!I$61 -> 0.19071976 | ... L34: ='Data Sheet'!K60/'Data Sheet'!K$61 -> 0.20099508
B36: Total Assets | C36: ='Data Sheet'!B66/'Data Sheet'!B$66 -> 1 | D36: ='Data Sheet'!C66/'Data Sheet'!C$66 -> 1 | E36: ='Data Sheet'!D66/'Data Sheet'!D$66 -> 1 | F36: ='Data Sheet'!E66/'Data Sheet'!E$66 -> 1 | G36: ='Data Sheet'!F66/'Data Sheet'!F$66 -> 1 | H36: ='Data Sheet'!G66/'Data Sheet'!G$66 -> 1 | I36: ='Data Sheet'!H66/'Data Sheet'!H$66 -> 1 | J36: ='Data Sheet'!I66/'Data Sheet'!I$66 -> 1 | ... L36: ='Data Sheet'!K66/'Data Sheet'!K$66 -> 1
B37: ='Data Sheet'!A62 -> Net Block | C37: ='Data Sheet'!B62/'Data Sheet'!B$66 -> 0.29247315 | D37: ='Data Sheet'!C62/'Data Sheet'!C$66 -> 0.2843284 | E37: ='Data Sheet'!D62/'Data Sheet'!D$66 -> 0.25721877 | F37: ='Data Sheet'!E62/'Data Sheet'!E$66 -> 0.27006481 | G37: ='Data Sheet'!F62/'Data Sheet'!F$66 -> 0.28085797 | H37: ='Data Sheet'!G62/'Data Sheet'!G$66 -> 0.31586551 | I37: ='Data Sheet'!H62/'Data Sheet'!H$66 -> 0.31389688 | J37: ='Data Sheet'!I62/'Data Sheet'!I$66 -> 0.30118817 | ... L37: ='Data Sheet'!K62/'Data Sheet'!K$66 -> 0.24947928
B38: ='Data Sheet'!A63 -> Capital Work in Progress | C38: ='Data Sheet'!B63/'Data Sheet'!B$66 -> 0.049557669 | D38: ='Data Sheet'!C63/'Data Sheet'!C$66 -> 0.066726335 | E38: ='Data Sheet'!D63/'Data Sheet'!D$66 -> 0.085744934 | F38: ='Data Sheet'!E63/'Data Sheet'!E$66 -> 0.057659261 | G38: ='Data Sheet'!F63/'Data Sheet'!F$66 -> 0.042121697 | H38: ='Data Sheet'!G63/'Data Sheet'!G$66 -> 0.054382439 | I38: ='Data Sheet'!H63/'Data Sheet'!H$66 -> 0.04178376 | J38: ='Data Sheet'!I63/'Data Sheet'!I$66 -> 0.03499087 | ... L38: ='Data Sheet'!K63/'Data Sheet'!K$66 -> 0.012396324
B39: ='Data Sheet'!A64 -> Investments | C39: ='Data Sheet'!B64/'Data Sheet'!B$66 -> 0.22744018 | D39: ='Data Sheet'!C64/'Data Sheet'!C$66 -> 0.3145243 | E39: ='Data Sheet'!D64/'Data Sheet'!D$66 -> 0.3432839 | F39: ='Data Sheet'!E64/'Data Sheet'!E$66 -> 0.34909151 | G39: ='Data Sheet'!F64/'Data Sheet'!F$66 -> 0.37075504 | H39: ='Data Sheet'!G64/'Data Sheet'!G$66 -> 0.33718294 | I39: ='Data Sheet'!H64/'Data Sheet'!H$66 -> 0.32179133 | J39: ='Data Sheet'!I64/'Data Sheet'!I$66 -> 0.34270874 | ... L39: ='Data Sheet'!K64/'Data Sheet'!K$66 -> 0.3945313
B40: ='Data Sheet'!A65 -> Other Assets | C40: =HistoricalFS!C63/'Data Sheet'!B$66 -> 0.10057474 | D40: =HistoricalFS!D63/'Data Sheet'!C$66 -> 0.09187718 | E40: =HistoricalFS!E63/'Data Sheet'!D$66 -> 0.11019074 | F40: =HistoricalFS!F63/'Data Sheet'!E$66 -> 0.099500495 | G40: =HistoricalFS!G63/'Data Sheet'!F$66 -> 0.064136617 | H40: =HistoricalFS!H63/'Data Sheet'!G$66 -> 0.054530891 | I40: =HistoricalFS!I63/'Data Sheet'!H$66 -> 0.089608376 | J40: =HistoricalFS!J63/'Data Sheet'!I$66 -> 0.092668776 | ... L40: =HistoricalFS!L63/'Data Sheet'!K$66 -> 0.066674432
B41: ='Data Sheet'!A67 -> Receivables | C41: ='Data Sheet'!B67/'Data Sheet'!B$66 -> 0.03711772 | D41: ='Data Sheet'!C67/'Data Sheet'!C$66 -> 0.044264121 | E41: ='Data Sheet'!D67/'Data Sheet'!D$66 -> 0.041753631 | F41: ='Data Sheet'!E67/'Data Sheet'!E$66 -> 0.056249428 | G41: ='Data Sheet'!F67/'Data Sheet'!F$66 -> 0.033145196 | H41: ='Data Sheet'!G67/'Data Sheet'!G$66 -> 0.033916408 | I41: ='Data Sheet'!H67/'Data Sheet'!H$66 -> 0.031891541 | J41: ='Data Sheet'!I67/'Data Sheet'!I$66 -> 0.034441768 | ... L41: ='Data Sheet'!K67/'Data Sheet'!K$66 -> 0.053630968
B42: ='Data Sheet'!A68 -> Inventory | C42: ='Data Sheet'!B68/'Data Sheet'!B$66 -> 0.17544753 | D42: ='Data Sheet'!C68/'Data Sheet'!C$66 -> 0.14519399 | E42: ='Data Sheet'!D68/'Data Sheet'!D$66 -> 0.11667166 | F42: ='Data Sheet'!E68/'Data Sheet'!E$66 -> 0.10955764 | G42: ='Data Sheet'!F68/'Data Sheet'!F$66 -> 0.11485246 | H42: ='Data Sheet'!G68/'Data Sheet'!G$66 -> 0.14095788 | I42: ='Data Sheet'!H68/'Data Sheet'!H$66 -> 0.14073459 | J42: ='Data Sheet'!I68/'Data Sheet'!I$66 -> 0.13714352 | ... L42: ='Data Sheet'!K68/'Data Sheet'!K$66 -> 0.17769409
B43: ='Data Sheet'!A69 -> Cash & Bank | C43: ='Data Sheet'!B69/'Data Sheet'!B$66 -> 0.11738902 | D43: ='Data Sheet'!C69/'Data Sheet'!C$66 -> 0.053085674 | E43: ='Data Sheet'!D69/'Data Sheet'!D$66 -> 0.045136368 | F43: ='Data Sheet'!E69/'Data Sheet'!E$66 -> 0.057876855 | G43: ='Data Sheet'!F69/'Data Sheet'!F$66 -> 0.094131023 | H43: ='Data Sheet'!G69/'Data Sheet'!G$66 -> 0.063163937 | I43: ='Data Sheet'!H69/'Data Sheet'!H$66 -> 0.060293523 | J43: ='Data Sheet'!I69/'Data Sheet'!I$66 -> 0.056858155 | ... L43: ='Data Sheet'!K69/'Data Sheet'!K$66 -> 0.045593601

Sheet Ratio Analysis
B2: ='Data Sheet'!B1 -> ITC LTD
B3: (ITC | BSE Code: 540376)
B4: =CONCATENATE("INR"," ", 'Data Sheet'!B8) -> INR 409.75
B5: 52 Week (High - INR 410.45 & Low - INR 401.90)
B7: ="Ratio Analysis - "&'Data Sheet'!B1 -> Ratio Analysis - ITC LTD
B8: Years | C8: ='Data Sheet'!B16 -> 42460 | D8: ='Data Sheet'!C16 -> 42825 | E8: ='Data Sheet'!D16 -> 43190 | F8: ='Data Sheet'!E16 -> 43555 | G8: ='Data Sheet'!F16 -> 43921 | H8: ='Data Sheet'!G16 -> 44286 | I8: ='Data Sheet'!H16 -> 44651 | J8: ='Data Sheet'!I16 -> 45016 | ... L8: ='Data Sheet'!K16 -> 45747 | M8: Trend | N8: Mean | O8: Median
B10: Sales Growth | D10: =IFERROR(HistoricalFS!D11,0) -> 0.09123012 | E10: =IFERROR(HistoricalFS!E11,0) -> 0.015931219 | F10: =IFERROR(HistoricalFS!F11,0) -> 0.11256063 | G10: =IFERROR(HistoricalFS!G11,0) -> 0.021682439 | H10: =IFERROR(HistoricalFS!H11,0) -> -0.0026372963 | I10: =IFERROR(HistoricalFS!I11,0) -> 0.23117498 | J10: =IFERROR(HistoricalFS!J11,0) -> 0.16942152 | K10: =IFERROR(HistoricalFS!K11,0) -> -0.042119724 | L10: =IFERROR(HistoricalFS!L11,0) -> 0.10880596 | N10: =IFERROR(AVERAGE(D10:L10),0) -> 0.078449983 | O10: =IFERROR(MEDIAN(D10:L10),0) -> 0.09123012
B11: EBITDA Growth | D11: =IFERROR(HistoricalFS!D22/HistoricalFS!C22-1,0) -> 0.064550848 | E11: =IFERROR(HistoricalFS!E22/HistoricalFS!D22-1,0) -> 0.067945268 | F11: =IFERROR(HistoricalFS!F22/HistoricalFS!E22-1,0) -> 0.12207796 | G11: =IFERROR(HistoricalFS!G22/HistoricalFS!F22-1,0) -> 0.043487783 | H11: =IFERROR(HistoricalFS!H22/HistoricalFS!G22-1,0) -> -0.1178047 | I11: =IFERROR(HistoricalFS!I22/HistoricalFS!H22-1,0) -> 0.20852129 | J11: =IFERROR(HistoricalFS!J22/HistoricalFS!I22-1,0) -> 0.24637895 | K11: =IFERROR(HistoricalFS!K22/HistoricalFS!J22-1,0) -> -0.020102893 | L11: =IFERROR(HistoricalFS!L22/HistoricalFS!K22-1,0) -> 0.025882649 | N11: =IFERROR(AVERAGE(D11:L11),0) -> 0.07121524 | O11: =IFERROR(MEDIAN(D11:L11),0) -> 0.064550848
B12: EBIT Growth | D12: =IFERROR(HistoricalFS!D31/HistoricalFS!C31-1,0) -> 0.064116562 | E12: =IFERROR(HistoricalFS!E31/HistoricalFS!D31-1,0) -> 0.067584614 | F12: =IFERROR(HistoricalFS!F31/HistoricalFS!E31-1,0) -> 0.12146247 | G12: =IFERROR(HistoricalFS!G31/HistoricalFS!F31-1,0) -> 0.032545193 | H12: =IFERROR(HistoricalFS!H31/HistoricalFS!G31-1,0) -> -0.12879189 | I12: =IFERROR(HistoricalFS!I31/HistoricalFS!H31-1,0) -> 0.22514477 | J12: =IFERROR(HistoricalFS!J31/HistoricalFS!I31-1,0) -> 0.26491869 | K12: =IFERROR(HistoricalFS!K31/HistoricalFS!J31-1,0) -> -0.0094483213 | L12: =IFERROR(HistoricalFS!L31/HistoricalFS!K31-1,0) -> 0.022123426 | N12: =IFERROR(AVERAGE(D12:L12),0) -> 0.073295057 | O12: =IFERROR(MEDIAN(D12:L12),0) -> 0.064116562
B13: EBT Growth | D13: =IFERROR(HistoricalFS!D34/HistoricalFS!C34-1,0) -> 0.066666617 | E13: =IFERROR(HistoricalFS!E34/HistoricalFS!D34-1,0) -> 0.06319243 | F13: =IFERROR(HistoricalFS!F34/HistoricalFS!E34-1,0) -> 0.12525825 | G13: =IFERROR(HistoricalFS!G34/HistoricalFS!F34-1,0) -> 0.032096655 | H13: =IFERROR(HistoricalFS!H34/HistoricalFS!G34-1,0) -> -0.12805801 | I13: =IFERROR(HistoricalFS!I34/HistoricalFS!H34-1,0) -> 0.22586292 | J13: =IFERROR(HistoricalFS!J34/HistoricalFS!I34-1,0) -> 0.26481845 | K13: =IFERROR(HistoricalFS!K34/HistoricalFS!J34-1,0) -> -0.0078559948 | L13: =IFERROR(HistoricalFS!L34/HistoricalFS!K34-1,0) -> 0.021908248 | N13: =IFERROR(AVERAGE(D13:L13),0) -> 0.073765507 | O13: =IFERROR(MEDIAN(D13:L13),0) -> 0.06319243
B14: Net Profit Growth | D14: =IFERROR(HistoricalFS!D40/HistoricalFS!C40-1,0) -> 0.087412304 | E14: =IFERROR(HistoricalFS!E40/HistoricalFS!D40-1,0) -> 0.061279334 | F14: =IFERROR(HistoricalFS!F40/HistoricalFS!E40-1,0) -> 0.16239178 | G14: =IFERROR(HistoricalFS!G40/HistoricalFS!F40-1,0) -> 0.225002 | H14: =IFERROR(HistoricalFS!H40/HistoricalFS!G40-1,0) -> -0.1798442 | I14: =IFERROR(HistoricalFS!I40/HistoricalFS!H40-1,0) -> 0.25795836 | J14: =IFERROR(HistoricalFS!J40/HistoricalFS!I40-1,0) -> 0.27849303 | K14: =IFERROR(HistoricalFS!K40/HistoricalFS!J40-1,0) -> 0.0024069168 | L14: =IFERROR(HistoricalFS!L40/HistoricalFS!K40-1,0) -> -0.0093743668 | N14: =IFERROR(AVERAGE(D14:L14),0) -> 0.098413907 | O14: =IFERROR(MEDIAN(D14:L14),0) -> 0.087412304
B15: Dividend Growth | D15: =IFERROR(HistoricalFS!D48/HistoricalFS!C48-1,0) -> -0.16176398 | E15: =IFERROR(HistoricalFS!E48/HistoricalFS!D48-1,0) -> 0.084208811 | F15: =IFERROR(HistoricalFS!F48/HistoricalFS!E48-1,0) -> 0.11650645 | G15: =IFERROR(HistoricalFS!G48/HistoricalFS!F48-1,0) -> 0.76521571 | H15: =IFERROR(HistoricalFS!H48/HistoricalFS!G48-1,0) -> 0.059113555 | I15: =IFERROR(HistoricalFS!I48/HistoricalFS!H48-1,0) -> 0.069767819 | J15: =IFERROR(HistoricalFS!J48/HistoricalFS!I48-1,0) -> 0.34782561 | K15: =IFERROR(HistoricalFS!K48/HistoricalFS!J48-1,0) -> -0.11290335 | L15: =IFERROR(HistoricalFS!L48/HistoricalFS!K48-1,0) -> 0.043636312 | N15: =IFERROR(AVERAGE(D15:L15),0) -> 0.13462299 | O15: =IFERROR(MEDIAN(D15:L15),0) -> 0.069767819
B17: Gross Margin | C17: =IFERROR(HistoricalFS!C17,0) -> 0.51105095 | D17: =IFERROR(HistoricalFS!D17,0) -> 0.48678158 | E17: =IFERROR(HistoricalFS!E17,0) -> 0.49440654 | F17: =IFERROR(HistoricalFS!F17,0) -> 0.49904509 | G17: =IFERROR(HistoricalFS!G17,0) -> 0.50735912 | H17: =IFERROR(HistoricalFS!H17,0) -> 0.45426509 | I17: =IFERROR(HistoricalFS!I17,0) -> 0.43848102 | J17: =IFERROR(HistoricalFS!J17,0) -> 0.45991746 | ... L17: =IFERROR(HistoricalFS!L17,0) -> 0.44945073 | N17: =IFERROR(AVERAGE(C17:L17),0) -> 0.47757322 | O17: =IFERROR(MEDIAN(C17:L17),0) -> 0.48087812
B18: EBITA Margin | C18: =IFERROR(HistoricalFS!C23,0) -> 0.370776 | D18: =IFERROR(HistoricalFS!D23,0) -> 0.36171097 | E18: =IFERROR(HistoricalFS!E23,0) -> 0.38022999 | F18: =IFERROR(HistoricalFS!F23,0) -> 0.38348265 | G18: =IFERROR(HistoricalFS!G23,0) -> 0.39166716 | H18: =IFERROR(HistoricalFS!H23,0) -> 0.34644059 | I18: =IFERROR(HistoricalFS!I23,0) -> 0.34006606 | J18: =IFERROR(HistoricalFS!J23,0) -> 0.36244517 | ... L18: =IFERROR(HistoricalFS!L23,0) -> 0.34304706 | N18: =IFERROR(AVERAGE(C18:L18),0) -> 0.36506416 | O18: =IFERROR(MEDIAN(C18:L18),0) -> 0.36661056
B19: EBIT Margin | C19: =IFERROR(HistoricalFS!C32,0) -> 0.34328576 | D19: =IFERROR(HistoricalFS!D32,0) -> 0.33475622 | E19: =IFERROR(HistoricalFS!E32,0) -> 0.35177636 | F19: =IFERROR(HistoricalFS!F32,0) -> 0.354591 | G19: =IFERROR(HistoricalFS!G32,0) -> 0.35836109 | H19: =IFERROR(HistoricalFS!H32,0) -> 0.31303265 | I19: =IFERROR(HistoricalFS!I32,0) -> 0.31149944 | J19: =IFERROR(HistoricalFS!J32,0) -> 0.33693707 | ... L19: =IFERROR(HistoricalFS!L32,0) -> 0.32119035 | N19: =IFERROR(AVERAGE(C19:L19),0) -> 0.33738593 | O19: =IFERROR(MEDIAN(C19:L19),0) -> 0.34011142
B20: EBT Margin | C20: =IFERROR(HistoricalFS!C35,0) -> 0.34129225 | D20: =IFERROR(HistoricalFS!D35,0) -> 0.33360979 | E20: =IFERROR(HistoricalFS!E35,0) -> 0.34912935 | F20: =IFERROR(HistoricalFS!F35,0) -> 0.35311395 | G20: =IFERROR(HistoricalFS!G35,0) -> 0.35671331 | H20: =IFERROR(HistoricalFS!H35,0) -> 0.31185577 | I20: =IFERROR(HistoricalFS!I35,0) -> 0.31051023 | J20: =IFERROR(HistoricalFS!J35,0) -> 0.33584046 | ... L20: =IFERROR(HistoricalFS!L35,0) -> 0.32059213 | N20: =IFERROR(AVERAGE(C20:L20),0) -> 0.33605108 | O20: =IFERROR(MEDIAN(C20:L20),0) -> 0.33856636
B21: Net Profit Margin | C21: =IFERROR(HistoricalFS!C41,0) -> 0.20457567 | D21: =IFERROR(HistoricalFS!D41,0) -> 0.20385993 | E21: =IFERROR(HistoricalFS!E41,0) -> 0.21295963 | F21: =IFERROR(HistoricalFS!F41,0) -> 0.222498 | G21: =IFERROR(HistoricalFS!G41,0) -> 0.26677614 | H21: =IFERROR(HistoricalFS!H41,0) -> 0.21937656 | I21: =IFERROR(HistoricalFS!I41,0) -> 0.22414895 | J21: =IFERROR(HistoricalFS!J41,0) -> 0.24505524 | ... L21: =IFERROR(HistoricalFS!L41,0) -> 0.22911358 | N21: =IFERROR(AVERAGE(C21:L21),0) -> 0.22848102 | O21: =IFERROR(MEDIAN(C21:L21),0) -> 0.22332348
B23: Sales Expenses % of sales | C23: =IFERROR(HistoricalFS!C20,0) -> 0.14027495 | D23: =IFERROR(HistoricalFS!D20,0) -> 0.12507061 | E23: =IFERROR(HistoricalFS!E20,0) -> 0.11417655 | F23: =IFERROR(HistoricalFS!F20,0) -> 0.11556244 | G23: =IFERROR(HistoricalFS!G20,0) -> 0.11569196 | H23: =IFERROR(HistoricalFS!H20,0) -> 0.1078245 | I23: =IFERROR(HistoricalFS!I20,0) -> 0.09841496 | J23: =IFERROR(HistoricalFS!J20,0) -> 0.097472286 | ... L23: =IFERROR(HistoricalFS!L20,0) -> 0.10640367 | N23: =IFERROR(AVERAGE(C23:L23),0) -> 0.11250906 | O23: =IFERROR(MEDIAN(C23:L23),0) -> 0.11100053
B24: Depriciation % of sales | C24: =IFERROR(HistoricalFS!C29,0) -> 0.027490234 | D24: =IFERROR(HistoricalFS!D29,0) -> 0.026954751 | E24: =IFERROR(HistoricalFS!E29,0) -> 0.028453629 | F24: =IFERROR(HistoricalFS!F29,0) -> 0.028891645 | G24: =IFERROR(HistoricalFS!G29,0) -> 0.033306066 | H24: =IFERROR(HistoricalFS!H29,0) -> 0.033407941 | I24: =IFERROR(HistoricalFS!I29,0) -> 0.028566628 | J24: =IFERROR(HistoricalFS!J29,0) -> 0.025508104 | ... L24: =IFERROR(HistoricalFS!L29,0) -> 0.021856705 | N24: =IFERROR(AVERAGE(C24:L24),0) -> 0.027678233 | O24: =IFERROR(MEDIAN(C24:L24),0) -> 0.027971931
B25: Operating Income % of sales | C25: =C19 -> 0.34328576 | D25: =D19 -> 0.33475622 | E25: =E19 -> 0.35177636 | F25: =F19 -> 0.354591 | G25: =G19 -> 0.35836109 | H25: =H19 -> 0.31303265 | I25: =I19 -> 0.31149944 | J25: =J19 -> 0.33693707 | ... L25: =L19 -> 0.32119035 | N25: =IFERROR(AVERAGE(C25:L25),0) -> 0.33738593 | O25: =IFERROR(MEDIAN(C25:L25),0) -> 0.34011142
B27: Return on Capital Employed (%) | C27: =IFERROR(HistoricalFS!C31/SUM(HistoricalFS!C54:C56),0) -> 0.31461767 | D27: =IFERROR(HistoricalFS!D31/SUM(HistoricalFS!D54:D56),0) -> 0.30816048 | E27: =IFERROR(HistoricalFS!E31/SUM(HistoricalFS!E54:E56),0) -> 0.29087469 | F27: =IFERROR(HistoricalFS!F31/SUM(HistoricalFS!F54:F56),0) -> 0.28976384 | G27: =IFERROR(HistoricalFS!G31/SUM(HistoricalFS!G54:G56),0) -> 0.26999906 | H27: =IFERROR(HistoricalFS!H31/SUM(HistoricalFS!H54:H56),0) -> 0.25436581 | I27: =IFERROR(HistoricalFS!I31/SUM(HistoricalFS!I54:I56),0) -> 0.30126365 | J27: =IFERROR(HistoricalFS!J31/SUM(HistoricalFS!J54:J56),0) -> 0.3440081 | ... L27: =IFERROR(HistoricalFS!L31/SUM(HistoricalFS!L54:L56),0) -> 0.34406984 | N27: =IFERROR(AVERAGE(C27:L27),0) -> 0.30335159 | O27: =IFERROR(MEDIAN(C27:L27),0) -> 0.30471206
B28: Retained Earnings (%) | C28: =IFERROR(HistoricalFS!C51,0) -> 0.14687786 | D28: =IFERROR(HistoricalFS!D51,0) -> 0.33819421 | E28: =IFERROR(HistoricalFS!E51,0) -> 0.3207286 | F28: =IFERROR(HistoricalFS!F51,0) -> 0.34463984 | G28: =IFERROR(HistoricalFS!G51,0) -> 0.053044068 | H28: =IFERROR(HistoricalFS!H51,0) -> 0 | I28: =IFERROR(HistoricalFS!I51,0) -> 0 | J28: =IFERROR(HistoricalFS!J51,0) -> 0 | ... L28: =IFERROR(HistoricalFS!L51,0) -> 0 | N28: =IFERROR(AVERAGE(C28:L28),0) -> 0.12180906 | O28: =IFERROR(MEDIAN(C28:L28),0) -> 0.03382504
B29: Return on Equity (%) | C29: =IFERROR(HistoricalFS!C40/SUM(HistoricalFS!C54:C55),0) -> 0.18785942 | D29: =IFERROR(HistoricalFS!D40/SUM(HistoricalFS!D54:D55),0) -> 0.18784852 | E29: =IFERROR(HistoricalFS!E40/SUM(HistoricalFS!E54:E55),0) -> 0.17621121 | F29: =IFERROR(HistoricalFS!F40/SUM(HistoricalFS!F54:F55),0) -> 0.18186171 | G29: =IFERROR(HistoricalFS!G40/SUM(HistoricalFS!G54:G55),0) -> 0.2018508 | H29: =IFERROR(HistoricalFS!H40/SUM(HistoricalFS!H54:H55),0) -> 0.17906224 | I29: =IFERROR(HistoricalFS!I40/SUM(HistoricalFS!I54:I55),0) -> 0.21764928 | J29: =IFERROR(HistoricalFS!J40/SUM(HistoricalFS!J54:J55),0) -> 0.25130525 | ... L29: =IFERROR(HistoricalFS!L40/SUM(HistoricalFS!L54:L55),0) -> 0.24643135 | N29: =IFERROR(AVERAGE(C29:L29),0) -> 0.20638955 | O29: =IFERROR(MEDIAN(C29:L29),0) -> 0.19485511
B30: Self Sustained Growth Rate (%) | C30: =IFERROR(C28*C29,0) -> 0.027592391 | D30: =IFERROR(D28*D29,0) -> 0.063529279 | E30: =IFERROR(E28*E29,0) -> 0.056515974 | F30: =IFERROR(F28*F29,0) -> 0.062676792 | G30: =IFERROR(G28*G29,0) -> 0.010706988 | H30: =IFERROR(H28*H29,0) -> 0 | I30: =IFERROR(I28*I29,0) -> 0 | J30: =IFERROR(J28*J29,0) -> 0 | ... L30: =IFERROR(L28*L29,0) -> 0 | N30: =IFERROR(AVERAGE(C30:L30),0) -> 0.022443654 | O30: =IFERROR(MEDIAN(C30:L30),0) -> 0.0070610516
B31: Interest Coverage Ratio | C31: =IFERROR(HistoricalFS!C31/HistoricalFS!C25,0) -> 172.20133 | D31: =IFERROR(HistoricalFS!D31/HistoricalFS!D25,0) -> 291.99918 | E31: =IFERROR(HistoricalFS!E31/HistoricalFS!E25,0) -> 132.89549 | F31: =IFERROR(HistoricalFS!F31/HistoricalFS!F25,0) -> 240.06695 | G31: =IFERROR(HistoricalFS!G31/HistoricalFS!G25,0) -> 217.48132 | H31: =IFERROR(HistoricalFS!H31/HistoricalFS!H25,0) -> 265.98568 | I31: =IFERROR(HistoricalFS!I31/HistoricalFS!I25,0) -> 314.89815 | J31: =IFERROR(HistoricalFS!J31/HistoricalFS!J25,0) -> 307.25537 | ... L31: =IFERROR(HistoricalFS!L31/HistoricalFS!L25,0) -> 536.90923 | N31: =IFERROR(AVERAGE(C31:L31),0) -> 308.48955 | O31: =IFERROR(MEDIAN(C31:L31),0) -> 278.99243
B33: Debtor Turnover Ratio | C33: =IFERROR(HistoricalFS!C10/HistoricalFS!C66,0) -> 20.442577 | D33: =IFERROR(HistoricalFS!D10/HistoricalFS!D66,0) -> 17.284797 | E33: =IFERROR(HistoricalFS!E10/HistoricalFS!E66,0) -> 16.19845 | F33: =IFERROR(HistoricalFS!F10/HistoricalFS!F66,0) -> 11.979238 | G33: =IFERROR(HistoricalFS!G10/HistoricalFS!G66,0) -> 19.273399 | H33: =IFERROR(HistoricalFS!H10/HistoricalFS!H66,0) -> 19.689591 | I33: =IFERROR(HistoricalFS!I10/HistoricalFS!I66,0) -> 24.633226 | J33: =IFERROR(HistoricalFS!J10/HistoricalFS!J66,0) -> 23.990173 | ... L33: =IFERROR(HistoricalFS!L10/HistoricalFS!L66,0) -> 15.959451 | N33: =IFERROR(AVERAGE(C33:L33),0) -> 18.632497 | O33: =IFERROR(MEDIAN(C33:L33),0) -> 18.279098
B34: Creditor Turnover Ratio | C34: =IFERROR(HistoricalFS!C10/HistoricalFS!C57,0) -> 4.4095324 | D34: =IFERROR(HistoricalFS!D10/HistoricalFS!D57,0) -> 4.5306245 | E34: =IFERROR(HistoricalFS!E10/HistoricalFS!E57,0) -> 3.7152199 | F34: =IFERROR(HistoricalFS!F10/HistoricalFS!F57,0) -> 3.8411297 | G34: =IFERROR(HistoricalFS!G10/HistoricalFS!G57,0) -> 4.1996201 | H34: =IFERROR(HistoricalFS!H10/HistoricalFS!H57,0) -> 3.7479256 | I34: =IFERROR(HistoricalFS!I10/HistoricalFS!I57,0) -> 4.1849768 | J34: =IFERROR(HistoricalFS!J10/HistoricalFS!J57,0) -> 4.3323459 | ... L34: =IFERROR(HistoricalFS!L10/HistoricalFS!L57,0) -> 4.2584165 | N34: =IFERROR(AVERAGE(C34:L34),0) -> 4.1229104 | O34: =IFERROR(MEDIAN(C34:L34),0) -> 4.1922984
B35: Inventory Turnover | C35: =IFERROR(HistoricalFS!C10/HistoricalFS!C67,0) -> 4.3248364 | D35: =IFERROR(HistoricalFS!D10/HistoricalFS!D67,0) -> 5.2694767 | E35: =IFERROR(HistoricalFS!E10/HistoricalFS!E67,0) -> 5.7969871 | F35: =IFERROR(HistoricalFS!F10/HistoricalFS!F67,0) -> 6.1504181 | G35: =IFERROR(HistoricalFS!G10/HistoricalFS!G67,0) -> 5.5620976 | H35: =IFERROR(HistoricalFS!H10/HistoricalFS!H67,0) -> 4.737587 | I35: =IFERROR(HistoricalFS!I10/HistoricalFS!I67,0) -> 5.5820787 | J35: =IFERROR(HistoricalFS!J10/HistoricalFS!J67,0) -> 6.0248123 | ... L35: =IFERROR(HistoricalFS!L10/HistoricalFS!L67,0) -> 4.8168218 | N35: =IFERROR(AVERAGE(C35:L35),0) -> 5.3064983 | O35: =IFERROR(MEDIAN(C35:L35),0) -> 5.4157872
B36: Fixed Asset Turnover | C36: =IFERROR(HistoricalFS!C10/HistoricalFS!C60,0) -> 2.5943642 | D36: =IFERROR(HistoricalFS!D10/HistoricalFS!D60,0) -> 2.6908896 | E36: =IFERROR(HistoricalFS!E10/HistoricalFS!E60,0) -> 2.6294508 | F36: =IFERROR(HistoricalFS!F10/HistoricalFS!F60,0) -> 2.4950504 | G36: =IFERROR(HistoricalFS!G10/HistoricalFS!G60,0) -> 2.2745326 | H36: =IFERROR(HistoricalFS!H10/HistoricalFS!H60,0) -> 2.1141916 | I36: =IFERROR(HistoricalFS!I10/HistoricalFS!I60,0) -> 2.5027058 | J36: =IFERROR(HistoricalFS!J10/HistoricalFS!J60,0) -> 2.743348 | ... L36: =IFERROR(HistoricalFS!L10/HistoricalFS!L60,0) -> 3.4308292 | N36: =IFERROR(AVERAGE(C36:L36),0) -> 2.5917181 | O36: =IFERROR(MEDIAN(C36:L36),0) -> 2.548535
B37: Capital Turnover Ratio | C37: =IFERROR(HistoricalFS!C10/SUM(HistoricalFS!C54:C55),0) -> 0.91828821 | D37: =IFERROR(HistoricalFS!D10/SUM(HistoricalFS!D54:D55),0) -> 0.92145874 | E37: =IFERROR(HistoricalFS!E10/SUM(HistoricalFS!E54:E55),0) -> 0.82743952 | F37: =IFERROR(HistoricalFS!F10/SUM(HistoricalFS!F54:F55),0) -> 0.81736336 | G37: =IFERROR(HistoricalFS!G10/SUM(HistoricalFS!G54:G55),0) -> 0.7566299 | H37: =IFERROR(HistoricalFS!H10/SUM(HistoricalFS!H54:H55),0) -> 0.81623233 | I37: =IFERROR(HistoricalFS!I10/SUM(HistoricalFS!I54:I55),0) -> 0.97100291 | J37: =IFERROR(HistoricalFS!J10/SUM(HistoricalFS!J54:J55),0) -> 1.0255045 | ... L37: =IFERROR(HistoricalFS!L10/SUM(HistoricalFS!L54:L55),0) -> 1.075586 | N37: =IFERROR(AVERAGE(C37:L37),0) -> 0.90412579 | O37: =IFERROR(MEDIAN(C37:L37),0) -> 0.91502033
B39: Debtor Days | C39: =IFERROR(365/C33,0) -> 17.854892 | D39: =IFERROR(365/D33,0) -> 21.116823 | E39: =IFERROR(365/E33,0) -> 22.53302 | F39: =IFERROR(365/F33,0) -> 30.469383 | G39: =IFERROR(365/G33,0) -> 18.938019 | H39: =IFERROR(365/H33,0) -> 18.537714 | I39: =IFERROR(365/I33,0) -> 14.817385 | J39: =IFERROR(365/J33,0) -> 15.214563 | ... L39: =IFERROR(365/L33,0) -> 22.870462 | N39: =IFERROR(AVERAGE(C39:L39),0) -> 20.398309 | O39: =IFERROR(MEDIAN(C39:L39),0) -> 20.027421
B40: Payable Days | C40: =IFERROR(365/C34,0) -> 82.775217 | D40: =IFERROR(365/D34,0) -> 80.562845 | E40: =IFERROR(365/E34,0) -> 98.24452 | F40: =IFERROR(365/F34,0) -> 95.024128 | G40: =IFERROR(365/G34,0) -> 86.912624 | H40: =IFERROR(365/H34,0) -> 97.387204 | I40: =IFERROR(365/I34,0) -> 87.216733 | J40: =IFERROR(365/J34,0) -> 84.249966 | ... L40: =IFERROR(365/L34,0) -> 85.712611 | N40: =IFERROR(AVERAGE(C40:L40),0) -> 88.912391 | O40: =IFERROR(MEDIAN(C40:L40),0) -> 87.064678
B41: Inventory Days | C41: =IFERROR(365/C35,0) -> 84.396256 | D41: =IFERROR(365/D35,0) -> 69.26684 | E41: =IFERROR(365/E35,0) -> 62.963742 | F41: =IFERROR(365/F35,0) -> 59.345559 | G41: =IFERROR(365/G35,0) -> 65.622725 | H41: =IFERROR(365/H35,0) -> 77.04344 | I41: =IFERROR(365/I35,0) -> 65.387828 | J41: =IFERROR(365/J35,0) -> 60.5828 | ... L41: =IFERROR(365/L35,0) -> 75.776106 | N41: =IFERROR(AVERAGE(C41:L41),0) -> 69.642907 | O41: =IFERROR(MEDIAN(C41:L41),0) -> 67.444782
B42: Cash Conversion Cycle (in days) | C42: =IFERROR(SUM(C39,C41)-C40,0) -> 19.47593 | D42: =IFERROR(SUM(D39,D41)-D40,0) -> 9.8208176 | E42: =IFERROR(SUM(E39,E41)-E40,0) -> -12.747757 | F42: =IFERROR(SUM(F39,F41)-F40,0) -> -5.2091857 | G42: =IFERROR(SUM(G39,G41)-G40,0) -> -2.3518801 | H42: =IFERROR(SUM(H39,H41)-H40,0) -> -1.8060507 | I42: =IFERROR(SUM(I39,I41)-I40,0) -> -7.0115199 | J42: =IFERROR(SUM(J39,J41)-J40,0) -> -8.4526036 | ... L42: =IFERROR(SUM(L39,L41)-L40,0) -> 12.933956 | N42: =IFERROR(AVERAGE(C42:L42),0) -> 1.1288252 | O42: =IFERROR(MEDIAN(C42:L42),0) -> -2.0789654
B44: CFO/Sales | C44: =IFERROR(HistoricalFS!C77/HistoricalFS!C10,0) -> 0.2500259 | D44: =IFERROR(HistoricalFS!D77/HistoricalFS!D10,0) -> 0.24848974 | E44: =IFERROR(HistoricalFS!E77/HistoricalFS!E10,0) -> 0.3031006 | F44: =IFERROR(HistoricalFS!F77/HistoricalFS!F10,0) -> 0.26031277 | G44: =IFERROR(HistoricalFS!G77/HistoricalFS!G10,0) -> 0.2974356 | H44: =IFERROR(HistoricalFS!H77/HistoricalFS!H10,0) -> 0.25431625 | I44: =IFERROR(HistoricalFS!I77/HistoricalFS!I10,0) -> 0.26013076 | J44: =IFERROR(HistoricalFS!J77/HistoricalFS!J10,0) -> 0.26618455 | ... L44: =IFERROR(HistoricalFS!L77/HistoricalFS!L10,0) -> 0.2340183 | N44: =IFERROR(AVERAGE(C44:L44),0) -> 0.26268979 | O44: =IFERROR(MEDIAN(C44:L44),0) -> 0.2572235
B45: CFO/Total Assets | C45: =IFERROR(HistoricalFS!C77/HistoricalFS!C71,0) -> 0.18971512 | D45: =IFERROR(HistoricalFS!D77/HistoricalFS!D71,0) -> 0.19011859 | E45: =IFERROR(HistoricalFS!E77/HistoricalFS!E71,0) -> 0.20500031 | F45: =IFERROR(HistoricalFS!F77/HistoricalFS!F71,0) -> 0.17540533 | G45: =IFERROR(HistoricalFS!G77/HistoricalFS!G71,0) -> 0.19000799 | H45: =IFERROR(HistoricalFS!H77/HistoricalFS!H71,0) -> 0.16983244 | I45: =IFERROR(HistoricalFS!I77/HistoricalFS!I71,0) -> 0.20435652 | J45: =IFERROR(HistoricalFS!J77/HistoricalFS!J71,0) -> 0.2199387 | ... L45: =IFERROR(HistoricalFS!L77/HistoricalFS!L71,0) -> 0.20030113 | N45: =IFERROR(AVERAGE(C45:L45),0) -> 0.19319036 | O45: =IFERROR(MEDIAN(C45:L45),0) -> 0.19006329
B46: CFO/Total Debt | C46: =IFERROR(HistoricalFS!C77/HistoricalFS!C56,0) -> 116.96157 | D46: =IFERROR(HistoricalFS!D77/HistoricalFS!D56,0) -> 232.44335 | E46: =IFERROR(HistoricalFS!E77/HistoricalFS!E56,0) -> 366.6314 | F46: =IFERROR(HistoricalFS!F77/HistoricalFS!F56,0) -> 936.26562 | G46: =IFERROR(HistoricalFS!G77/HistoricalFS!G56,0) -> 52.945251 | H46: =IFERROR(HistoricalFS!H77/HistoricalFS!H56,0) -> 46.253997 | I46: =IFERROR(HistoricalFS!I77/HistoricalFS!I56,0) -> 63.243706 | J46: =IFERROR(HistoricalFS!J77/HistoricalFS!J56,0) -> 61.683277 | ... L46: =IFERROR(HistoricalFS!L77/HistoricalFS!L56,0) -> 61.949251 | N46: =IFERROR(AVERAGE(C46:L46),0) -> 199.4993 | O46: =IFERROR(MEDIAN(C46:L46),0) -> 62.596479

Sheet WACC
B2: ='Data Sheet'!B1 -> ITC LTD
B3: (ITC | BSE Code: 540376)
B4: =CONCATENATE("INR"," ", 'Data Sheet'!B8) -> INR 409.75
B5: 52 Week (High - INR 410.45 & Low - INR 401.90)
B6: Weighted Average Cost of Capital
B7: Peers comms
I8: Debt / | J8: Debt / | K8: Levered 2 | L8: Unlevered 3
B9: Name of the comp | C9: Ticker | E9: Country | F9: Total Debt | G9: Total Equity | H9: Tax rate 1 | I9: Equity | J9: Capital | K9: Beta | L9: Beta
B11: ='Comps Data'!C4 -> Hind. Unilever | C11: ='Comps Data'!D4 -> HINDUNILVR | E11: India | F11: ='Comps Data'!H4 -> 1648 | G11: ='Comps Data'!G4 -> 624946.61 | H11: 0.3 | I11: =F11/G11 -> 0.0026370253 | J11: =F11/SUM(G11,F11) -> 0.0026300897 | K11: 0.448 | L11: =K11/(1+(1-H11)*I11) -> 0.44717455
B12: ='Comps Data'!C3 -> ITC | C12: ='Comps Data'!D3 -> ITC | E12: India | F12: ='Comps Data'!H3 -> 284.54 | G12: ='Comps Data'!G3 -> 513281.53 | H12: 0.3 | I12: =F12/G12 -> 0.00055435464 | J12: =F12/SUM(G12,F12) -> 0.0005540475 | K12: 0.566 | L12: =K12/(1+(1-H12)*I12) -> 0.56578045
B13: ='Comps Data'!C5 -> Nestle India | C13: ='Comps Data'!D5 -> NESTLEIND | E13: India | F13: ='Comps Data'!H5 -> 1166.85 | G13: ='Comps Data'!G5 -> 222950.05 | H13: 0.3 | I13: =F13/G13 -> 0.0052336836 | J13: =F13/SUM(G13,F13) -> 0.0052064348 | K13: 0.702 | L13: =K13/(1+(1-H13)*I13) -> 0.69943756
B14: ='Comps Data'!C6 -> Varun Beverages | C14: ='Comps Data'!D6 -> VBL | E14: India | F14: ='Comps Data'!H6 -> 2138.25 | G14: ='Comps Data'!G6 -> 164754.13 | H14: 0.3 | I14: =F14/G14 -> 0.01297843 | J14: =F14/SUM(G14,F14) -> 0.012812149 | K14: 0.911 | L14: =K14/(1+(1-H14)*I14) -> 0.90279817
B15: ='Comps Data'!C7 -> Britannia Inds. | C15: ='Comps Data'!D7 -> BRITANNIA | E15: India | F15: ='Comps Data'!H7 -> 1246.51 | G15: ='Comps Data'!G7 -> 140300.16 | H15: 0.3 | I15: =F15/G15 -> 0.0088845943 | J15: =F15/SUM(G15,F15) -> 0.0088063534 | K15: 0.528 | L15: =K15/(1+(1-H15)*I15) -> 0.52473655
G17: Average | H17: =AVERAGE(H11:H15) -> 0.3 | I17: =AVERAGE(I11:I15) -> 0.0060576176 | J17: =AVERAGE(J11:J15) -> 0.0060018148 | K17: =AVERAGE(K11:K15) -> 0.631 | L17: =AVERAGE(L11:L15) -> 0.62798546
G18: Median | H18: =MEDIAN(H11:H15) -> 0.3 | I18: =MEDIAN(I11:I15) -> 0.0052336836 | J18: =MEDIAN(J11:J15) -> 0.0052064348 | K18: =MEDIAN(K11:K15) -> 0.566 | L18: =MEDIAN(L11:L15) -> 0.56578045
B20: Cost of Debt | H20: Cost of Equity
B22: Interest | F22: 216 | H22: Risk Free Rate | L22: 0.06402
B23: Pre-Tax Cost of Debt | F23: =F22/F11 -> 0.13106796 | H23: Market Risk Premium | L23: 0.06
B24: Tax Rate | F24: =H14 -> 0.3 | H24: Levered Beta 4 | L24: =L32 -> 0.56786414
B25: Post Tax Cost of Debt | F25: =F23*(1-F24) -> 0.091747573 | H25: Cost of Equity | L25: =L22+L23*L24 -> 0.098091848
B27: Capital Structure | H27: Levered Beta
E29: Current | F29: Target | H29: Comps Median Unlevered Beta | L29: =L18 -> 0.56578045
B30: Total Debt | D30: =F11 -> 1648 | E30: =D30/$D$32 -> 0.0026300897 | F30: =I18 -> 0.0052336836 | H30: Target Debt / Equity | L30: =F34 -> 0.0052612192
B31: Market Capitalization | D31: =G11 -> 624946.61 | E31: =D31/$D$32 -> 0.99736991 | F31: =F32-F30 -> 0.99476632 | H31: Tax Rate | L31: =F24 -> 0.3
B32: Total Capital | D32: =SUM(D30:D31) -> 626594.61 | E32: =D32/$D$32 -> 1 | F32: =E32 -> 1 | H32: Levered Beta | L32: =L29*(1+(1-L31)*L30) -> 0.56786414
B34: Debt / Equity | E34: =E30/E31 -> 0.0026370253 | F34: =F30/F31 -> 0.0052612192
H35: Weighted Average Cost of Capital
B36: Notes:
B37: 1. Tax Rate is Considered Marginal Tax Rate for the country | K37: Total Cost | L37: Total Weight
B38: 2. Levered Beta is based on 2 years weekly data | H38: Debt | K38: =F25 -> 0.091747573 | L38: =F30 -> 0.0052336836
B39: 3. Unlevered Beta = Levered Beta/(1+(1-Tax Rate)*Debt/Equity | H39: Equity | K39: =L25 -> 0.098091848 | L39: =F31 -> 0.99476632
B40: 3. Levered Beta = Unlevered Beta*(1+(1-Tax Rate)*Debt/Equity | H40: Weighted Average Cost Of Capital | L40: =SUMPRODUCT(K38:K39,L38:L39) -> 0.098058644

Sheet Intrinsic Growth
B2: ='Data Sheet'!B1 -> ITC LTD
B3: (ITC | BSE Code: 540376)
B4: =CONCATENATE("INR"," ", 'Data Sheet'!B8) -> INR 409.75
B5: 52 Week (High - INR 410.45 & Low - INR 401.90)
B7: Calculation of Intrinsic Growth Rate | D7: ='Raw Bs'!G2 -> 43891 | E7: ='Raw Bs'!H2 -> 44256 | F7: ='Raw Bs'!I2 -> 44621 | G7: ='Raw Bs'!J2 -> 44986 | H7: ='Raw Bs'!K2 -> 45352 | I7: ='Raw Bs'!L2 -> 45717
B9: Current Assets
B10: ='Raw Bs'!B36 -> Inventories | D10: ='Raw Bs'!G36 -> 8879 | E10: ='Raw Bs'!H36 -> 10397 | F10: ='Raw Bs'!I36 -> 10864 | G10: ='Raw Bs'!J36 -> 11771 | H10: ='Raw Bs'!K36 -> 14153 | I10: ='Raw Bs'!L36 -> 15638
B11: ='Raw Bs'!B37 -> Trade receivables | D11: ='Raw Bs'!G37 -> 2562 | E11: ='Raw Bs'!H37 -> 2502 | F11: ='Raw Bs'!I37 -> 2462 | G11: ='Raw Bs'!J37 -> 2956 | H11: ='Raw Bs'!K37 -> 4026 | I11: ='Raw Bs'!L37 -> 4720
B12: ='Raw Bs'!B39 -> Loans n Advances | D12: ='Raw Bs'!G39 -> 6 | E12: ='Raw Bs'!H39 -> 7 | F12: ='Raw Bs'!I39 -> 11 | G12: ='Raw Bs'!J39 -> 13 | H12: ='Raw Bs'!K39 -> 31 | I12: ='Raw Bs'!L39 -> 10
B13: ='Raw Bs'!B40 -> Other asset items | D13: ='Raw Bs'!G40 -> 4952 | E13: ='Raw Bs'!H40 -> 4015 | F13: ='Raw Bs'!I40 -> 6906 | G13: ='Raw Bs'!J40 -> 7941 | H13: ='Raw Bs'!K40 -> 4531 | I13: ='Raw Bs'!L40 -> 5858
B14: Total Current Assets | D14: =SUM(D10:D13) -> 16399 | E14: =SUM(E10:E13) -> 16921 | F14: =SUM(F10:F13) -> 20243 | G14: =SUM(G10:G13) -> 22681 | H14: =SUM(H10:H13) -> 22741 | I14: =SUM(I10:I13) -> 26226
B16: Current Liabilities
B17: ='Raw Bs'!B13 -> Trade Payables | D17: ='Raw Bs'!G13 -> 3630 | E17: ='Raw Bs'!H13 -> 4319 | F17: ='Raw Bs'!I13 -> 4417 | G17: ='Raw Bs'!J13 -> 4659 | H17: ='Raw Bs'!K13 -> 4798 | I17: ='Raw Bs'!L13 -> 4807
B18: ='Raw Bs'!B14 -> Advance from Customers | D18: ='Raw Bs'!G14 -> 703 | E18: ='Raw Bs'!H14 -> 811 | F18: ='Raw Bs'!I14 -> 1278 | G18: ='Raw Bs'!J14 -> 1295 | H18: ='Raw Bs'!K14 -> 886 | I18: ='Raw Bs'!L14 -> 1264
B19: ='Raw Bs'!B15 -> Other liability items | D19: ='Raw Bs'!G15 -> 7050 | E19: ='Raw Bs'!H15 -> 7666 | F19: ='Raw Bs'!I15 -> 8429 | G19: ='Raw Bs'!J15 -> 10032 | H19: ='Raw Bs'!K15 -> 10877 | I19: ='Raw Bs'!L15 -> 11249
B20: Total Current Liabilities | D20: =SUM(D17:D19) -> 11383 | E20: =SUM(E17:E19) -> 12796 | F20: =SUM(F17:F19) -> 14124 | G20: =SUM(G17:G19) -> 15986 | H20: =SUM(H17:H19) -> 16561 | I20: =SUM(I17:I19) -> 17320
B22: Net Working Capital | D22: =D14-D20 -> 5016 | E22: =E14-E20 -> 4125 | F22: =F14-F20 -> 6119 | G22: =G14-G20 -> 6695 | H22: =H14-H20 -> 6180 | I22: =I14-I20 -> 8906
B24: Non- Current Assets
B25: ='Raw Bs'!B19 -> Land | D25: ='Raw Bs'!G19 -> 2797 | E25: ='Raw Bs'!H19 -> 2889 | F25: ='Raw Bs'!I19 -> 2829 | G25: ='Raw Bs'!J19 -> 2830 | H25: ='Raw Bs'!K19 -> 2865 | I25: ='Raw Bs'!L19 -> 1588
B26: ='Raw Bs'!B20 -> Building | D26: ='Raw Bs'!G20 -> 8161 | E26: ='Raw Bs'!H20 -> 8387 | F26: ='Raw Bs'!I20 -> 9100 | G26: ='Raw Bs'!J20 -> 9789 | H26: ='Raw Bs'!K20 -> 10944 | I26: ='Raw Bs'!L20 -> 7550
B27: ='Raw Bs'!B21 -> Plant Machinery | D27: ='Raw Bs'!G21 -> 14625 | E27: ='Raw Bs'!H21 -> 15307 | F27: ='Raw Bs'!I21 -> 16912 | G27: ='Raw Bs'!J21 -> 18480 | H27: ='Raw Bs'!K21 -> 20718 | I27: ='Raw Bs'!L21 -> 19423
B28: ='Raw Bs'!B22 -> Equipments | D28: ='Raw Bs'!G22 -> 40 | E28: ='Raw Bs'!H22 -> 41 | F28: ='Raw Bs'!I22 -> 44 | G28: ='Raw Bs'!J22 -> 44 | H28: ='Raw Bs'!K22 -> 53 | I28: ='Raw Bs'!L22 -> 63
B29: ='Raw Bs'!B23 -> Furniture n fittings | D29: ='Raw Bs'!G23 -> 810 | E29: ='Raw Bs'!H23 -> 833 | F29: ='Raw Bs'!I23 -> 907 | G29: ='Raw Bs'!J23 -> 1000 | H29: ='Raw Bs'!K23 -> 1068 | I29: ='Raw Bs'!L23 -> 282
B30: ='Raw Bs'!B24 -> Railway sidings | D30: ='Raw Bs'!G24 -> 2 | E30: ='Raw Bs'!H24 -> 2 | F30: ='Raw Bs'!I24 -> 2 | G30: ='Raw Bs'!J24 -> 2 | H30: ='Raw Bs'!K24 -> 2 | I30: ='Raw Bs'!L24 -> 2
B31: ='Raw Bs'!B25 -> Vehicles | D31: ='Raw Bs'!G25 -> 184 | E31: ='Raw Bs'!H25 -> 180 | F31: ='Raw Bs'!I25 -> 179 | G31: ='Raw Bs'!J25 -> 189 | H31: ='Raw Bs'!K25 -> 192 | I31: ='Raw Bs'!L25 -> 141
B32: ='Raw Bs'!B26 -> Intangible Assets | D32: ='Raw Bs'!G26 -> 684 | E32: ='Raw Bs'!H26 -> 2734 | F32: ='Raw Bs'!I26 -> 2744 | G32: ='Raw Bs'!J26 -> 3490 | H32: ='Raw Bs'!K26 -> 3505 | I32: ='Raw Bs'!L26 -> 3622
B33: ='Raw Bs'!B27 -> Other fixed assets | D33: ='Raw Bs'!G27 -> 663 | E33: ='Raw Bs'!H27 -> 716 | F33: ='Raw Bs'!I27 -> 719 | G33: ='Raw Bs'!J27 -> 786 | H33: ='Raw Bs'!K27 -> 841 | I33: ='Raw Bs'!L27 -> 967
B35: Gross Block | D35: =SUM(D25:D32) -> 27303 | E35: =SUM(E25:E32) -> 30373 | F35: =SUM(F25:F32) -> 32717 | G35: =SUM(G25:G32) -> 35824 | H35: =SUM(H25:H32) -> 39347 | I35: =SUM(I25:I32) -> 32671
B36: Accumulated Depreciation | D36: =-'Raw Bs'!G29 -> -6252 | E36: =-'Raw Bs'!H29 -> -7790 | F36: =-'Raw Bs'!I29 -> -9204 | G36: =-'Raw Bs'!J29 -> -10757 | H36: =-'Raw Bs'!K29 -> -12368 | I36: =-'Raw Bs'!L29 -> -11683
B38: Net Non- Current Assets | D38: =SUM(D35:D36) -> 21051 | E38: =SUM(E35:E36) -> 22583 | F38: =SUM(F35:F36) -> 23513 | G38: =SUM(G35:G36) -> 25067 | H38: =SUM(H35:H36) -> 26979 | I38: =SUM(I35:I36) -> 20988
B40: Invested Capital | D40: =D22+D38 -> 26067 | E40: =E22+E38 -> 26708 | F40: =F22+F38 -> 29632 | G40: =G22+G38 -> 31762 | H40: =H22+H38 -> 33159 | I40: =I22+I38 -> 29894
B41: EBIT | D41: =HistoricalFS!G31 -> 17698.63 | E41: =HistoricalFS!H31 -> 15419.19 | F41: =HistoricalFS!I31 -> 18890.74 | G41: =HistoricalFS!J31 -> 23895.25 | H41: =HistoricalFS!K31 -> 23669.48 | I41: =HistoricalFS!L31 -> 24193.13
B42: Marginal Tax Rate | D42: 0.3 | E42: 0.3 | F42: 0.3 | G42: 0.3 | H42: 0.3 | I42: 0.3
B43: NOPAT | D43: =D41*(1-D42) -> 12389.041 | E43: =E41*(1-E42) -> 10793.433 | F43: =F41*(1-F42) -> 13223.518 | G43: =G41*(1-G42) -> 16726.675 | H43: =H41*(1-H42) -> 16568.636 | I43: =I41*(1-I42) -> 16935.191
B45: ROIC | D45: =D43/D40 -> 0.47527683 | E45: =E43/E40 -> 0.40412734 | F45: =F43/F40 -> 0.44625803 | G45: =G43/G40 -> 0.52662537 | H45: =H43/H40 -> 0.49967237 | I45: =I43/I40 -> 0.56650803
B47: =B7 -> Calculation of Intrinsic Growth Rate | D47: =D7 -> 43891 | E47: =E7 -> 44256 | F47: =F7 -> 44621 | G47: =G7 -> 44986 | H47: =H7 -> 45352 | I47: =I7 -> 45717
B49: Net Capex | D49: =-'Raw CF'!I11+'Raw CF'!I12 -> 2468 | E49: =-'Raw CF'!J11+'Raw CF'!J12 -> 1840 | F49: =-'Raw CF'!K11+'Raw CF'!K12 -> 2275 | G49: =-'Raw CF'!L11+'Raw CF'!L12 -> 2792 | H49: =-'Raw CF'!M11+'Raw CF'!M12 -> 3670 | I49: =-'Raw CF'!N11+'Raw CF'!N12 -> 2454
B50: ΔW.C | D50: 0 | E50: =E22-D22 -> -891 | F50: =F22-E22 -> 1994 | G50: =G22-F22 -> 576 | H50: =H22-G22 -> -515 | I50: =I22-H22 -> 2726
B51: EBIT | D51: =D41 -> 17698.63 | E51: =E41 -> 15419.19 | F51: =F41 -> 18890.74 | G51: =G41 -> 23895.25 | H51: =H41 -> 23669.48 | I51: =I41 -> 24193.13
B52: Marginal Tax Rate | D52: 0.3 | E52: 0.3 | F52: 0.3 | G52: 0.3 | H52: 0.3 | I52: 0.3
B53: NOPAT | D53: =D51*(1-D52) -> 12389.041 | E53: =E51*(1-E52) -> 10793.433 | F53: =F51*(1-F52) -> 13223.518 | G53: =G51*(1-G52) -> 16726.675 | H53: =H51*(1-H52) -> 16568.636 | I53: =I51*(1-I52) -> 16935.191
B54: Reinvestment | D54: =D49+D50 -> 2468 | E54: =E49+E50 -> 949 | F54: =F49+F50 -> 4269 | G54: =G49+G50 -> 3368 | H54: =H49+H50 -> 3155 | I54: =I49+I50 -> 5180
B56: Reinvestment Rate | E56: =E54/E53 -> 0.087923833 | F56: =F54/F53 -> 0.32283391 | G56: =G54/G53 -> 0.20135502 | H56: =H54/H53 -> 0.19042002 | I56: =I54/I53 -> 0.30587196
H58: 4 Year Average | I58: =AVERAGE(E56:I56) -> 0.22168095
H59: 4 Year Median | I59: =MEDIAN(E56:I56) -> 0.20135502
B61: Calculation of Intrinsic Growth Rate | D61: =D47 -> 43891 | E61: =E47 -> 44256 | F61: =F47 -> 44621 | G61: =G47 -> 44986 | H61: =H47 -> 45352 | I61: =I47 -> 45717
B63: Reinvestment Rate | E63: =E56 -> 0.087923833 | F63: =F56 -> 0.32283391 | G63: =G56 -> 0.20135502 | H63: =H56 -> 0.19042002 | I63: =I56 -> 0.30587196
B64: ROIC | E64: =E45 -> 0.40412734 | F64: =F45 -> 0.44625803 | G64: =G45 -> 0.52662537 | H64: =H45 -> 0.49967237 | I64: =I45 -> 0.56650803
B66: Intrinsic Growth | E66: =E63*E64 -> 0.035532425 | F66: =F63*F64 -> 0.14406722 | G66: =G63*G64 -> 0.10603866 | H66: =H63*H64 -> 0.095147622 | I66: =I63*I64 -> 0.17327892
H68: 4 Year Average | I68: =AVERAGE(E66:I66) -> 0.11081297
H69: 4 Year Median | I69: =MEDIAN(E66:I66) -> 0.10603866

Sheet DCF
B2: ='Data Sheet'!B1 -> ITC LTD
B3: (ITC | BSE Code: 540376)
B4: =CONCATENATE("INR"," ", 'Data Sheet'!B8) -> INR 409.75
B5: 52 Week (High - INR 410.45 & Low - INR 401.90)
B7: Calculation of PV of FCFF | E7: ='Intrinsic Growth'!I47 -> 45717 | F7: =E7+366 -> 46083 | G7: =F7+366 -> 46449 | H7: =G7+366 -> 46815 | I7: =H7+366 -> 47181 | J7: =I7+366 -> 47547
B9: EBIT | E9: ='Intrinsic Growth'!D51 -> 17698.63 | F9: ='Intrinsic Growth'!E51 -> 15419.19 | G9: ='Intrinsic Growth'!F51 -> 18890.74 | H9: ='Intrinsic Growth'!G51 -> 23895.25 | I9: ='Intrinsic Growth'!H51 -> 23669.48 | J9: ='Intrinsic Growth'!I51 -> 24193.13
B10: Tax Rate | E10: ='Intrinsic Growth'!D52 -> 0.3 | F10: ='Intrinsic Growth'!E52 -> 0.3 | G10: ='Intrinsic Growth'!F52 -> 0.3 | H10: ='Intrinsic Growth'!G52 -> 0.3 | I10: ='Intrinsic Growth'!H52 -> 0.3 | J10: ='Intrinsic Growth'!I52 -> 0.3
B11: NOPAT | E11: =E9*(1-E10) -> 12389.041 | F11: =F9*(1-F10) -> 10793.433 | G11: =G9*(1-G10) -> 13223.518 | H11: =H9*(1-H10) -> 16726.675 | I11: =I9*(1-I10) -> 16568.636 | J11: =J9*(1-J10) -> 16935.191
B12: Less: Reinvestment Rate | E12: ='Intrinsic Growth'!$I$59 -> 0.20135502 | F12: ='Intrinsic Growth'!$I$59 -> 0.20135502 | G12: ='Intrinsic Growth'!$I$59 -> 0.20135502 | H12: ='Intrinsic Growth'!$I$59 -> 0.20135502 | I12: ='Intrinsic Growth'!$I$59 -> 0.20135502 | J12: ='Intrinsic Growth'!$I$59 -> 0.20135502
B13: Free Cash Flow to Firm (FCFF) | E13: =E11*(1-E12) -> 9894.4454 | F13: =F11*(1-F12) -> 8620.1211 | G13: =G11*(1-G12) -> 10560.896 | H13: =H11*(1-H12) -> 13358.675 | I13: =I11*(1-I12) -> 13232.458 | J13: =J11*(1-J12) -> 13525.205
B15: Mid Year Convention | F15: =IF(B15="Mid Year Convention",0.5,1) -> 0.5 | G15: =1+F15 -> 1.5 | H15: =1+G15 -> 2.5 | I15: =1+H15 -> 3.5 | J15: =1+I15 -> 4.5
B16: Discounting Factor | F16: =1/(1+$D$21)^F15 -> 0.95430507 | G16: =1/(1+$D$21)^G15 -> 0.86908389 | H16: =1/(1+$D$21)^H15 -> 0.79147311 | I16: =1/(1+$D$21)^I15 -> 0.72079311 | J16: =1/(1+$D$21)^J15 -> 0.65642497
B18: PV of FCFF | F18: =F13*F16 -> 8226.2253 | G18: =G13*G16 -> 9178.3047 | H18: =H13*H16 -> 10573.032 | I18: =I13*I16 -> 9537.8645 | J18: =J13*J16 -> 8878.2824
B20: Terminal Growth | D20: 0.05
B21: WACC | D21: =WACC!L40 -> 0.098058644
B23: Calculation of Terminal Value | F23: Sensitivity Analysis
B25: FCFF(n+1) | D25: =J13*(1+D20) -> 14201.466 | F25: Enterprise Value (in INR)
B26: WACC | D26: =WACC!L40 -> 0.098058644
B27: Terminal Growth | D27: =D20 -> 0.05 | G27: Terminal Growth Rate
F28: =D36 -> 178286.66 | G28: 0.03 | H28: 0.04 | I28: 0.05 | J28: 0.07
B29: Terminal Value | D29: =D25/D26-D27 -> 144826.2 | F29: 0.07 | G29: 182345.83 | H29: 183634.89 | I29: 184923.94 | J29: 187502.05
F30: 0.08 | G30: 179942.81 | H30: 181219.93 | I30: 182497.05 | J30: 185051.28
B31: Calculation of Implied Share Value | F31: 0.098058644 | G31: 175774.43 | H31: 177030.55 | I31: 178286.66 | J31: 180798.89
F32: 0.11 | G32: 173132.3 | H32: 174374.9 | I32: 175617.5 | J32: 178102.7
B33: Sum PV of FCFF | D33: =SUM(F18:J18) -> 46393.709 | F33: 0.13 | G33: 168896.88 | H33: 170117.49 | I33: 171338.1 | J33: 173779.31
B34: PV of T.V | D34: =NPV(D21,D29) -> 131892.95
B36: Enterprise Value | D36: =SUM(D33:D34) -> 178286.66 | F36: Implied Share Value (in INR)
B37: Add: Cash | D37: ='Data Sheet'!K69 -> 4012.36
B38: Less: Debt | D38: ='Data Sheet'!K59 -> 284.54 | G38: Terminal Growth Rate
B39: Equity Value | D39: =D36+D37-D38 -> 182014.48 | F39: =D42 -> 145.30165 | G39: 0.03 | H39: 0.04 | I39: 0.05 | J39: 0.07
B40: Total Shares | D40: ='Data Sheet'!B6 -> 1252.6663 | F40: 0.07 | G40: 148.54208 | H40: 149.57113 | I40: 150.60018 | J40: 152.65827
F41: 0.08 | G41: 146.62375 | H41: 147.64327 | I41: 148.66279 | J41: 150.70183
B42: Implied Share Value | D42: =D39/D40 -> 145.30165 | F42: 0.098058644 | G42: 143.29615 | H42: 144.2989 | I42: 145.30165 | J42: 147.30716
B43: Share Price | D43: ='Data Sheet'!B8 -> 409.75 | F43: 0.11 | G43: 141.18694 | H43: 142.1789 | I43: 143.17087 | J43: 145.1548
B44: =IF(D42>D43,"Discount","Premium") -> Premium | D44: =D43/D42 -> 2.8199954 | F44: 0.13 | G44: 137.80582 | H44: 138.78022 | I44: 139.75463 | J44: 141.70345

Sheet Comps Val
B2: ='Data Sheet'!B1 -> ITC LTD
B3: (ITC | BSE Code: 540376)
B4: =CONCATENATE("INR"," ", 'Data Sheet'!B8) -> INR 409.75
B5: 52 Week (High - INR 410.45 & Low - INR 401.90)
B7: Comparable Company Valuation - Ambuja Cements | E7: (Amount in crores)
D9: Market Data | J9: Financials | N9: Valuation
B10: Company | C10: Ticker | D10: Share Price | E10: Share Outstanding | F10: Equity Value | G10: Net Debt | H10: Enterprise Value | J10: Revenue | K10: EBITDA | L10: Net Income | N10: EV / Revenue | O10: EV / EBITDA | P10: P/E
B12: ='Comps Data'!C3 -> ITC | C12: ='Comps Data'!D3 -> ITC | D12: ='Comps Data'!E3 -> 409.75 | E12: ='Comps Data'!F3 -> 1252.67 | F12: =E12*D12 -> 513281.53 | G12: ='Comps Data'!H3 -> 284.54 | H12: ='Comps Data'!J3 -> 509553.71 | J12: ='Comps Data'!K3 -> 79040.32 | K12: ='Comps Data'!L3 -> 43885.8 | L12: ='Comps Data'!M3 -> 35218.9 | N12: =$H12/J12 -> 6.4467567 | O12: =$H12/K12 -> 11.610902 | P12: =F12/L12 -> 14.574036
B13: ='Comps Data'!C4 -> Hind. Unilever | C13: ='Comps Data'!D4 -> HINDUNILVR | D13: ='Comps Data'!E4 -> 2659.8 | E13: ='Comps Data'!F4 -> 234.96 | F13: =E13*D13 -> 624946.61 | G13: ='Comps Data'!H4 -> 1648 | H13: ='Comps Data'!J4 -> 619040.61 | J13: ='Comps Data'!K4 -> 63928 | K13: ='Comps Data'!L4 -> 16005 | L13: ='Comps Data'!M4 -> 10827 | N13: =H13/J13 -> 9.6834033 | O13: =$H13/K13 -> 38.677951 | P13: =F13/L13 -> 57.721124
B14: ='Comps Data'!C5 -> Nestle India | C14: ='Comps Data'!D5 -> NESTLEIND | D14: ='Comps Data'!E5 -> 1156.2 | E14: ='Comps Data'!F5 -> 192.83 | F14: =E14*D14 -> 222950.05 | G14: ='Comps Data'!H5 -> 1166.85 | H14: ='Comps Data'!J5 -> 224021.25 | J14: ='Comps Data'!K5 -> 20483.77 | K14: ='Comps Data'!L5 -> 5074.24 | L14: ='Comps Data'!M5 -> 3227.13 | N14: =H14/J14 -> 10.936524 | O14: =$H14/K14 -> 44.148729 | P14: =F14/L14 -> 69.086168
B15: ='Comps Data'!C6 -> Varun Beverages | C15: ='Comps Data'!D6 -> VBL | D15: ='Comps Data'!E6 -> 487.15 | E15: ='Comps Data'!F6 -> 338.2 | F15: =E15*D15 -> 164754.13 | G15: ='Comps Data'!H6 -> 2138.25 | H15: ='Comps Data'!J6 -> 164442.33 | J15: ='Comps Data'!K6 -> 21077.78 | K15: ='Comps Data'!L6 -> 5165.4 | L15: ='Comps Data'!M6 -> 2881.31 | N15: =H15/J15 -> 7.8016912 | O15: =$H15/K15 -> 31.835353 | P15: =F15/L15 -> 57.180286
B16: ='Comps Data'!C7 -> Britannia Inds. | C16: ='Comps Data'!D7 -> BRITANNIA | D16: ='Comps Data'!E7 -> 5824 | E16: ='Comps Data'!F7 -> 24.09 | F16: =E16*D16 -> 140300.16 | G16: ='Comps Data'!H7 -> 1246.51 | H16: ='Comps Data'!J7 -> 141234.19 | J16: ='Comps Data'!K7 -> 18314.59 | K16: ='Comps Data'!L7 -> 3403.93 | L16: ='Comps Data'!M7 -> 2193.11 | N16: =H16/J16 -> 7.7115671 | O16: =$H16/K16 -> 41.491508 | P16: =F16/L16 -> 63.973152
B17: ='Comps Data'!C8 -> Godrej Consumer | C17: ='Comps Data'!D8 -> GODREJCP | D17: ='Comps Data'!E8 -> 1242.6 | E17: ='Comps Data'!F8 -> 102.31 | F17: =E17*D17 -> 127130.41 | G17: ='Comps Data'!H8 -> 4009.19 | H17: ='Comps Data'!J8 -> 130656.54 | J17: ='Comps Data'!K8 -> 14694.57 | K17: ='Comps Data'!L8 -> 3234.21 | L17: ='Comps Data'!M8 -> 1853.97 | N17: =H17/J17 -> 8.8914841 | O17: =$H17/K17 -> 40.398285 | P17: =F17/L17 -> 68.571987
B18: ='Comps Data'!C9 -> Tata Consumer | C18: ='Comps Data'!D9 -> TATACONSUM | D18: ='Comps Data'!E9 -> 1065.4 | E18: ='Comps Data'!F9 -> 98.95 | F18: =E18*D18 -> 105421.33 | G18: ='Comps Data'!H9 -> 2392.68 | H18: ='Comps Data'!J9 -> 104996.15 | J18: ='Comps Data'!K9 -> 18045.14 | K18: ='Comps Data'!L9 -> 2626.15 | L18: ='Comps Data'!M9 -> 1329.6 | N18: =H18/J18 -> 5.8185279 | O18: =$H18/K18 -> 39.981018 | P18: =F18/L18 -> 79.288004
B19: ='Comps Data'!C10 -> United Spirits | C19: ='Comps Data'!D10 -> MCDOWELL-N | D19: ='Comps Data'!E10 -> 1311 | E19: ='Comps Data'!F10 -> 72.74 | F19: =E19*D19 -> 95362.14 | G19: ='Comps Data'!H10 -> 480 | H19: ='Comps Data'!J10 -> 93812.14 | J19: ='Comps Data'!K10 -> 12329 | K19: ='Comps Data'!L10 -> 2456 | L19: ='Comps Data'!M10 -> 1514 | N19: =H19/J19 -> 7.6090632 | O19: =$H19/K19 -> 38.197125 | P19: =F19/L19 -> 62.986882
B20: ='Comps Data'!C11 -> Marico | C20: ='Comps Data'!D11 -> MARICO | D20: ='Comps Data'!E11 -> 725.85 | E20: ='Comps Data'!F11 -> 129.79 | F20: =E20*D20 -> 94208.071 | G20: ='Comps Data'!H11 -> 554 | H20: ='Comps Data'!J11 -> 93985.071 | J20: ='Comps Data'!K11 -> 11447 | K20: ='Comps Data'!L11 -> 2395 | L20: ='Comps Data'!M11 -> 1697 | N20: =H20/J20 -> 8.2104544 | O20: =$H20/K20 -> 39.242201 | P20: =F20/L20 -> 55.514479
B21: ='Comps Data'!C12 -> Dabur India | C21: ='Comps Data'!D12 -> DABUR | D21: ='Comps Data'!E12 -> 521.1 | E21: ='Comps Data'!F12 -> 177.37 | F21: =E21*D21 -> 92427.507 | G21: ='Comps Data'!H12 -> 950.37 | H21: ='Comps Data'!J12 -> 92799.867 | J21: ='Comps Data'!K12 -> 12618.56 | K21: ='Comps Data'!L12 -> 2894.15 | L21: ='Comps Data'!M12 -> 1754.36 | N21: =H21/J21 -> 7.3542359 | O21: =$H21/K21 -> 32.064636 | P21: =F21/L21 -> 52.684459
B23: High | N23: =MAX(N12:N21) -> 10.936524 | O23: =MAX(O12:O21) -> 44.148729 | P23: =MAX(P12:P21) -> 79.288004
B24: 75th Percentile | N24: =QUARTILE(N12:N21,3) -> 8.7212267 | O24: =QUARTILE(O12:O21,3) -> 40.293968 | P24: =QUARTILE(P12:P21,3) -> 67.422278
B25: Average | N25: =AVERAGE(N12:N21) -> 8.0463708 | O25: =AVERAGE(O12:O21) -> 35.764771 | P25: =AVERAGE(P12:P21) -> 58.158058
B26: Median | N26: =MEDIAN(N12:N21) -> 7.7566291 | O26: =MEDIAN(O12:O21) -> 38.960076 | P26: =MEDIAN(P12:P21) -> 60.354003
B27: 25th Percentile | N27: =QUARTILE(N12:N21,) -> 5.8185279 | O27: =QUARTILE(O12:O21,) -> 11.610902 | P27: =QUARTILE(P12:P21,) -> 14.574036
B28: Low | N28: =MIN(N12:N21) -> 5.8185279 | O28: =MIN(O12:O21) -> 11.610902 | P28: =MIN(P12:P21) -> 14.574036
B30: Ambuja Cement Comparable Valuation | N30: =N10 -> EV / Revenue | O30: =O10 -> EV / EBITDA | P30: =P10 -> P/E
B32: Implied Enterprise Value | N32: =N26*J12 -> 613086.45 | O32: =O26*K12 -> 1709794.1 | P32: =P34+P33 -> 2125886.1
B33: Net Debt | N33: =$G$12 -> 284.54 | O33: =$G$12 -> 284.54 | P33: =$G$12 -> 284.54
B34: Implied Market Value | N34: =N32-N33 -> 612801.91 | O34: =O32-O33 -> 1709509.6 | P34: =P26*L12 -> 2125601.6
B35: Shares Outstanding | N35: =$E$12 -> 1252.67 | O35: =$E$12 -> 1252.67 | P35: =$E$12 -> 1252.67
B37: Implied Value Per Share | N37: =N34/N35 -> 489.1966 | O37: =O34/O35 -> 1364.6927 | P37: =P34/P35 -> 1696.8568
B39: Source: The Valuation School, Screener.in | N39: =IF(N37>$D$12,"Undervalued","Overvalued") -> Undervalued | O39: =IF(O37>$D$12,"Undervalued","Overvalued") -> Undervalued | P39: =IF(P37>$D$12,"Undervalued","Overvalued") -> Undervalued

Sheet VAR
B2: ='Data Sheet'!B1 -> ITC LTD
B3: (ITC | BSE Code: 540376)
B4: =CONCATENATE("INR"," ", 'Data Sheet'!B8) -> INR 409.75
B5: 52 Week (High - INR 410.45 & Low - INR 401.90)
B7: Date | C7: Adj. Price | D7: Return | E7: Sorted Returns | F7: Replication | G7: Simulated Returns | I7: ="Calculation of Value at Risk - " & 'Data Sheet'!B1&" (Simulation)" -> Calculation of Value at Risk - ITC LTD (Simulation)
B9: 39951 | C9: 68.53 | D9: =(C9-C10)/C10 -> -0.68227549 | E9: 0.11123723 | F9: 1 | G9: =_xlfn.NORM.INV(RAND(),$M$10,$M$11) -> 0.0041594296 | I9: Historical Approach
B10: 42430 | C10: 215.69 | D10: =(C10-C11)/C11 -> 2.9223495 | E10: 0.10045918 | F10: 2 | G10: =_xlfn.NORM.INV(RAND(),$M$10,$M$11) -> 0.022500525 | I10: Mean | M10: =AVERAGE(E9:E4966) -> 0.00068033167
B11: 39288 | C11: 54.99 | D11: =(C11-C12)/C12 -> 0.18334409 | E11: 0.089990089 | F11: 3 | G11: =_xlfn.NORM.INV(RAND(),$M$10,$M$11) -> 0.019060382 | I11: Std. Deviation | M11: =_xlfn.STDEV.S(E9:E4966) -> 0.017427485
B12: 38616 | C12: 46.47 | D12: =(C12-C13)/C13 -> -0.31832184 | E12: 0.089821764 | F12: 4 | G12: =_xlfn.NORM.INV(RAND(),$M$10,$M$11) -> -0.0091361537 | I12: Min | M12: =MIN(E9:E4966) -> -0.12486545
B13: 39937 | C13: 68.17 | D13: =(C13-C14)/C14 -> 0.28139098 | E13: 0.088629831 | F13: 5 | G13: =_xlfn.NORM.INV(RAND(),$M$10,$M$11) -> 0.010839158 | I13: Max | M13: =MAX(E9:E4966) -> 0.11123723
B14: 38877 | C14: 53.2 | D14: =(C14-C15)/C15 -> -0.6968661 | E14: 0.087045362 | F14: 6 | G14: =_xlfn.NORM.INV(RAND(),$M$10,$M$11) -> 0.013117869 | I14: CPM | M14: ='Data Sheet'!B8 -> 409.75
B15: 43910 | C15: 175.5 | D15: =(C15-C16)/C16 -> 1.581262 | E15: 0.084337349 | F15: 7 | G15: =_xlfn.NORM.INV(RAND(),$M$10,$M$11) -> -0.026304286
B16: 39402 | C16: 67.99 | D16: =(C16-C17)/C17 -> -0.39316316 | E16: 0.082643312 | F16: 8 | G16: =_xlfn.NORM.INV(RAND(),$M$10,$M$11) -> 0.034144123 | I16: Monte Carlo Simulation
B17: 40602 | C17: 112.04 | D17: =(C17-C18)/C18 -> -0.34746651 | E17: 0.081258444 | F17: 9 | G17: =_xlfn.NORM.INV(RAND(),$M$10,$M$11) -> -0.026788585 | I17: Mean | M17: =AVERAGE(G9:G4966) -> 0.00085604596
B18: 43921 | C18: 171.7 | D18: =(C18-C19)/C19 -> -0.091293993 | E18: 0.078517588 | F18: 10 | G18: =_xlfn.NORM.INV(RAND(),$M$10,$M$11) -> -0.032766104 | I18: Std. Deviation | M18: =_xlfn.STDEV.S(G9:G4966) -> 0.017516451
B19: 43972 | C19: 188.95 | D19: =(C19-C20)/C20 -> 0.16743899 | E19: 0.075106686 | F19: 11 | G19: =_xlfn.NORM.INV(RAND(),$M$10,$M$11) -> -0.0092165208 | I19: Min | M19: =MIN(G9:G4966) -> -0.075600571
B20: 43909 | C20: 161.85 | D20: =(C20-C21)/C21 -> -0.36492054 | E20: 0.073988056 | F20: 12 | G20: =_xlfn.NORM.INV(RAND(),$M$10,$M$11) -> 0.010706994 | I20: Max | M20: =MAX(G9:G4966) -> 0.066022196
B21: 43731 | C21: 254.85 | D21: =(C21-C22)/C22 -> 3.1819823 | E21: 0.070573409 | F21: 13 | G21: =_xlfn.NORM.INV(RAND(),$M$10,$M$11) -> 0.014917386 | I21: CPM | M21: =M14 -> 409.75
B22: 39638 | C22: 60.94 | D22: =(C22-C23)/C23 -> -0.657448 | E22: 0.070061457 | F22: 14 | G22: =_xlfn.NORM.INV(RAND(),$M$10,$M$11) -> -0.032251043
B23: 43924 | C23: 177.9 | D23: =(C23-C24)/C24 -> 2.1431095 | E23: 0.069110577 | F23: 15 | G23: =_xlfn.NORM.INV(RAND(),$M$10,$M$11) -> -0.0013822244 | I23: Percentile | J23: Confidence | K23: VAR% | L23: Stock Price | M23: VAR (INR)
B24: 39756 | C24: 56.6 | D24: =(C24-C25)/C25 -> -0.19154407 | E24: 0.068529356 | F24: 16 | G24: =_xlfn.NORM.INV(RAND(),$M$10,$M$11) -> -0.011462545 | I24: 0.05 | J24: =1-I24 -> 0.95 | K24: =_xlfn.PERCENTILE.INC(E9:E4966,I24) -> -0.026252153 | L24: =$M$14*(1-K24) -> 420.50682 | M24: =$M$14-L24 -> -10.75682
B25: 40001 | C25: 70.01 | D25: =(C25-C26)/C26 -> -0.69659805 | E25: 0.068365634 | F25: 17 | G25: =_xlfn.NORM.INV(RAND(),$M$10,$M$11) -> -0.019203165 | I25: 0.01 | J25: =1-I25 -> 0.99 | K25: =_xlfn.PERCENTILE.INC(E9:E4967,I25) -> -0.046484484 | L25: =$M$14*(1-K25) -> 428.79702 | M25: =$M$14-L25 -> -19.047017
B26: 44455 | C26: 230.75 | D26: =(C26-C27)/C27 -> 2.5725344 | E26: 0.068287037 | F26: 18 | G26: =_xlfn.NORM.INV(RAND(),$M$10,$M$11) -> -0.0091642696 | I26: 0.005 | J26: =1-I26 -> 0.995 | K26: =_xlfn.PERCENTILE.INC(E9:E4968,I26) -> -0.057279058 | L26: =$M$14*(1-K26) -> 433.22009 | M26: =$M$14-L26 -> -23.470094
B27: 39470 | C27: 64.59 | D27: =(C27-C28)/C28 -> -0.84324718 | E27: 0.065314201 | F27: 19 | G27: =_xlfn.NORM.INV(RAND(),$M$10,$M$11) -> 0.01608778 | I27: 0.1 | J27: =1-I27 -> 0.9 | K27: =_xlfn.PERCENTILE.INC(E10:E4969,I27) -> -0.018144219 | L27: =$M$14*(1-K27) -> 417.18459 | M27: =$M$14-L27 -> -7.4345937
B28: 45353 | C28: 412.05 | D28: =(C28-C29)/C29 -> 0.90808057 | E28: 0.06365678 | F28: 20 | G28: =_xlfn.NORM.INV(RAND(),$M$10,$M$11) -> -0.00043215142
B29: 44228 | C29: 215.95 | D29: =(C29-C30)/C30 -> -0.50746949 | E29: 0.062484625 | F29: 21 | G29: =_xlfn.NORM.INV(RAND(),$M$10,$M$11) -> 0.0071827683
B30: 45242 | C30: 438.45 | D30: =(C30-C31)/C31 -> 0.96888051 | E30: 0.061673689 | F30: 22 | G30: =_xlfn.NORM.INV(RAND(),$M$10,$M$11) -> 0.011060545
B31: 41527 | C31: 222.69 | D31: =(C31-C32)/C32 -> 2.0269131 | E31: 0.061641876 | F31: 23 | G31: =_xlfn.NORM.INV(RAND(),$M$10,$M$11) -> 0.02988539
B32: 39596 | C32: 73.57 | D32: =(C32-C33)/C33 -> -0.52960358 | E32: 0.061462992 | F32: 24 | G32: =_xlfn.NORM.INV(RAND(),$M$10,$M$11) -> -0.0072590849
B33: 43916 | C33: 156.4 | D33: =(C33-C34)/C34 -> -0.31985214 | E33: 0.061418392 | F33: 25 | G33: =_xlfn.NORM.INV(RAND(),$M$10,$M$11) -> 0.018851328
B34: 44231 | C34: 229.95 | D34: =(C34-C35)/C35 -> -0.24258893 | E34: 0.060899654 | F34: 26 | G34: =_xlfn.NORM.INV(RAND(),$M$10,$M$11) -> 0.0014173578
B35: 42877 | C35: 303.6 | D35: =(C35-C36)/C36 -> 3.8244081 | E35: 0.060796646 | F35: 27 | G35: =_xlfn.NORM.INV(RAND(),$M$10,$M$11) -> 0.00018288948
B36: 39651 | C36: 62.93 | D36: =(C36-C37)/C37 -> 0.061751308 | E36: 0.059427609 | F36: 28 | G36: =_xlfn.NORM.INV(RAND(),$M$10,$M$11) -> 0.032484458
B37: 39398 | C37: 59.27 | D37: =(C37-C38)/C38 -> -0.098966251 | E37: 0.059338695 | F37: 29 | G37: =_xlfn.NORM.INV(RAND(),$M$10,$M$11) -> -0.018138331
B38: 39472 | C38: 65.78 | D38: =(C38-C39)/C39 -> -0.80794161 | E38: 0.05840708 | F38: 30 | G38: =_xlfn.NORM.INV(RAND(),$M$10,$M$11) -> 0.025144759
B39: 42919 | C39: 342.5 | D39: =(C39-C40)/C40 -> 4.8727709 | E39: 0.058241928 | F39: 31 | G39: =_xlfn.NORM.INV(RAND(),$M$10,$M$11) -> 0.0078097552
... B4966: 42934 | C4966: 284.55 | D4966: =(C4966-C4967)/C4967 -> 8.5422535 | E4966: -0.12486545 | F4966: 4958 | G4966: =_xlfn.NORM.INV(RAND(),$M$10,$M$11) -> -0.020636788
B4967: 38446 | C4967: 29.82

Sheet DuPont Analysis
B2: ='Data Sheet'!B1 -> ITC LTD
B3: =CONCATENATE("(",VLOOKUP(B2,'List of Stocks'!B2:D5442,3,FALSE)," | ","BSE Code: ",VLOOKUP('DuPont Analysis'!B2,'List of Stocks'!B3:D5442,2,FALSE),")") -> (ITC | BSE Code: 540376)
B4: =CONCATENATE("INR"," ", 'Data Sheet'!B8) -> INR 409.75
B5: 52 Week (High - INR 410.45 & Low - INR 401.90)
B6: DuPont Analysis
B7: DuPont analysis breaks down Return on Equity (ROE) into three drivers profitability, efficiency, and leverage by expressing it as Net Profit Margin × Asset Turnover × Equity Multiplier. This helps reveal whether a company’s ROE is mainly fueled by strong margins, effective asset utilization, or higher financial leverage, giving a clearer picture of the true source of shareholder returns. In practice, it allows investors to pinpoint both strengths and weaknesses in a firm’s performance drivers.
B12: Financial Summary
B59: Return on Equity (ROE)
C60: ='Data Sheet'!D16 -> 43190 | D60: ='Data Sheet'!E16 -> 43555 | E60: ='Data Sheet'!F16 -> 43921 | F60: ='Data Sheet'!G16 -> 44286 | G60: ='Data Sheet'!H16 -> 44651 | H60: ='Data Sheet'!I16 -> 45016 | I60: ='Data Sheet'!J16 -> 45382 | J60: ='Data Sheet'!K16 -> 45747
B61: Net Profit | C61: ='Data Sheet'!D30 -> 11271.2 | D61: ='Data Sheet'!E30 -> 12592.33 | E61: ='Data Sheet'!F30 -> 15306.23 | F61: ='Data Sheet'!G30 -> 13161.19 | G61: ='Data Sheet'!H30 -> 15242.66 | H61: ='Data Sheet'!I30 -> 19191.66 | I61: ='Data Sheet'!J30 -> 20458.78 | J61: ='Data Sheet'!K30 -> 34746.63
B62: Average Shareholder Equity | C62: {=SUM('Data Sheet'!D57:D58+SUM('Data Sheet'!C57:C58))/2} -> 72667.985 | D62: {=SUM('Data Sheet'!E57:E58+SUM('Data Sheet'!D57:D58))/2} -> 82080.545 | E62: {=SUM('Data Sheet'!F57:F58+SUM('Data Sheet'!E57:E58))/2} -> 91777.5 | F62: {=SUM('Data Sheet'!G57:G58+SUM('Data Sheet'!F57:F58))/2} -> 95446.93 | G62: {=SUM('Data Sheet'!H57:H58+SUM('Data Sheet'!G57:G58))/2} -> 91575.125 | H62: {=SUM('Data Sheet'!I57:I58+SUM('Data Sheet'!H57:H58))/2} -> 97033.2 | I62: {=SUM('Data Sheet'!J57:J58+SUM('Data Sheet'!I57:I58))/2} -> 106408.76 | J62: {=SUM('Data Sheet'!K57:K58+SUM('Data Sheet'!J57:J58))/2} -> 109522.03
B63: Return on Equity | C63: =C61/C62 -> 0.15510544 | D63: =D61/D62 -> 0.15341431 | E63: =E61/E62 -> 0.16677541 | F63: =F61/F62 -> 0.13789013 | G63: =G61/G62 -> 0.16644979 | H63: =H61/H62 -> 0.19778447 | I63: =I61/I62 -> 0.19226594 | J63: =J61/J62 -> 0.31725701
B65: ROE - DuPont Equation
C66: 43190 | D66: 43555 | E66: 43921 | F66: 44286 | G66: 44651 | H66: 45016 | I66: 45382 | J66: 45747
B67: =B61 -> Net Profit | C67: =C61 -> 11271.2 | D67: =D61 -> 12592.33 | E67: =E61 -> 15306.23 | F67: =F61 -> 13161.19 | G67: =G61 -> 15242.66 | H67: =H61 -> 19191.66 | I67: =I61 -> 20458.78 | J67: =J61 -> 34746.63
B68: Revenue | C68: ='Data Sheet'!D17 -> 43448.94 | D68: ='Data Sheet'!E17 -> 48339.58 | E68: ='Data Sheet'!F17 -> 49387.7 | F68: ='Data Sheet'!G17 -> 49257.45 | G68: ='Data Sheet'!H17 -> 60644.54 | H68: ='Data Sheet'!I17 -> 70919.03 | I68: ='Data Sheet'!J17 -> 67931.94 | J68: ='Data Sheet'!K17 -> 75323.34
B69: Net Profit Margins (A) | C69: =C67/C68 -> 0.25941254 | D69: =D67/D68 -> 0.2604973 | E69: =E67/E68 -> 0.30991988 | F69: =F67/F68 -> 0.26719187 | G69: =G67/G68 -> 0.25134431 | H69: =H67/H68 -> 0.27061368 | I69: =I67/I68 -> 0.30116584 | J69: =J67/J68 -> 0.46129964
B71: Revenue | C71: =C68 -> 43448.94 | D71: =D68 -> 48339.58 | E71: =E68 -> 49387.7 | F71: =F68 -> 49257.45 | G71: =G68 -> 60644.54 | H71: =H68 -> 70919.03 | I71: =I68 -> 67931.94 | J71: =J68 -> 75323.34
B72: Average Total Assets | C72: ='Data Sheet'!D66+'Data Sheet'!C66/2 -> 92190.04 | D72: ='Data Sheet'!E66+'Data Sheet'!D66/2 -> 103859.48 | E72: ='Data Sheet'!F66+'Data Sheet'!E66/2 -> 113180.27 | F72: ='Data Sheet'!G66+'Data Sheet'!F66/2 -> 112416.13 | G72: ='Data Sheet'!H66+'Data Sheet'!G66/2 -> 114076.4 | H72: ='Data Sheet'!I66+'Data Sheet'!H66/2 -> 124428.97 | I72: ='Data Sheet'!J66+'Data Sheet'!I66/2 -> 134669.45 | J72: ='Data Sheet'!K66+'Data Sheet'!J66/2 -> 133879.68
B73: Asset Turnover Ratio (B) | C73: =C71/C72 -> 0.47129755 | D73: =D71/D72 -> 0.46543252 | E73: =E71/E72 -> 0.43636316 | F73: =F71/F72 -> 0.43817064 | G73: =G71/G72 -> 0.53161337 | H73: =H71/H72 -> 0.56995594 | I73: =I71/I72 -> 0.50443467 | J73: =J71/J72 -> 0.56261964
B75: Average Total Assets | C75: =C72 -> 92190.04 | D75: =D72 -> 103859.48 | E75: =E72 -> 113180.27 | F75: =F72 -> 112416.13 | G75: =G72 -> 114076.4 | H75: =H72 -> 124428.97 | I75: =I72 -> 134669.45 | J75: =J72 -> 133879.68
B76: =B62 -> Average Shareholder Equity | C76: =C62 -> 72667.985 | D76: =D62 -> 82080.545 | E76: =E62 -> 91777.5 | F76: =F62 -> 95446.93 | G76: =G62 -> 91575.125 | H76: =H62 -> 97033.2 | I76: =I62 -> 106408.76 | J76: =J62 -> 109522.03
B77: Equity Mutliplier (C) | C77: =C75/C76 -> 1.2686473 | D77: =D75/D76 -> 1.2653361 | E77: =E75/E76 -> 1.2332028 | F77: =F75/F76 -> 1.1777868 | G77: =G75/G76 -> 1.2457138 | H77: =H75/H76 -> 1.282334 | I77: =I75/I76 -> 1.2655861 | J77: =J75/J76 -> 1.2223996
B79: Return on Equity (A×B×C) | C79: =C77*C73*C69 -> 0.15510544 | D79: =D77*D73*D69 -> 0.15341431 | E79: =E77*E73*E69 -> 0.16677541 | F79: =F77*F73*F69 -> 0.13789013 | G79: =G77*G73*G69 -> 0.16644979 | H79: =H77*H73*H69 -> 0.19778447 | I79: =I77*I73*I69 -> 0.19226594 | J79: =J77*J73*J69 -> 0.31725701
B82: Return on Asset (ROA)
C83: ='Data Sheet'!D16 -> 43190 | D83: ='Data Sheet'!E16 -> 43555 | E83: ='Data Sheet'!F16 -> 43921 | F83: ='Data Sheet'!G16 -> 44286 | G83: ='Data Sheet'!H16 -> 44651 | H83: ='Data Sheet'!I16 -> 45016 | I83: ='Data Sheet'!J16 -> 45382 | J83: ='Data Sheet'!K16 -> 45747
B84: Net Profit | C84: =C61 -> 11271.2 | D84: =D61 -> 12592.33 | E84: =E61 -> 15306.23 | F84: =F61 -> 13161.19 | G84: =G61 -> 15242.66 | H84: =H61 -> 19191.66 | I84: =I61 -> 20458.78 | J84: =J61 -> 34746.63
B85: Average Total Assets | C85: =C72 -> 92190.04 | D85: =D72 -> 103859.48 | E85: =E72 -> 113180.27 | F85: =F72 -> 112416.13 | G85: =G72 -> 114076.4 | H85: =H72 -> 124428.97 | I85: =I72 -> 134669.45 | J85: =J72 -> 133879.68
B86: Return on Asset | C86: =C84/C85 -> 0.1222605 | D86: =D84/D85 -> 0.12124392 | E86: =E84/E85 -> 0.13523762 | F86: =F84/F85 -> 0.11707563 | G86: =G84/G85 -> 0.133618 | H86: =H84/H85 -> 0.15423788 | I86: =I84/I85 -> 0.15191849 | J86: =J84/J85 -> 0.25953624
B88: ROA - DuPont Equation
C89: 43190 | D89: 43555 | E89: 43921 | F89: 44286 | G89: 44651 | H89: 45016 | I89: 45382 | J89: 45747
B90: =B84 -> Net Profit | C90: =C61 -> 11271.2 | D90: =D61 -> 12592.33 | E90: =E61 -> 15306.23 | F90: =F61 -> 13161.19 | G90: =G61 -> 15242.66 | H90: =H61 -> 19191.66 | I90: =I61 -> 20458.78 | J90: =J61 -> 34746.63
B91: Revenue | C91: =C68 -> 43448.94 | D91: =D68 -> 48339.58 | E91: =E68 -> 49387.7 | F91: =F68 -> 49257.45 | G91: =G68 -> 60644.54 | H91: =H68 -> 70919.03 | I91: =I68 -> 67931.94 | J91: =J68 -> 75323.34
B92: Net Profit Margins (A) | C92: =C90/C91 -> 0.25941254 | D92: =D90/D91 -> 0.2604973 | E92: =E90/E91 -> 0.30991988 | F92: =F90/F91 -> 0.26719187 | G92: =G90/G91 -> 0.25134431 | H92: =H90/H91 -> 0.27061368 | I92: =I90/I91 -> 0.30116584 | J92: =J90/J91 -> 0.46129964
B94: Revenue | C94: =C91 -> 43448.94 | D94: =D91 -> 48339.58 | E94: =E91 -> 49387.7 | F94: =F91 -> 49257.45 | G94: =G91 -> 60644.54 | H94: =H91 -> 70919.03 | I94: =I91 -> 67931.94 | J94: =J91 -> 75323.34
B95: Average Total Assets | C95: =C85 -> 92190.04 | D95: =D85 -> 103859.48 | E95: =E85 -> 113180.27 | F95: =F85 -> 112416.13 | G95: =G85 -> 114076.4 | H95: =H85 -> 124428.97 | I95: =I85 -> 134669.45 | J95: =J85 -> 133879.68
B96: Asset Turnover Ratio (B) | C96: =C94/C95 -> 0.47129755 | D96: =D94/D95 -> 0.46543252 | E96: =E94/E95 -> 0.43636316 | F96: =F94/F95 -> 0.43817064 | G96: =G94/G95 -> 0.53161337 | H96: =H94/H95 -> 0.56995594 | I96: =I94/I95 -> 0.50443467 | J96: =J94/J95 -> 0.56261964
B98: Return on Asset (A×B) | C98: =C96*C92 -> 0.1222605 | D98: =D96*D92 -> 0.12124392 | E98: =E96*E92 -> 0.13523762 | F98: =F96*F92 -> 0.11707563 | G98: =G96*G92 -> 0.133618 | H98: =H96*H92 -> 0.15423788 | I98: =I96*I92 -> 0.15191849 | J98: =J96*J92 -> 0.25953624

Sheet Altman Z Score
B2: ='Data Sheet'!B1 -> ITC LTD
B3: =CONCATENATE("(",VLOOKUP(B2,'List of Stocks'!B2:D5442,3,FALSE)," | ","BSE Code: ",VLOOKUP('Altman Z Score'!B2,'List of Stocks'!B3:D5442,2,FALSE),")") -> (ITC | BSE Code: 540376)
B4: =CONCATENATE("INR"," ", 'Data Sheet'!B8) -> INR 409.75
B5: 52 Week (High - INR 410.45 & Low - INR 401.90)
B6: Altman's Z Score
B7: Altman’s Z Score is a financial model developed by Edward Altman in 1968 to predict a company’s likelihood of bankruptcy within two years by combining five key ratios working capital to total assets, retained earnings to total assets, EBIT to total assets, market value of equity to total liabilities, and sales to total assets into a weighted formula, where a score above 2.99 indicates financial safety, between 1.81 and 2.99 signals a grey zone of potential risk, and below 1.81 suggests high distress, making it a widely used tool for investors, creditors, and analysts to quickly assess corporate financial stability.
B12: Financial Summary
B60: Working Capital / Total Assets
C61: ='Data Sheet'!D16 -> 43190 | D61: ='Data Sheet'!E16 -> 43555 | E61: ='Data Sheet'!F16 -> 43921 | F61: ='Data Sheet'!G16 -> 44286 | G61: ='Data Sheet'!H16 -> 44651 | H61: ='Data Sheet'!I16 -> 45016 | I61: ='Data Sheet'!J16 -> 45382 | J61: ='Data Sheet'!K16 -> 45747
B62: Working Capital | C62: ='Data Sheet'!D65-'Data Sheet'!D60 -> 8460.88 | D62: ='Data Sheet'!E65-'Data Sheet'!E60 -> 10600.21 | E62: ='Data Sheet'!F65-'Data Sheet'!F60 -> 11917.56 | F62: ='Data Sheet'!G65-'Data Sheet'!G60 -> 8437.53 | G62: ='Data Sheet'!H65-'Data Sheet'!H60 -> 10406.87 | H62: ='Data Sheet'!I65-'Data Sheet'!I60 -> 11191.71 | I62: ='Data Sheet'!J65-'Data Sheet'!J60 -> 13015.41 | J62: ='Data Sheet'!K65-'Data Sheet'!K60 -> 12549.01
B63: Total Assets | C63: ='Data Sheet'!D61 -> 64240.88 | D63: ='Data Sheet'!E61 -> 71739.04 | E63: ='Data Sheet'!F61 -> 77310.75 | F63: ='Data Sheet'!G61 -> 73760.76 | G63: ='Data Sheet'!H61 -> 77196.02 | H63: ='Data Sheet'!I61 -> 85830.96 | I63: ='Data Sheet'!J61 -> 91753.97 | J63: ='Data Sheet'!K61 -> 88002.7
B64: Working Capital / Total Assets (A) | C64: =C62/C63 -> 0.13170554 | D64: =D62/D63 -> 0.14776069 | E64: =E62/E63 -> 0.1541514 | F64: =F62/F63 -> 0.1143905 | G64: =G62/G63 -> 0.13481097 | H64: =H62/H63 -> 0.13039246 | I64: =I62/I63 -> 0.14185119 | J64: =J62/J63 -> 0.14259801
B66: Retained Earnings / Total Assets
C67: 43190 | D67: 43555 | E67: 43921 | F67: 44286 | G67: 44651 | H67: 45016 | I67: 45382 | J67: 45747
B68: Retained Earnings | C68: =HistoricalFS!E43*HistoricalFS!E45*HistoricalFS!E51 -> 2967.66 | D68: =HistoricalFS!F43*HistoricalFS!F45*HistoricalFS!F51 -> 3706.76 | E68: =HistoricalFS!G43*HistoricalFS!G45*HistoricalFS!G51 -> 698.88 | F68: =HistoricalFS!H43*HistoricalFS!H45*HistoricalFS!H51 -> 0 | G68: =HistoricalFS!I43*HistoricalFS!I45*HistoricalFS!I51 -> 0 | H68: =HistoricalFS!J43*HistoricalFS!J45*HistoricalFS!J51 -> 0 | I68: =HistoricalFS!K43*HistoricalFS!K45*HistoricalFS!K51 -> 254.45 | J68: =HistoricalFS!L43*HistoricalFS!L45*HistoricalFS!L51 -> 0
B69: Total Assets | C69: =C63 -> 64240.88 | D69: =D63 -> 71739.04 | E69: =E63 -> 77310.75 | F69: =F63 -> 73760.76 | G69: =G63 -> 77196.02 | H69: =H63 -> 85830.96 | I69: =I63 -> 91753.97 | J69: =J63 -> 88002.7
B70: Retained Earnings / Total Assets (B) | C70: =C68/C69 -> 0.046195818 | D70: =D68/D69 -> 0.051670053 | E70: =E68/E69 -> 0.0090398813 | F70: =F68/F69 -> 0 | G70: =G68/G69 -> 0 | H70: =H68/H69 -> 0 | I70: =I68/I69 -> 0.002773177 | J70: =J68/J69 -> 0
B72: EBIT / Total Assets
C73: 43190 | D73: 43555 | E73: 43921 | F73: 44286 | G73: 44651 | H73: 45016 | I73: 45382 | J73: 45747
B74: EBIT | C74: =HistoricalFS!E31 -> 15284.31 | D74: =HistoricalFS!F31 -> 17140.78 | E74: =HistoricalFS!G31 -> 17698.63 | F74: =HistoricalFS!H31 -> 15419.19 | G74: =HistoricalFS!I31 -> 18890.74 | H74: =HistoricalFS!J31 -> 23895.25 | I74: =HistoricalFS!K31 -> 23669.48 | J74: =HistoricalFS!L31 -> 24193.13
B75: Total Assets | C75: =C69 -> 64240.88 | D75: =D69 -> 71739.04 | E75: =E69 -> 77310.75 | F75: =F69 -> 73760.76 | G75: =G69 -> 77196.02 | H75: =H69 -> 85830.96 | I75: =I69 -> 91753.97 | J75: =J69 -> 88002.7
B76: EBIT / Total Assets (C) | C76: =C74/C75 -> 0.23792187 | D76: =D74/D75 -> 0.23893239 | E76: =E74/E75 -> 0.22892845 | F76: =F74/F75 -> 0.20904326 | G76: =G74/G75 -> 0.24471132 | H76: =H74/H75 -> 0.27839896 | I76: =I74/I75 -> 0.25796682 | J76: =J74/J75 -> 0.2749135
B78: Market Cap. / Long-Term Liabilities
C79: ='Data Sheet'!D16 -> 43190 | D79: ='Data Sheet'!E16 -> 43555 | E79: ='Data Sheet'!F16 -> 43921 | F79: ='Data Sheet'!G16 -> 44286 | G79: ='Data Sheet'!H16 -> 44651 | H79: ='Data Sheet'!I16 -> 45016 | I79: ='Data Sheet'!J16 -> 45382 | J79: ='Data Sheet'!K16 -> 45747
B80: Market Cap. | C80: ='Data Sheet'!D93*'Data Sheet'!D90 -> 292292.99 | D80: ='Data Sheet'!E93*'Data Sheet'!E90 -> 341573.63 | E80: ='Data Sheet'!F93*'Data Sheet'!F90 -> 197842.96 | F80: ='Data Sheet'!G93*'Data Sheet'!G90 -> 252108.84 | G80: ='Data Sheet'!H93*'Data Sheet'!H90 -> 289548.26 | H80: ='Data Sheet'!I93*'Data Sheet'!I90 -> 446774.17 | I80: ='Data Sheet'!J93*'Data Sheet'!J90 -> 501298.16 | J80: ='Data Sheet'!K93*'Data Sheet'!K90 -> 512765.25
B81: Long-Term Liabilities | C81: ='Data Sheet'!D59 -> 35.92 | D81: ='Data Sheet'!E59 -> 13.44 | E81: ='Data Sheet'!F59 -> 277.45 | F81: ='Data Sheet'!G59 -> 270.83 | G81: ='Data Sheet'!H59 -> 249.44 | H81: ='Data Sheet'!I59 -> 306.04 | I81: ='Data Sheet'!J59 -> 303.43 | J81: ='Data Sheet'!K59 -> 284.54
B82: Market Cap. / Long-Term Liabilities (D) | C82: =C80/C81 -> 8137.3325 | D82: =D80/D81 -> 25414.705 | E82: =E80/E81 -> 713.07608 | F82: =F80/F81 -> 930.87487 | G82: =G80/G81 -> 1160.7932 | H82: =H80/H81 -> 1459.8555 | I82: =I80/I81 -> 1652.1048 | J82: =J80/J81 -> 1802.0849
B84: Sales / Total Assets
C85: 43190 | D85: 43555 | E85: 43921 | F85: 44286 | G85: 44651 | H85: 45016 | I85: 45382 | J85: 45747
B86: Total Sales | C86: ='Data Sheet'!D17 -> 43448.94 | D86: ='Data Sheet'!E17 -> 48339.58 | E86: ='Data Sheet'!F17 -> 49387.7 | F86: ='Data Sheet'!G17 -> 49257.45 | G86: ='Data Sheet'!H17 -> 60644.54 | H86: ='Data Sheet'!I17 -> 70919.03 | I86: ='Data Sheet'!J17 -> 67931.94 | J86: ='Data Sheet'!K17 -> 75323.34
B87: =B75 -> Total Assets | C87: =C69 -> 64240.88 | D87: =D69 -> 71739.04 | E87: =E69 -> 77310.75 | F87: =F69 -> 73760.76 | G87: =G69 -> 77196.02 | H87: =H69 -> 85830.96 | I87: =I69 -> 91753.97 | J87: =J69 -> 88002.7
B88: Sales / Total Assets (E) | C88: =C86/C87 -> 0.6763441 | D88: =D86/D87 -> 0.6738253 | E88: =E86/E87 -> 0.6388206 | F88: =F86/F87 -> 0.6678002 | G88: =G86/G87 -> 0.78559154 | H88: =H86/H87 -> 0.82626397 | I88: =I86/I87 -> 0.74037058 | J88: =J86/J87 -> 0.85592078
B90: Altman's Z Score
C91: 43190 | D91: 43555 | E91: 43921 | F91: 44286 | G91: 44651 | H91: 45016 | I91: 45382 | J91: 45747
B92: Final Score | C92: =(C64*1.2)+(C70*1.4)+(C76*3.3)+(C82*0.6)+(C88*1) -> 4884.0837 | D92: ='Data Sheet'!E24 -> 1039.85 | E92: ='Data Sheet'!F24 -> 1225.13 | F92: ='Data Sheet'!G24 -> 1074.39 | G92: ='Data Sheet'!H24 -> 1109.95 | H92: ='Data Sheet'!I24 -> 1308.56 | I92: ='Data Sheet'!J24 -> 1765.97 | J92: ='Data Sheet'!K24 -> 2221.39
B93: Financial Health | C93: =IF(C92<1.81,"Distressed",IF(C92>3,"Strong","Grey Zone")) -> Strong | D93: =IF(D92<1.81,"Distressed",IF(D92>3,"Strong","Grey Zone")) -> Strong | E93: =IF(E92<1.81,"Distressed",IF(E92>3,"Strong","Grey Zone")) -> Strong | F93: =IF(F92<1.81,"Distressed",IF(F92>3,"Strong","Grey Zone")) -> Strong | G93: =IF(G92<1.81,"Distressed",IF(G92>3,"Strong","Grey Zone")) -> Strong | H93: =IF(H92<1.81,"Distressed",IF(H92>3,"Strong","Grey Zone")) -> Strong | I93: =IF(I92<1.81,"Distressed",IF(I92>3,"Strong","Grey Zone")) -> Strong | J93: =IF(J92<1.81,"Distressed",IF(J92>3,"Strong","Grey Zone")) -> Strong

Sheet Summary
B2: ='Data Sheet'!B1 -> ITC LTD
B3: (ITC | BSE Code: 540376)
B4: =CONCATENATE("INR"," ", 'Data Sheet'!B9) -> INR 513280.01
B5: 52 Week (High - INR 410.45 & Low - INR 401.90)
B7: ="Valuation Summary "&" - "&'Data Sheet'!B1 -> Valuation Summary - ITC LTD
B9: This report presents an independent valuation of ITC Ltd., one of India’s largest diversified FMCG players. The analysis combines the Discounted Cash Flow (DCF) approach with market multiple comparisons, offering a dual perspective: one rooted in company fundamentals and the other benchmarked against peer valuations in the FMCG space.
B13: Core Assumptions:
B20: Valuation Outcomes:
B22: 1. DCF Valuation Output
B31: 2. Relative Valuation (Market Multiples)
B40: 3. Value at Risk (VaR) - Monte Carlo Simulation
B48: 4. DuPont Analysis
B57: 5. Altman’s Z-Score (Financial Health)
B63: Sources:
B69: Limitations:

Sheet Data>

Sheet Data Sheet
A1: COMPANY NAME | B1: ITC LTD | E1: =IF(B2<>B3, "A NEW VERSION OF THE WORKSHEET IS AVAILABLE", "")
A2: LATEST VERSION | B2: 2.1 | E2: PLEASE DO NOT MAKE ANY CHANGES TO THIS SHEET
A3: CURRENT VERSION | B3: 2.1
A5: META
A6: Number of shares | B6: =IF(B9>0, B9/B8, 0) -> 1252.6663
A7: Face Value | B7: 1
A8: Current Price | B8: 409.75
A9: Market Capitalization | B9: 513280.01
A15: PROFIT & LOSS
A16: Report Date | B16: 42460 | C16: 42825 | D16: 43190 | E16: 43555 | F16: 43921 | G16: 44286 | H16: 44651 | I16: 45016 | J16: 45382 | K16: 45747
A17: Sales | B17: 39192.1 | C17: 42767.6 | D17: 43448.94 | E17: 48339.58 | F17: 49387.7 | G17: 49257.45 | H17: 60644.54 | I17: 70919.03 | J17: 67931.94 | K17: 75323.34
A18: Raw Material Cost | B18: 13763.88 | C18: 15456.59 | D18: 14827.72 | E18: 17623.52 | F18: 18048.6 | G18: 20776.71 | H18: 27071.07 | I18: 29364.36 | J18: 27348.57 | K18: 32704.37
A19: Change in Inventory | B19: 195.38 | C19: -592.57 | D19: -1027.76 | E19: 203.19 | F19: 703.13 | G19: 645.27 | H19: 686 | I19: 358.59 | J19: 367.77 | K19: 725.65
A20: Power and Fuel | B20: 571.88 | C20: 584.33 | D20: 653.5 | E20: 746.73 | F20: 780.85 | G20: 699.56 | H20: 889.77 | I20: 1232.34 | J20: 952.9 | K20: 975.35
A21: Other Mfr. Exp | B21: 1581.59 | C21: 1683.9 | D21: 1697.62 | E21: 1871.01 | F21: 1908.29 | G21: 1587.18 | H21: 1887.67 | I21: 2327.8 | J21: 2183.76 | K21: 2345.36
A22: Employee Cost | B22: 3440.97 | C22: 3631.73 | D22: 3760.9 | E22: 4177.88 | F22: 4295.79 | G22: 4463.33 | H22: 4890.55 | I22: 5736.22 | J22: 5548.53 | K22: 6169.78
A23: Selling and admin | B23: 4261.78 | C23: 4179.74 | D23: 3954.87 | E23: 4546.39 | F23: 4488.63 | G23: 4236.77 | H23: 4858.38 | I23: 5604.08 | J23: 5312.45 | K23: 5793.29
A24: Other Expenses | B24: 1235.89 | C24: 1169.23 | D24: 1005.98 | E24: 1039.85 | F24: 1225.13 | G24: 1074.39 | H24: 1109.95 | I24: 1308.56 | J24: 1765.97 | K24: 2221.39
A25: Other Income | B25: 1483.11 | C25: 1758.63 | D25: 2239.81 | E25: 2080.44 | F25: 2417.32 | G25: 2576.95 | H25: 1909.72 | I25: 2097.64 | J25: 3330.45 | K25: 17794.88
A26: Depreciation | B26: 1077.4 | C26: 1152.79 | D26: 1236.28 | E26: 1396.61 | F26: 1644.91 | G26: 1645.59 | H26: 1732.41 | I26: 1809.01 | J26: 1518.05 | K26: 1646.32
A27: Interest | B27: 78.13 | C27: 49.03 | D27: 115.01 | E27: 71.4 | F27: 81.38 | G27: 57.97 | H27: 59.99 | I27: 77.77 | J27: 39.11 | K27: 45.06
... A31: Dividend Amount | B31: 6840.12 | C31: 5770.02 | D31: 6285.21 | E31: 7048.7 | F31: 12476.58 | G31: 13231.96 | H31: 14171.8 | I31: 19263.4 | J31: 17166.46 | K31: 17957.73
A40: Quarters
A41: Report Date | B41: 45016 | C41: 45107 | D41: 45199 | E41: 45291 | F41: 45382 | G41: 45473 | H41: 45565 | I41: 45657 | J41: 45747 | K41: 45838
A42: Sales | B42: 17634.89 | C42: 17164.46 | D42: 17774.47 | E42: 17195.24 | F42: 17037.8 | G42: 17777.81 | H42: 19990.36 | I42: 18790.17 | J42: 18765 | K42: 21494.79
A43: Expenses | B43: 11010.89 | C43: 10494.39 | D43: 11320.23 | E43: 10985.01 | F43: 10735.73 | G43: 11232.97 | H43: 13438.28 | I43: 12428.27 | J43: 12245.61 | K43: 14678.32
A44: Other Income | B44: 682.52 | C44: 722.3 | D44: 673.5 | E44: 820.26 | F44: 868 | G44: 771.13 | H44: 690.31 | I44: 803.4 | J44: 15391.28 | K44: 750.97
A45: Depreciation | B45: 461.4 | C45: 442.46 | D45: 453.04 | E45: 384.04 | F45: 385.09 | G45: 403.13 | H45: 416.18 | I45: 415.98 | J45: 411.03 | K45: 422.96
A46: Interest | B46: 12.15 | C46: 9.9 | D46: 9.87 | E46: 11.94 | F46: 10.72 | G46: 9.6 | H46: 14.73 | I46: 9.82 | J46: 10.91 | K46: 16.47
A47: Profit before tax | B47: 6832.97 | C47: 6940.01 | D47: 6664.83 | E47: 6634.51 | F47: 6774.26 | G47: 6903.24 | H47: 6811.48 | I47: 6739.5 | J47: 21488.73 | K47: 7128.01
A48: Tax | B48: 1607.95 | C48: 1759.89 | D48: 1700.31 | E48: 1227.99 | F48: 1583.55 | G48: 1726.25 | H48: 1757.05 | I48: 1726.32 | J48: 1680.85 | K48: 1784.6
A49: Net profit | B49: 5175.48 | C49: 5104.93 | D49: 4898.07 | E49: 5335.23 | F49: 5120.55 | G49: 5091.59 | H49: 4992.87 | I49: 4934.8 | J49: 19727.37 | K49: 5244.2
A50: Operating Profit | B50: 6624 | C50: 6670.07 | D50: 6454.24 | E50: 6210.23 | F50: 6302.07 | G50: 6544.84 | H50: 6552.08 | I50: 6361.9 | J50: 6519.39 | K50: 6816.47
A55: BALANCE SHEET
A56: Report Date | B56: 42460 | C56: 42825 | D56: 43190 | E56: 43555 | F56: 43921 | G56: 44286 | H56: 44651 | I56: 45016 | J56: 45382 | K56: 45747
A57: Equity Share Capital | B57: 804.72 | C57: 1214.74 | D57: 1220.43 | E57: 1225.86 | F57: 1229.22 | G57: 1230.88 | H57: 1232.33 | I57: 1242.8 | J57: 1248.47 | K57: 1251.41
A58: Reserves | B58: 41874.8 | C58: 45198.19 | D58: 51289.68 | E58: 57915.01 | F58: 64044.04 | G58: 59116.46 | H58: 61223.24 | I58: 67912.46 | J58: 73258.53 | K58: 68778.64
A59: Borrowings | B59: 83.78 | C59: 45.72 | D59: 35.92 | E59: 13.44 | F59: 277.45 | G59: 270.83 | H59: 249.44 | I59: 306.04 | J59: 303.43 | K59: 284.54
A60: Other Liabilities | B60: 8888.04 | C60: 9439.67 | D60: 11694.85 | E60: 12584.73 | F60: 11760.04 | G60: 13142.59 | H60: 14491.01 | I60: 16369.66 | J60: 16943.54 | K60: 17688.11
A61: Total | B61: 51651.34 | C61: 55898.32 | D61: 64240.88 | E61: 71739.04 | F61: 77310.75 | G61: 73760.76 | H61: 77196.02 | I61: 85830.96 | J61: 91753.97 | K61: 88002.7
A62: Net Block | B62: 15106.63 | C62: 15893.48 | D62: 16523.96 | E62: 19374.19 | F62: 21713.34 | G62: 23298.48 | H62: 24231.59 | I62: 25851.27 | J62: 27820.22 | K62: 21954.85
A63: Capital Work in Progress | B63: 2559.72 | C63: 3729.89 | D63: 5508.33 | E63: 4136.42 | F63: 3256.46 | G63: 4011.29 | H63: 3225.54 | I63: 3003.3 | J63: 2860.78 | K63: 1090.91
A64: Investments | B64: 11747.59 | C64: 17581.38 | D64: 22052.86 | E64: 25043.49 | F64: 28663.35 | G64: 24870.87 | H64: 24841.01 | I64: 29415.02 | J64: 31114.02 | K64: 34719.82
A65: Other Assets | B65: 22237.4 | C65: 18693.57 | D65: 20155.73 | E65: 23184.94 | F65: 23677.6 | G65: 21580.12 | H65: 24897.88 | I65: 27561.37 | J65: 29958.95 | K65: 30237.12
A66: Total | B66: 51651.34 | C66: 55898.32 | D66: 64240.88 | E66: 71739.04 | F66: 77310.75 | G66: 73760.76 | H66: 77196.02 | I66: 85830.96 | J66: 91753.97 | K66: 88002.7
A67: Receivables | B67: 1917.18 | C67: 2474.29 | D67: 2682.29 | E67: 4035.28 | F67: 2562.48 | G67: 2501.7 | H67: 2461.9 | I67: 2956.17 | J67: 4025.82 | K67: 4719.67
... A70: No. of Equity Shares | B70: 8047206991 | C70: 12147383071 | D70: 12204294911 | E70: 12258631601 | F70: 12292231241 | G70: 12308844231 | H70: 12323255931 | I70: 12428017741 | J70: 12484700000 | K70: 12514119781
A71: New Bonus Shares | C71: 4026657100
A72: Face value | B72: 1 | C72: 1 | D72: 1 | E72: 1 | F72: 1 | G72: 1 | H72: 1 | I72: 1 | J72: 1 | K72: 1
A80: CASH FLOW:
A81: Report Date | B81: 42460 | C81: 42825 | D81: 43190 | E81: 43555 | F81: 43921 | G81: 44286 | H81: 44651 | I81: 45016 | J81: 45382 | K81: 45747
A82: Cash from Operating Activity | B82: 9799.04 | C82: 10627.31 | D82: 13169.4 | E82: 12583.41 | F82: 14689.66 | G82: 12526.97 | H82: 15775.51 | I82: 18877.55 | J82: 17178.86 | K82: 17627.04
A83: Cash from Investing Activity | B83: -3920.73 | C83: -3250.93 | D83: -7113.89 | E83: -5545.68 | F83: -6174.02 | G83: 5739.98 | H83: -2238.49 | I83: -5732.29 | J83: 1562.77 | K83: -563.84
A84: Cash from Financing Activity | B84: -5612.52 | C84: -7301.03 | D84: -6221.13 | E84: -6868.64 | F84: -8181.48 | G84: -18633.83 | H84: -13580.5 | I84: -13006.03 | J84: -18550.96 | K84: -17037.4
A85: Net Cash Flow | B85: 265.79 | C85: 75.35 | D85: -165.62 | E85: 169.09 | F85: 334.16 | G85: -366.88 | H85: -43.48 | I85: 139.23 | J85: 190.67 | K85: 25.8
A90: PRICE: | B90: 205.13 | C90: 262.75 | D90: 239.5 | E90: 278.64 | F90: 160.95 | G90: 204.82 | H90: 234.96 | I90: 359.49 | J90: 401.53 | K90: 409.75
A92: DERIVED:
A93: Adjusted Equity Shares in Cr | B93: 1207.08 | C93: 1214.74 | D93: 1220.43 | E93: 1225.86 | F93: 1229.22 | G93: 1230.88 | H93: 1232.33 | I93: 1242.8 | J93: 1248.47 | K93: 1251.41

Sheet Comps Data
B2: S.No. | C2: Name | D2: Ticker | E2: CMP (INR) | F2: No. Eq. Shares Cr. | G2: Market Capitalization | H2: Debt | I2: Cash at End | J2: Enterprise V. | K2: Sales | L2: EBITDA | M2: NP 12M Rs.Cr. | N2: ROE % | O2: ROCE %
B3: 1 | C3: ITC | D3: ITC | E3: 409.75 | F3: 1252.67 | G3: =F3*E3 -> 513281.53 | H3: 284.54 | I3: 4012.36 | J3: =G3+H3-I3 -> 509553.71 | K3: 79040.32 | L3: 43885.8 | M3: 35218.9 | N3: 0.2072 | O3: 0.2785
B4: 2 | C4: Hind. Unilever | D4: HINDUNILVR | E4: 2659.8 | F4: 234.96 | G4: =F4*E4 -> 624946.61 | H4: 1648 | I4: 7554 | J4: =G4+H4-I4 -> 619040.61 | K4: 63928 | L4: 16005 | M4: 10827 | N4: 0.2732 | O4: 0.3679
B5: 3 | C5: Nestle India | D5: NESTLEIND | E5: 1156.2 | F5: 192.83 | G5: =F5*E5 -> 222950.05 | H5: 1166.85 | I5: 95.65 | J5: =G5+H5-I5 -> 224021.25 | K5: 20483.77 | L5: 5074.24 | M5: 3227.13 | N5: 0.8302 | O5: 0.9566
B6: 4 | C6: Varun Beverages | D6: VBL | E6: 487.15 | F6: 338.2 | G6: =F6*E6 -> 164754.13 | H6: 2138.25 | I6: 2450.05 | J6: =G6+H6-I6 -> 164442.33 | K6: 21077.78 | L6: 5165.4 | M6: 2881.31 | N6: 0.2249 | O6: 0.2485 | R6: 100
B7: 5 | C7: Britannia Inds. | D7: BRITANNIA | E7: 5824 | F7: 24.09 | G7: =F7*E7 -> 140300.16 | H7: 1246.51 | I7: 312.48 | J7: =G7+H7-I7 -> 141234.19 | K7: 18314.59 | L7: 3403.93 | M7: 2193.11 | N7: 0.5294 | O7: 0.5299
B8: 6 | C8: Godrej Consumer | D8: GODREJCP | E8: 1242.6 | F8: 102.31 | G8: =F8*E8 -> 127130.41 | H8: 4009.19 | I8: 483.06 | J8: =G8+H8-I8 -> 130656.54 | K8: 14694.57 | L8: 3234.21 | M8: 1853.97 | N8: 0.1521 | O8: 0.1921
B9: 7 | C9: Tata Consumer | D9: TATACONSUM | E9: 1065.4 | F9: 98.95 | G9: =F9*E9 -> 105421.33 | H9: 2392.68 | I9: 2817.86 | J9: =G9+H9-I9 -> 104996.15 | K9: 18045.14 | L9: 2626.15 | M9: 1329.6 | N9: 0.0701 | O9: 0.0916
B10: 8 | C10: United Spirits | D10: MCDOWELL-N | E10: 1311 | F10: 72.74 | G10: =F10*E10 -> 95362.14 | H10: 480 | I10: 2030 | J10: =G10+H10-I10 -> 93812.14 | K10: 12329 | L10: 2456 | M10: 1514 | N10: 0.1974 | O10: 0.265
B11: 9 | C11: Marico | D11: MARICO | E11: 725.85 | F11: 129.79 | G11: =F11*E11 -> 94208.071 | H11: 554 | I11: 777 | J11: =G11+H11-I11 -> 93985.071 | K11: 11447 | L11: 2395 | M11: 1697 | N11: 0.1704 | O11: 0.2024
B12: 10 | C12: Dabur India | D12: DABUR | E12: 521.1 | F12: 177.37 | G12: =F12*E12 -> 92427.507 | H12: 950.37 | I12: 578.01 | J12: =G12+H12-I12 -> 92799.867 | K12: 12618.56 | L12: 2894.15 | M12: 1754.36 | N12: 0.4134 | O12: 0.4516
C24: ='Data Sheet'!B1 -> ITC LTD
C25: (ITC | BSE Code: 540376)
C26: =CONCATENATE("INR"," ", 'Data Sheet'!C29) -> INR 5549.09
C27: 52 Week (High - INR 410.45 & Low - INR 401.90)

Sheet Share price
B2: Date | C2: Price | D2: Vol.
B3: 45744 | C3: 409.75 | D3: 12.98
B4: 45743 | C4: 409.45 | D4: 18.64
B5: 45742 | C5: 407.35 | D5: 13.89
B6: 45741 | C6: 409.8 | D6: 20.34
B7: 45740 | C7: 410.9 | D7: 14.36
B8: 45737 | C8: 405.55 | D8: 25.3
B9: 45736 | C9: 403.95 | D9: 16.99
B10: 45735 | C10: 403.05 | D10: 12.83
B11: 45734 | C11: 409.1 | D11: 13.86
B12: 45733 | C12: 407.95 | D12: 5.26
B13: 45729 | C13: 412.05 | D13: 8.2
B14: 45728 | C14: 412.4 | D14: 13.84
... B1236: 43922 | C1236: 166.4 | D1236: 18.14

Sheet Input
B2: Description | C2: ITC Limited is an Indian conglomerate, headquartered in Kolkata. It has a presence across six business segments, namely FMCG, agribusiness, information technology, paper products, and packaging. It generates a plurality of its revenue from tobacco products. In terms of market capitalization, ITC is the second largest FMCG company in India and the third-largest tobacco company in the world. It employs 36,500 people at more than 60 locations across India.
C3: ='Data Sheet'!B81 -> 42460 | D3: ='Data Sheet'!C81 -> 42825 | E3: ='Data Sheet'!D81 -> 43190 | F3: ='Data Sheet'!E81 -> 43555 | G3: ='Data Sheet'!F81 -> 43921 | H3: ='Data Sheet'!G81 -> 44286 | I3: ='Data Sheet'!H81 -> 44651 | J3: ='Data Sheet'!I81 -> 45016 | ... L3: ='Data Sheet'!K81 -> 45747
B4: Market Capitalisation | C4: ='Data Sheet'!B90*'Data Sheet'!B93 -> 247608.32 | D4: ='Data Sheet'!C90*'Data Sheet'!C93 -> 319172.93 | E4: ='Data Sheet'!D90*'Data Sheet'!D93 -> 292292.99 | F4: ='Data Sheet'!E90*'Data Sheet'!E93 -> 341573.63 | G4: ='Data Sheet'!F90*'Data Sheet'!F93 -> 197842.96 | H4: ='Data Sheet'!G90*'Data Sheet'!G93 -> 252108.84 | I4: ='Data Sheet'!H90*'Data Sheet'!H93 -> 289548.26 | J4: ='Data Sheet'!I90*'Data Sheet'!I93 -> 446774.17 | ... L4: ='Data Sheet'!K90*'Data Sheet'!K93 -> 512765.25
B5: Debt | C5: ='Data Sheet'!B59 -> 83.78 | D5: ='Data Sheet'!C59 -> 45.72 | E5: ='Data Sheet'!D59 -> 35.92 | F5: ='Data Sheet'!E59 -> 13.44 | G5: ='Data Sheet'!F59 -> 277.45 | H5: ='Data Sheet'!G59 -> 270.83 | I5: ='Data Sheet'!H59 -> 249.44 | J5: ='Data Sheet'!I59 -> 306.04 | ... L5: ='Data Sheet'!K59 -> 284.54
B6: Cash | C6: ='Data Sheet'!B69 -> 6063.3 | D6: ='Data Sheet'!C69 -> 2967.4 | E6: ='Data Sheet'!D69 -> 2899.6 | F6: ='Data Sheet'!E69 -> 4152.03 | G6: ='Data Sheet'!F69 -> 7277.34 | H6: ='Data Sheet'!G69 -> 4659.02 | I6: ='Data Sheet'!H69 -> 4654.42 | J6: ='Data Sheet'!I69 -> 4880.19 | ... L6: ='Data Sheet'!K69 -> 4012.36
B7: EV | C7: =C4+C5-C6 -> 241628.8 | D7: =D4+D5-D6 -> 316251.25 | E7: =E4+E5-E6 -> 289429.31 | F7: =F4+F5-F6 -> 337435.04 | G7: =G4+G5-G6 -> 190843.07 | H7: =H4+H5-H6 -> 247720.65 | I7: =I4+I5-I6 -> 285143.28 | J7: =J4+J5-J6 -> 442200.02 | ... L7: =L4+L5-L6 -> 509037.43
B8: EBITDA | C8: =HistoricalFS!C22 -> 14531.49 | D8: =HistoricalFS!D22 -> 15469.51 | E8: =HistoricalFS!E22 -> 16520.59 | F8: =HistoricalFS!F22 -> 18537.39 | G8: =HistoricalFS!G22 -> 19343.54 | H8: =HistoricalFS!H22 -> 17064.78 | I8: =HistoricalFS!I22 -> 20623.15 | J8: =HistoricalFS!J22 -> 25704.26 | ... L8: =HistoricalFS!L22 -> 25839.45
B9: EV/EBITDA | C9: =C7/C8 -> 16.627944 | D9: =D7/D8 -> 20.443521 | E9: =E7/E8 -> 17.519308 | F9: =F7/F8 -> 18.202942 | G9: =G7/G8 -> 9.8659847 | H9: =H7/H8 -> 14.516487 | I9: =I7/I8 -> 13.826369 | J9: =J7/J8 -> 17.203375 | ... L9: =L7/L8 -> 19.70001
B10: EV/Sales | C10: =C7/'Data Sheet'!B17 -> 6.1652425 | D10: =D7/'Data Sheet'!C17 -> 7.3946458 | E10: =E7/'Data Sheet'!D17 -> 6.6613663 | F10: =F7/'Data Sheet'!E17 -> 6.9805125 | G10: =G7/'Data Sheet'!F17 -> 3.8641822 | H10: =H7/'Data Sheet'!G17 -> 5.0291002 | I10: =I7/'Data Sheet'!H17 -> 4.7018788 | J10: =J7/'Data Sheet'!I17 -> 6.2352802 | ... L10: =L7/'Data Sheet'!K17 -> 6.7580305
B11: Book Value | C11: =SUM('Data Sheet'!B57:B58) -> 42679.52 | D11: =SUM('Data Sheet'!C57:C58) -> 46412.93 | E11: =SUM('Data Sheet'!D57:D58) -> 52510.11 | F11: =SUM('Data Sheet'!E57:E58) -> 59140.87 | G11: =SUM('Data Sheet'!F57:F58) -> 65273.26 | H11: =SUM('Data Sheet'!G57:G58) -> 60347.34 | I11: =SUM('Data Sheet'!H57:H58) -> 62455.57 | J11: =SUM('Data Sheet'!I57:I58) -> 69155.26 | ... L11: =SUM('Data Sheet'!K57:K58) -> 70030.05
B12: Price to Book Value | C12: =C4/C11 -> 5.8015723 | D12: =D4/D11 -> 6.8768107 | E12: =E4/E11 -> 5.5664135 | F12: =F4/F11 -> 5.7755936 | G12: =G4/G11 -> 3.0309955 | H12: =H4/H11 -> 4.1776297 | I12: =I4/I11 -> 4.6360678 | J12: =J4/J11 -> 6.460451 | ... L12: =L4/L11 -> 7.3220746
B13: ='Ratio Analysis'!B27 -> Return on Capital Employed (%) | C13: ='Ratio Analysis'!C27 -> 0.31461767 | D13: ='Ratio Analysis'!D27 -> 0.30816048 | E13: ='Ratio Analysis'!E27 -> 0.29087469 | F13: ='Ratio Analysis'!F27 -> 0.28976384 | G13: ='Ratio Analysis'!G27 -> 0.26999906 | H13: ='Ratio Analysis'!H27 -> 0.25436581 | I13: ='Ratio Analysis'!I27 -> 0.30126365 | ... L13: ='Ratio Analysis'!L27 -> 0.34406984
B14: Price to Earning | C14: ='Data Sheet'!B90/HistoricalFS!C45 -> 30.882519 | D14: ='Data Sheet'!C90/HistoricalFS!D45 -> 36.608278 | E14: ='Data Sheet'!D90/HistoricalFS!E45 -> 31.58944 | F14: ='Data Sheet'!E90/HistoricalFS!F45 -> 31.758161 | G14: ='Data Sheet'!F90/HistoricalFS!G45 -> 15.016019 | H14: ='Data Sheet'!G90/HistoricalFS!H45 -> 23.330601 | I14: ='Data Sheet'!H90/HistoricalFS!I45 -> 21.300634 | J14: ='Data Sheet'!I90/HistoricalFS!J45 -> 25.707585 | ... L14: ='Data Sheet'!K90/HistoricalFS!L45 -> 29.712431
B16: Shareholder's name | C16: Shares Held | D16: Shareholding (%) | E16: Market Value
B17: Tobacco Manufacturers Ltd. | C17: 222.84959 | D17: 0.1781 | E17: =C17*'Data Sheet'!$B$8 -> 91312.618 | F17: 10000000
B18: Life Insurance Corporation of India | C18: 197.70109 | D18: 0.158 | E18: =C18*'Data Sheet'!$B$8 -> 81008.021 | F18: 100
B19: SUUTI | C19: 97.453143 | D19: 0.0779 | E19: =C19*'Data Sheet'!$B$8 -> 39931.425
B20: Myddleton Investment Company Ltd | C20: 48.631194 | D20: 0.0389 | E20: =C20*'Data Sheet'!$B$8 -> 19926.632
B21: SBI Mutual Funds | C21: 43.517441 | D21: 0.0348 | E21: =C21*'Data Sheet'!$B$8 -> 17831.272
B22: ICICI Prudential Mutual Funds | C22: 27.619721 | D22: 0.0221 | E22: =C22*'Data Sheet'!$B$8 -> 11317.181
B23: GQG Partners Equity Fund | C23: 26.390174 | D23: 0.0211 | E23: =C23*'Data Sheet'!$B$8 -> 10813.374
B24: General Insurance Corporation | C24: 21.708551 | D24: 0.0173 | E24: =C24*'Data Sheet'!$B$8 -> 8895.0787
B25: Goldman Sachs Trust II | C25: 20.70918 | D25: 0.0165 | E25: =C25*'Data Sheet'!$B$8 -> 8485.5863
B26: NPS Trust (various Pension Funds) | C26: 19.633872 | D26: 0.0157 | E26: =C26*'Data Sheet'!$B$8 -> 8044.9791
B28: Shareholding Pattern | C28: %
B29: FIIs | C29: 0.3798
B30: DIIs | C30: 0.4691
B31: Government | C31: 0.0004
B32: Public | C32: 0.1507
B39: Recent Updates

Sheet Raw CF
B1: ='Data Sheet'!B1 -> ITC LTD
B2: Particulars | C2: 41699 | D2: 42064 | E2: 42430 | F2: 42795 | G2: 43160 | H2: 43525 | I2: 43891 | J2: 44256 | K2: 44621 | L2: 44986 | M2: 45352 | N2: 45717
B3: Cash from Operating Activity - | C3: 7344 | D3: 9843 | E3: 9799 | F3: 10627 | G3: 13169 | H3: 12583 | I3: 14690 | J3: 12527 | K3: 15776 | L3: 18878 | M3: 17179 | N3: 17627
B4: Profit from operations | C4: 13172 | D4: 14261 | E4: 15154 | F4: 16075 | G4: 17433 | H4: 18862 | I4: 19416 | J4: 17326 | K4: 20857 | L4: 26052 | M4: 26635 | N4: 26719
B5: Receivables | C5: -1546 | D5: 558 | E5: -207 | F5: -870 | G5: -964 | H5: -755 | I5: 1411 | J5: -66 | K5: -732 | L5: -884 | M5: -934 | N5: -1023
B6: Inventory | C6: -755 | D6: -505 | E6: -693 | F6: 593 | G6: 602 | H6: -359 | I6: -508 | J6: -1460 | K6: -466 | L6: -1098 | M6: -2545 | N6: -2975
B7: Payables | C7: 456 | D7: -23 | E7: 622 | F7: 321 | G7: 2098 | H7: 639 | I7: -607 | J7: 1112 | K7: 1099 | L7: 1058 | M7: 141 | N7: 1256
B8: Working capital changes | C8: -1844 | D8: 31 | E8: -277 | F8: 44 | G8: 1736 | H8: -476 | I8: 296 | J8: -413 | K8: -100 | L8: -924 | M8: -3337 | N8: -2742
B9: Direct taxes | C9: -3984 | D9: -4449 | E9: -5078 | F9: -5492 | G9: -6000 | H9: -5803 | I9: -5023 | J9: -4387 | K9: -4982 | L9: -6250 | M9: -6120 | N9: -6350
B10: Cash from Investing Activity - | C10: -3254 | D10: -5275 | E10: -3921 | F10: -3251 | G10: -7114 | H10: -5546 | I10: -6174 | J10: 5740 | K10: -2238 | L10: -5732 | M10: 1563 | N10: -564
B11: Fixed assets purchased | C11: -2887 | D11: -3300 | E11: -2348 | F11: -3122 | G11: -2878 | H11: -3169 | I11: -2441 | J11: -1837 | K11: -2142 | L11: -2743 | M11: -3563 | N11: -2279
B12: Fixed assets sold | C12: 38 | D12: 9 | E12: 8 | F12: 50 | G12: 80 | H12: 28 | I12: 27 | J12: 3 | K12: 133 | L12: 49 | M12: 107 | N12: 175
B13: Investments purchased | C13: -94242 | D13: -98742 | E13: -154081 | F13: -85683 | G13: -98330 | H13: -94187 | I13: -79835 | J13: -57553 | K13: -69776 | L13: -80932 | M13: -75107 | N13: -66373
... B29: Net Cash Flow | C29: -32 | D29: -93 | E29: 266 | F29: 75 | G29: -166 | H29: 169 | I29: 334 | J29: -367 | K29: -43 | L29: 139 | M29: 191 | N29: 26

Sheet Raw Bs
B2: Particulars | C2: 42430 | D2: 42795 | E2: 43160 | F2: 43525 | G2: 43891 | H2: 44256 | I2: 44621 | J2: 44986 | K2: 45352 | L2: 45717
B4: Equity Capital | C4: 805 | D4: 1215 | E4: 1220 | F4: 1226 | G4: 1229 | H4: 1231 | I4: 1232 | J4: 1243 | K4: 1248 | L4: 1251
B5: Reserves | C5: 41875 | D5: 45198 | E5: 51290 | F5: 57915 | G5: 64044 | H5: 59116 | I5: 61223 | J5: 67912 | K5: 73259 | L5: 68779
B6: Borrowings -
B7: Long term Borrowings | C7: 27 | D7: 18 | E7: 12 | F7: 8 | G7: 6 | H7: 6 | I7: 5 | J7: 3 | K7: 2 | L7: 0
B8: Short term Borrowings | C8: 44 | D8: 19 | E8: 17 | F8: 2 | G8: 1 | H8: 4 | I8: 1 | J8: 35 | K8: 10 | L8: 91
B9: Lease Liabilities | C9: 0 | D9: 0 | E9: 0 | F9: 0 | G9: 268 | H9: 261 | I9: 244 | J9: 267 | K9: 292 | L9: 193
B10: Other Borrowings | C10: 13 | D10: 8 | E10: 7 | F10: 3 | G10: 2 | H10: 0 | I10: 0 | J10: 0 | K10: 0 | L10: 0
B11: Other Liabilities - | C11: 8888 | D11: 9440 | E11: 11695 | F11: 12585 | G11: 11760 | H11: 13143 | I11: 14491 | J11: 16370 | K11: 16944 | L11: 17688
B12: Non controlling int | C12: 261 | D12: 295 | E12: 334 | F12: 343 | G12: 377 | H12: 347 | I12: 366 | J12: 384 | K12: 383 | L12: 368
B13: Trade Payables | C13: 2339 | D13: 2659 | E13: 3496 | F13: 3510 | G13: 3630 | H13: 4319 | I13: 4417 | J13: 4659 | K13: 4798 | L13: 4807
B14: Advance from Customers | C14: 805 | D14: 495 | E14: 461 | F14: 430 | G14: 703 | H14: 811 | I14: 1278 | J14: 1295 | K14: 886 | L14: 1264
B15: Other liability items | C15: 5483 | D15: 5991 | E15: 7404 | F15: 8301 | G15: 7050 | H15: 7666 | I15: 8429 | J15: 10032 | K15: 10877 | L15: 11249
B16: Total Liabilities | C16: 51651 | D16: 55898 | E16: 64241 | F16: 71739 | G16: 77311 | H16: 73761 | I16: 77196 | J16: 85831 | K16: 91754 | L16: 88003
B18: Fixed Assets -
B19: Land | C19: 1615 | D19: 1673 | E19: 1685 | F19: 2021 | G19: 2797 | H19: 2889 | I19: 2829 | J19: 2830 | K19: 2865 | L19: 1588
B20: Building | C20: 4219 | D20: 4716 | E20: 5331 | F20: 6996 | G20: 8161 | H20: 8387 | I20: 9100 | J20: 9789 | K20: 10944 | L20: 7550
B21: Plant Machinery | C21: 9112 | D21: 10384 | E21: 11453 | F21: 13316 | G21: 14625 | H21: 15307 | I21: 16912 | J21: 18480 | K21: 20718 | L21: 19423
B22: Equipments | C22: 27 | D22: 32 | E22: 32 | F22: 34 | G22: 40 | H22: 41 | I22: 44 | J22: 44 | K22: 53 | L22: 63
B23: Furniture n fittings | C23: 413 | D23: 459 | E23: 497 | F23: 644 | G23: 810 | H23: 833 | I23: 907 | J23: 1000 | K23: 1068 | L23: 282
B24: Railway sidings | C24: 2 | D24: 2 | E24: 2 | F24: 2 | G24: 2 | H24: 2 | I24: 2 | J24: 2 | K24: 2 | L24: 2
B25: Vehicles | C25: 107 | D25: 128 | E25: 140 | F25: 161 | G25: 184 | H25: 180 | I25: 179 | J25: 189 | K25: 192 | L25: 141
B26: Intangible Assets | C26: 563 | D26: 563 | E26: 570 | F26: 684 | G26: 684 | H26: 2734 | I26: 2744 | J26: 3490 | K26: 3505 | L26: 3622
B27: Other fixed assets | C27: 117 | D27: 138 | E27: 212 | F27: 234 | G27: 663 | H27: 716 | I27: 719 | J27: 786 | K27: 841 | L27: 967
B28: Gross Block | C28: 16176 | D28: 18094 | E28: 19920 | F28: 24090 | G28: 27965 | H28: 31088 | I28: 33435 | J28: 36608 | K28: 40189 | L28: 33638
B29: Accumulated Depreciation | C29: 1069 | D29: 2201 | E29: 3396 | F29: 4716 | G29: 6252 | H29: 7790 | I29: 9204 | J29: 10757 | K29: 12368 | L29: 11683
B30: Net Block | C30: =C28-C29 -> 15107 | D30: =D28-D29 -> 15893 | E30: =E28-E29 -> 16524 | F30: =F28-F29 -> 19374 | G30: =G28-G29 -> 21713 | H30: =H28-H29 -> 23298 | I30: =I28-I29 -> 24231 | J30: =J28-J29 -> 25851 | ... L30: =L28-L29 -> 21955
B32: CWIP | C32: 2560 | D32: 3730 | E32: 5508 | F32: 4136 | G32: 3256 | H32: 4011 | I32: 3226 | J32: 3003 | K32: 2861 | L32: 1091
B33: Investments | C33: 11748 | D33: 17581 | E33: 22053 | F33: 25043 | G33: 28663 | H33: 24871 | I33: 24841 | J33: 29415 | K33: 31114 | L33: 34720
B35: Other Assets -
B36: Inventories | C36: 9062 | D36: 8116 | E36: 7495 | F36: 7860 | G36: 8879 | H36: 10397 | I36: 10864 | J36: 11771 | K36: 14153 | L36: 15638
B37: Trade receivables | C37: 1917 | D37: 2474 | E37: 2682 | F37: 4035 | G37: 2562 | H37: 2502 | I37: 2462 | J37: 2956 | K37: 4026 | L37: 4720
B38: Cash Equivalents | C38: 6063 | D38: 2967 | E38: 2900 | F38: 4152 | G38: 7277 | H38: 4659 | I38: 4654 | J38: 4880 | K38: 7218 | L38: 4012
B39: Loans n Advances | C39: 14 | D39: 7 | E39: 74 | F39: 67 | G39: 6 | H39: 7 | I39: 11 | J39: 13 | K39: 31 | L39: 10
B40: Other asset items | C40: 5180 | D40: 5129 | E40: 7004 | F40: 7071 | G40: 4952 | H40: 4015 | I40: 6906 | J40: 7941 | K40: 4531 | L40: 5858
B41: Total Assets | C41: 51651 | D41: 55898 | E41: 64241 | F41: 71739 | G41: 77311 | H41: 73761 | I41: 77196 | J41: 85831 | K41: 91754 | L41: 88003

Sheet List of Stocks
B2: COMPANY_NAME | C2: BSE | D2: NSE | E2: Industry
B3: 20 MICRONS LTD | C3: 533022 | D3: 20MICRONS | E3: Mining
B4: 21ST CENTURY MANAGEMENT SERVICES LTD | C4: 526921 | D4: 21STCENMGM | E4: Other Financial Services
B5: 3I INFOTECH LTD | C5: 532628 | D5: 3IINFOTECH | E5: IT Consulting & Software
B6: 3M (INDIA) LTD | C6: 523395 | D6: 3M(INDIA) | E6: Diversified
B7: 3M INDIA LTD | C7: 523395 | D7: 3MINDIA | E7: Diversified
B8: 3P LAND HOLDINGS LTD | C8: 516092 | D8: 3PLAND | E8: Paper & Paper Products
B9: 5PAISA CAPITAL LTD | C9: 540776 | D9: 5PAISA | E9: Other Financial Services
B10: 63 MOONS TECHNOLOGIES LTD | C10: 526881 | D10: 63MOONS | E10: IT Consulting & Software
B11: 7NR RETAIL LTD | C11: 540615 | D11: Not Listed | E11: Specialty Retail
B12: 7SEAS ENTERTAINMENT LTD | C12: 540874 | D12: Not Listed | E12: Movies & Entertainment
B13: 8K MILES SOFTWARE SERVICES LTD | C13: 512161 | D13: 8KMILES | E13: Internet Software & Services
B14: A & M FEBCON LTD | C14: 540697 | D14: Not Listed | E14: Industrial Machinery
B15: A AND M JUMBO BAGS LTD | C15: Not Listed | D15: AMJUMBO | E15: SME
B16: A INFRASTRUCTURE LTD | C16: 539620 | D16: Not Listed | E16: Cement & Cement Products
B17: A K SPINTEX LTD | C17: 539300 | D17: Not Listed | E17: Textiles
B18: A K CAPITAL SERVICES LTD | C18: 530499 | D18: Not Listed | E18: Finance (including NBFCs)
B19: A.F. Enterprises Ltd | C19: 538351 | D19: AFEL | E19: Investment Companies
B20: A-1 ACID LTD | C20: 542012 | D20: Not Listed | E20: Comm.Trading & Distribution
B21: A2Z INFRA ENGINEERING LTD | C21: 533292 | D21: A2ZINFRA | E21: Utilities:Non-Elec.
B22: AADHAAR VENTURES (INDIA) LTD | C22: 531611 | D22: Not Listed | E22: Finance (including NBFCs)
B23: AADHAAR VENTURES INDIA LTD | C23: 531611 | D23: Not Listed | E23: Finance (including NBFCs)
B24: AAKASH EXPLORATION SERVICES LTD | C24: Not Listed | D24: AAKASH | E24: SME
B25: AANANDA LAKSHMI SPINNING MILLS LTD | C25: 539096 | D25: Not Listed | E25: Textiles
B26: AANCHAL ISPAT LTD | C26: 538812 | D26: Not Listed | E26: Iron & Steel/Interm.Products
B27: AAR COMMERCIAL COMPANY LTD | C27: 539632 | D27: Not Listed | E27: Distributors
B28: Aar Shyam India Investment Company Ltd | C28: 542377 | D28: AARSHYAM | E28: Finance (including NBFCs)
B29: AAREY DRUGS & PHARMACEUTICALS LTD | C29: 524412 | D29: Not Listed | E29: Pharmaceuticals
B30: AARON INDUSTRIES LTD | C30: Not Listed | D30: AARON | E30: SME
B31: Aartech Solonics Ltd | C31: 542580 | D31: AARTECH | E31: Heavy Electrical Equipment
B32: AARTI DRUGS LTD | C32: 524348 | D32: AARTIDRUGS | E32: Pharmaceuticals
B33: AARTI INDUSTRIES LTD | C33: 524208 | D33: AARTIIND | E33: Commodity Chemicals
B34: AARV INFRATEL LTD | C34: 526488 | D34: Not Listed | E34: Textiles
B35: AARVEE DENIMS & EXPORTS LTD | C35: 514274 | D35: AARVEEDEN | E35: Textiles
B36: AARVI ENCON LTD | C36: Not Listed | D36: AARVI | E36: SME
B37: AASHEE INFOTECH LTD | C37: 519319 | D37: Not Listed | E37: Internet Software & Services
B38: AASWA TRADING & EXPORTS LTD | C38: 512038 | D38: Not Listed | E38: Comm.Trading & Distribution
B39: AAVAS FINANCIERS LTD | C39: 541988 | D39: AAVAS | E39: Housing Finance
B40: AAYUSH FOOD AND HERBS LTD | C40: 539528 | D40: Not Listed | E40: Packaged Foods
B41: ABAN OFFSHORE LTD | C41: 523204 | D41: ABAN | E41: Exploration & Production
B42: ABANS ENTERPRISES LTD | C42: 512165 | D42: Not Listed | E42: Comm.Trading & Distribution
B43: ABB INDIA LTD | C43: 500002 | D43: ABB | E43: Heavy Electrical Equipment
B44: ABBOTT (INDIA) LTD | C44: 500488 | D44: ABBOT(INDIA) | E44: Pharmaceuticals
B45: ABBOTT INDIA LTD | C45: 500488 | D45: ABBOTINDIA | E45: Pharmaceuticals
B46: ABC (INDIA) LTD | C46: 520123 | D46: Not Listed | E46: Surface Transportation
B47: ABC GAS INTERNATIONAL LTD | C47: 513119 | D47: Not Listed | E47: Copper
B48: ABC INDIA LTD | C48: 520123 | D48: Not Listed | E48: Surface Transportation
... B56: ABIRAMI FINANCIAL SERVICES INDIA LTD | C56: 511756 | D56: Not Listed | E56: Finance (including NBFCs)
B57: ABM INTERNATIONAL LTD | C57: Not Listed | D57: ABMINTLTD | E57: Others
B58: ABM KNOWLEDGEWARE LTD | C58: 531161 | D58: Not Listed | E58: IT Software Products
B59: ACC LTD | C59: 500410 | D59: ACC | E59: Cement & Cement Products
B60: ACCEL LTD | C60: 517494 | D60: Not Listed | E60: Storage Media & Peripherals
B61: ACCELYA KALE SOLUTIONS LTD | C61: 532268 | D61: ACCELYA | E61: IT Consulting & Software
B62: ACCORD SYNERGY LTD | C62: Not Listed | D62: ACCORD | E62: SME
B63: ACCURACY SHIPPING LTD | C63: Not Listed | D63: ACCURACY | E63: SME
B64: ACE EDUTREND LTD | C64: 530093 | D64: Not Listed | E64: Education
B65: ACE INTEGRATED SOLUTIONS LTD | C65: Not Listed | D65: ACEINTEG | E65: SME
B66: ACE MEN ENGG WORKS LTD | C66: 539661 | D66: Not Listed | E66: Distributors
B67: ACE SOFTWARE EXPORTS LTD | C67: 531525 | D67: Not Listed | E67: IT Software Products
B68: Achal Investments Ltd | C68: 538570 | D68: ACHAL | E68: Other Financial Services
B69: ACI INFOCOM LTD | C69: 517356 | D69: Not Listed | E69: Storage Media & Peripherals
B70: ACKNIT INDUSTRIES LTD | C70: 530043 | D70: Not Listed | E70: Other Apparels & Accessories
B71: ACME RESOURCES LTD | C71: 539391 | D71: Not Listed | E71: Finance (including NBFCs)
B72: ACROW INDIA LTD. | C72: 513149 | D72: ACROW | E72: Iron &amp; Steel Products
B73: ACRYSIL LTD | C73: 524091 | D73: Not Listed | E73: Plastic Products
B74: ACTION CONSTRUCTION EQUIPMENT LTD | C74: 532762 | D74: ACE | E74: Transport Related Services
B75: ACTION FINANCIAL SERVICES (INDIA) LTD | C75: 511706 | D75: Not Listed | E75: Other Financial Services
B76: ACTION FINANCIAL SERVICES INDIA LTD | C76: 511706 | D76: Not Listed | E76: Other Financial Services
B77: ACTIVE CLOTHING CO LTD | C77: 541144 | D77: Not Listed | E77: Other Apparels & Accessories
... B135: AGRI-TECH INDIA LTD | C135: 537292 | D135: AGRITECH | E135: Other Agricultural Products
B136: AGRO PHOS (INDIA) LTD | C136: Not Listed | D136: AGROPHOS | E136: SME
B137: AGRO PHOS INDIA LTD | C137: Not Listed | D137: AGROPHOS | E137: SME
B138: AGRO TECH FOODS LTD | C138: 500215 | D138: ATFL | E138: Other Agricultural Products
B139: AHIMSA INDUSTRIES LTD | C139: Not Listed | D139: AHIMSA | E139: SME
B140: AHLADA ENGINEERS LTD | C140: Not Listed | D140: AHLADA | E140: SME
B141: AHLUWALIA CONTRACTS (INDIA) LTD | C141: 532811 | D141: AHLUCONT | E141: Realty
B142: AHLUWALIA CONTRACTS INDIA LTD | C142: 532811 | D142: AHLUCONT | E142: Realty
B143: AHMEDABAD STEELCRAFT LTD | C143: 522273 | D143: Not Listed | E143: Iron & Steel/Interm.Products
B144: AI CHAMPDANY INDUSTRIES LTD | C144: 532806 | D144: Not Listed | E144: Jute & Jute Products
B145: AIA ENGINEERING LTD | C145: 532683 | D145: AIAENG | E145: Other Industrial Goods
B146: AIMCO PESTICIDES LTD | C146: 524288 | D146: Not Listed | E146: Agrochemicals
B147: AIRAN LTD | C147: Not Listed | D147: AIRAN | E147: SME
B148: AIRO LAM LTD | C148: Not Listed | D148: AIROLAM | E148: SME
B149: AISHWARYA TELECOM LTD | C149: 532975 | D149: Not Listed | E149: Telecom Equipment
B150: AJANTA PHARMA LTD | C150: 532331 | D150: AJANTPHARM | E150: Pharmaceuticals
B151: AJANTA SOYA LTD | C151: 519216 | D151: Not Listed | E151: Edible Oils
B152: AJCON GLOBAL SERVICES LTD | C152: 511692 | D152: Not Listed | E152: Other Financial Services
B153: AJEL LTD | C153: 530713 | D153: Not Listed | E153: IT Consulting & Software
B154: AJMERA REALTY & INFRA (INDIA) LTD | C154: 513349 | D154: AJMERA | E154: Realty
B155: AJMERA REALTY & INFRA INDIA LTD | C155: 513349 | D155: AJMERA | E155: Realty
B156: AJOONI BIOTECH LTD | C156: Not Listed | D156: AJOONI | E156: SME
B157: AJWA FUN WORLD & RESORT LTD | C157: 526628 | D157: Not Listed | E157: Other Leisure Facilities
B158: AKAR AUTO INDUSTRIES LTD | C158: 530621 | D158: Not Listed | E158: Industrial Machinery
B159: AKASH INFRA PROJECTS LTD | C159: Not Listed | D159: AKASH | E159: SME
B160: AKASHDEEP METAL INDUSTRIES LTD | C160: 538778 | D160: Not Listed | E160: Finance (including NBFCs)
B161: AKG EXIM LTD | C161: Not Listed | D161: AKG | E161: SME
B162: AKI (INDIA) LTD | C162: 542020 | D162: Not Listed | E162: Other Apparels & Accessories
B163: AKI INDIA LTD | C163: 542020 | D163: Not Listed | E163: Other Apparels & Accessories
B164: AKM LACE AND EMBROTEX LTD | C164: 540718 | D164: Not Listed | E164: Textiles
B165: AKME STAR HOUSING FINANCE LTD | C165: 539017 | D165: Not Listed | E165: Housing Finance
...
